Workbook

Sheet MATRIZ CARTA
E5: CARTA | K5: SUGERIDO COSTOS | N5: PRECIO FINAL
B6: ADICIONES | C6: DESCRIPCION | D6: COSTO | E6: VENTA | F6: ICO 8% | G6: BASE | H6: % | I6: RENTABILIDAD | J6: ROTACION | K6: PRECIO SUGERIDO | L6: ICO2 | M6: CARTA | N6: PRECIO N | O6: ICO 8%2 | P6: CARTA | Q6: % | R6: RATION
A7: 1 | B7: =+ADICIONES!A6 -> ACEITUNA | D7: =+ADICIONES!J9 -> 828.933 | E7: =+ADICIONES!J10 -> 4900 | F7: =+E7/1.08*0.08 -> 362.96296 | G7: =+Tabla551857211411[[#This Row],[VENTA]]-Tabla551857211411[[#This Row],[ICO 8%]] -> 4537.037 | H7: =+Tabla551857211411[[#This Row],[COSTO]]/Tabla551857211411[[#This Row],[BASE]] -> 0.1827036 | I7: =+Tabla551857211411[[#This Row],[BASE]]/Tabla551857211411[[#This Row],[COSTO]] -> 5.4733459 | J7: =+VLOOKUP(Tabla551857211411[[#This Row],[ADICIONES]],Tabla77[#All],3,0) -> #N/A | K7: =+D7/(100-70)*100 -> 2763.11 | L7: =+K7/1.08*0.08 -> 204.67481 | M7: =+Tabla551857211411[[#This Row],[PRECIO SUGERIDO]]+Tabla551857211411[[#This Row],[ICO2]] -> 2967.7848 | O7: =+N7/1.08*0.08 -> 0 | P7: =+Tabla551857211411[[#This Row],[PRECIO N]]-Tabla551857211411[[#This Row],[ICO 8%2]] -> 0 | Q7: =+Tabla551857211411[[#This Row],[COSTO]]/Tabla551857211411[[#This Row],[CARTA]] -> #DIV/0! | R7: =+Tabla551857211411[[#This Row],[PRECIO N]]/Tabla551857211411[[#This Row],[COSTO]] -> 0
A8: 2 | B8: =+ADICIONES!A18 -> ADICION CANCHA Y CHIPS | D8: =+ADICIONES!J21 -> 986.50335 | E8: =+ADICIONES!J22 -> 4900 | F8: =+E8/1.08*0.08 -> 362.96296 | G8: =+Tabla551857211411[[#This Row],[VENTA]]-Tabla551857211411[[#This Row],[ICO 8%]] -> 4537.037 | H8: =+Tabla551857211411[[#This Row],[COSTO]]/Tabla551857211411[[#This Row],[BASE]] -> 0.21743339 | I8: =+Tabla551857211411[[#This Row],[BASE]]/Tabla551857211411[[#This Row],[COSTO]] -> 4.5991096 | J8: =+VLOOKUP(Tabla551857211411[[#This Row],[ADICIONES]],Tabla77[#All],3,0) -> 50 | K8: =+D8/(100-70)*100 -> 3288.3445 | L8: =+K8/1.08*0.08 -> 243.58108 | M8: =+Tabla551857211411[[#This Row],[PRECIO SUGERIDO]]+Tabla551857211411[[#This Row],[ICO2]] -> 3531.9256 | O8: =+N8/1.08*0.08 -> 0 | P8: =+Tabla551857211411[[#This Row],[PRECIO N]]-Tabla551857211411[[#This Row],[ICO 8%2]] -> 0 | Q8: =+Tabla551857211411[[#This Row],[COSTO]]/Tabla551857211411[[#This Row],[CARTA]] -> #DIV/0! | R8: =+Tabla551857211411[[#This Row],[PRECIO N]]/Tabla551857211411[[#This Row],[COSTO]] -> 0
A9: 3 | B9: =+ADICIONES!A30 -> AGUACATE | D9: =+ADICIONES!J33 -> 2778.3 | E9: =+ADICIONES!J34 -> 2500 | F9: =+E9/1.08*0.08 -> 185.18519 | G9: =+Tabla551857211411[[#This Row],[VENTA]]-Tabla551857211411[[#This Row],[ICO 8%]] -> 2314.8148 | H9: =+Tabla551857211411[[#This Row],[COSTO]]/Tabla551857211411[[#This Row],[BASE]] -> 1.2002256 | I9: =+Tabla551857211411[[#This Row],[BASE]]/Tabla551857211411[[#This Row],[COSTO]] -> 0.8331767 | J9: =+VLOOKUP(Tabla551857211411[[#This Row],[ADICIONES]],Tabla77[#All],3,0) -> 45 | K9: =+D9/(100-70)*100 -> 9261 | L9: =+K9/1.08*0.08 -> 686 | M9: =+Tabla551857211411[[#This Row],[PRECIO SUGERIDO]]+Tabla551857211411[[#This Row],[ICO2]] -> 9947 | O9: =+N9/1.08*0.08 -> 0 | P9: =+Tabla551857211411[[#This Row],[PRECIO N]]-Tabla551857211411[[#This Row],[ICO 8%2]] -> 0 | Q9: =+Tabla551857211411[[#This Row],[COSTO]]/Tabla551857211411[[#This Row],[CARTA]] -> #DIV/0! | R9: =+Tabla551857211411[[#This Row],[PRECIO N]]/Tabla551857211411[[#This Row],[COSTO]] -> 0
A10: 4 | B10: =+ADICIONES!A41 -> ARROZ BLANCO | D10: =+ADICIONES!J44 -> 911.00442 | E10: =+ADICIONES!J45 -> 8000 | F10: =+E10/1.08*0.08 -> 592.59259 | G10: =+Tabla551857211411[[#This Row],[VENTA]]-Tabla551857211411[[#This Row],[ICO 8%]] -> 7407.4074 | H10: =+Tabla551857211411[[#This Row],[COSTO]]/Tabla551857211411[[#This Row],[BASE]] -> 0.1229856 | I10: =+Tabla551857211411[[#This Row],[BASE]]/Tabla551857211411[[#This Row],[COSTO]] -> 8.1310334 | J10: =+VLOOKUP(Tabla551857211411[[#This Row],[ADICIONES]],Tabla77[#All],3,0) -> 1320 | K10: =+D10/(100-70)*100 -> 3036.6814 | L10: =+K10/1.08*0.08 -> 224.93936 | M10: =+Tabla551857211411[[#This Row],[PRECIO SUGERIDO]]+Tabla551857211411[[#This Row],[ICO2]] -> 3261.6208 | O10: =+N10/1.08*0.08 -> 0 | P10: =+Tabla551857211411[[#This Row],[PRECIO N]]-Tabla551857211411[[#This Row],[ICO 8%2]] -> 0 | Q10: =+Tabla551857211411[[#This Row],[COSTO]]/Tabla551857211411[[#This Row],[CARTA]] -> #DIV/0! | R10: =+Tabla551857211411[[#This Row],[PRECIO N]]/Tabla551857211411[[#This Row],[COSTO]] -> 0
A11: 5 | B11: =+ADICIONES!A54 -> ARROZ CREMOSO ADC | D11: =+ADICIONES!J57 -> 5609.736 | E11: =+ADICIONES!J58 -> 0 | F11: =+E11/1.08*0.08 -> 0 | G11: =+Tabla551857211411[[#This Row],[VENTA]]-Tabla551857211411[[#This Row],[ICO 8%]] -> 0 | H11: =+Tabla551857211411[[#This Row],[COSTO]]/Tabla551857211411[[#This Row],[BASE]] -> #DIV/0! | I11: =+Tabla551857211411[[#This Row],[BASE]]/Tabla551857211411[[#This Row],[COSTO]] -> 0 | J11: =+VLOOKUP(Tabla551857211411[[#This Row],[ADICIONES]],Tabla77[#All],3,0) -> 612 | K11: =+D11/(100-70)*100 -> 18699.12 | L11: =+K11/1.08*0.08 -> 1385.12 | M11: =+Tabla551857211411[[#This Row],[PRECIO SUGERIDO]]+Tabla551857211411[[#This Row],[ICO2]] -> 20084.24 | O11: =+N11/1.08*0.08 -> 0 | P11: =+Tabla551857211411[[#This Row],[PRECIO N]]-Tabla551857211411[[#This Row],[ICO 8%2]] -> 0 | Q11: =+Tabla551857211411[[#This Row],[COSTO]]/Tabla551857211411[[#This Row],[CARTA]] -> #DIV/0! | R11: =+Tabla551857211411[[#This Row],[PRECIO N]]/Tabla551857211411[[#This Row],[COSTO]] -> 0
A12: 6 | B12: =+ADICIONES!A66 -> CAMARON | D12: =+ADICIONES!J69 -> 3570 | E12: =+ADICIONES!J70 -> 10000 | F12: =+E12/1.08*0.08 -> 740.74074 | G12: =+Tabla551857211411[[#This Row],[VENTA]]-Tabla551857211411[[#This Row],[ICO 8%]] -> 9259.2593 | H12: =+Tabla551857211411[[#This Row],[COSTO]]/Tabla551857211411[[#This Row],[BASE]] -> 0.38556 | I12: =+Tabla551857211411[[#This Row],[BASE]]/Tabla551857211411[[#This Row],[COSTO]] -> 2.59363 | J12: =+VLOOKUP(Tabla551857211411[[#This Row],[ADICIONES]],Tabla77[#All],3,0) -> 8 | K12: =+D12/(100-70)*100 -> 11900 | L12: =+K12/1.08*0.08 -> 881.48148 | M12: =+Tabla551857211411[[#This Row],[PRECIO SUGERIDO]]+Tabla551857211411[[#This Row],[ICO2]] -> 12781.481 | O12: =+N12/1.08*0.08 -> 0 | P12: =+Tabla551857211411[[#This Row],[PRECIO N]]-Tabla551857211411[[#This Row],[ICO 8%2]] -> 0 | Q12: =+Tabla551857211411[[#This Row],[COSTO]]/Tabla551857211411[[#This Row],[CARTA]] -> #DIV/0! | R12: =+Tabla551857211411[[#This Row],[PRECIO N]]/Tabla551857211411[[#This Row],[COSTO]] -> 0
A13: 7 | B13: =+ADICIONES!A80 -> CAMOTE | D13: =+ADICIONES!J83 -> 1250.4377 | E13: =+ADICIONES!J84 -> 5000 | F13: =+E13/1.08*0.08 -> 370.37037 | G13: =+Tabla551857211411[[#This Row],[VENTA]]-Tabla551857211411[[#This Row],[ICO 8%]] -> 4629.6296 | H13: =+Tabla551857211411[[#This Row],[COSTO]]/Tabla551857211411[[#This Row],[BASE]] -> 0.27009454 | I13: =+Tabla551857211411[[#This Row],[BASE]]/Tabla551857211411[[#This Row],[COSTO]] -> 3.7024074 | J13: =+VLOOKUP(Tabla551857211411[[#This Row],[ADICIONES]],Tabla77[#All],3,0) -> 3 | K13: =+D13/(100-70)*100 -> 4168.1256 | L13: =+K13/1.08*0.08 -> 308.75004 | M13: =+Tabla551857211411[[#This Row],[PRECIO SUGERIDO]]+Tabla551857211411[[#This Row],[ICO2]] -> 4476.8756 | O13: =+N13/1.08*0.08 -> 0 | P13: =+Tabla551857211411[[#This Row],[PRECIO N]]-Tabla551857211411[[#This Row],[ICO 8%2]] -> 0 | Q13: =+Tabla551857211411[[#This Row],[COSTO]]/Tabla551857211411[[#This Row],[CARTA]] -> #DIV/0! | R13: =+Tabla551857211411[[#This Row],[PRECIO N]]/Tabla551857211411[[#This Row],[COSTO]] -> 0
A14: 8 | B14: =+ADICIONES!A92 -> CEREZA | D14: =+ADICIONES!J95 -> 167.03912 | E14: =+ADICIONES!J96 -> 4900 | F14: =+E14/1.08*0.08 -> 362.96296 | G14: =+Tabla551857211411[[#This Row],[VENTA]]-Tabla551857211411[[#This Row],[ICO 8%]] -> 4537.037 | H14: =+Tabla551857211411[[#This Row],[COSTO]]/Tabla551857211411[[#This Row],[BASE]] -> 0.036816785 | I14: =+Tabla551857211411[[#This Row],[BASE]]/Tabla551857211411[[#This Row],[COSTO]] -> 27.161524 | J14: =+VLOOKUP(Tabla551857211411[[#This Row],[ADICIONES]],Tabla77[#All],3,0) -> 2 | K14: =+D14/(100-70)*100 -> 556.79706 | L14: =+K14/1.08*0.08 -> 41.244227 | M14: =+Tabla551857211411[[#This Row],[PRECIO SUGERIDO]]+Tabla551857211411[[#This Row],[ICO2]] -> 598.04129 | O14: =+N14/1.08*0.08 -> 0 | P14: =+Tabla551857211411[[#This Row],[PRECIO N]]-Tabla551857211411[[#This Row],[ICO 8%2]] -> 0 | Q14: =+Tabla551857211411[[#This Row],[COSTO]]/Tabla551857211411[[#This Row],[CARTA]] -> #DIV/0! | R14: =+Tabla551857211411[[#This Row],[PRECIO N]]/Tabla551857211411[[#This Row],[COSTO]] -> 0
A15: 9 | B15: =+ADICIONES!A108 -> CHANCHO | D15: =+ADICIONES!J111 -> 5166.8431 | E15: =+ADICIONES!J112 -> 35000 | F15: =+E15/1.08*0.08 -> 2592.5926 | G15: =+Tabla551857211411[[#This Row],[VENTA]]-Tabla551857211411[[#This Row],[ICO 8%]] -> 32407.407 | H15: =+Tabla551857211411[[#This Row],[COSTO]]/Tabla551857211411[[#This Row],[BASE]] -> 0.15943402 | I15: =+Tabla551857211411[[#This Row],[BASE]]/Tabla551857211411[[#This Row],[COSTO]] -> 6.2721872 | J15: =+VLOOKUP(Tabla551857211411[[#This Row],[ADICIONES]],Tabla77[#All],3,0) -> #N/A | K15: =+D15/(100-70)*100 -> 17222.81 | L15: =+K15/1.08*0.08 -> 1275.7637 | M15: =+Tabla551857211411[[#This Row],[PRECIO SUGERIDO]]+Tabla551857211411[[#This Row],[ICO2]] -> 18498.574 | O15: =+N15/1.08*0.08 -> 0 | P15: =+Tabla551857211411[[#This Row],[PRECIO N]]-Tabla551857211411[[#This Row],[ICO 8%2]] -> 0 | Q15: =+Tabla551857211411[[#This Row],[COSTO]]/Tabla551857211411[[#This Row],[CARTA]] -> #DIV/0! | R15: =+Tabla551857211411[[#This Row],[PRECIO N]]/Tabla551857211411[[#This Row],[COSTO]] -> 0
A16: 10 | B16: =+ADICIONES!A120 -> ENSALADA | D16: =+ADICIONES!J123 -> 2012.019 | E16: =+ADICIONES!J124 -> 5500 | F16: =+E16/1.08*0.08 -> 407.40741 | G16: =+Tabla551857211411[[#This Row],[VENTA]]-Tabla551857211411[[#This Row],[ICO 8%]] -> 5092.5926 | H16: =+Tabla551857211411[[#This Row],[COSTO]]/Tabla551857211411[[#This Row],[BASE]] -> 0.39508736 | I16: =+Tabla551857211411[[#This Row],[BASE]]/Tabla551857211411[[#This Row],[COSTO]] -> 2.5310858 | J16: =+VLOOKUP(Tabla551857211411[[#This Row],[ADICIONES]],Tabla77[#All],3,0) -> 29 | K16: =+D16/(100-70)*100 -> 6706.7299 | L16: =+K16/1.08*0.08 -> 496.79481 | M16: =+Tabla551857211411[[#This Row],[PRECIO SUGERIDO]]+Tabla551857211411[[#This Row],[ICO2]] -> 7203.5247 | O16: =+N16/1.08*0.08 -> 0 | P16: =+Tabla551857211411[[#This Row],[PRECIO N]]-Tabla551857211411[[#This Row],[ICO 8%2]] -> 0 | Q16: =+Tabla551857211411[[#This Row],[COSTO]]/Tabla551857211411[[#This Row],[CARTA]] -> #DIV/0! | R16: =+Tabla551857211411[[#This Row],[PRECIO N]]/Tabla551857211411[[#This Row],[COSTO]] -> 0
A17: 11 | B17: =+ADICIONES!A135 -> FILETE DE POLLO | D17: =+ADICIONES!J137 -> 2169.9999 | E17: =+ADICIONES!J138 -> 9000 | F17: =+E17/1.08*0.08 -> 666.66667 | G17: =+Tabla551857211411[[#This Row],[VENTA]]-Tabla551857211411[[#This Row],[ICO 8%]] -> 8333.3333 | H17: =+Tabla551857211411[[#This Row],[COSTO]]/Tabla551857211411[[#This Row],[BASE]] -> 0.26039999 | I17: =+Tabla551857211411[[#This Row],[BASE]]/Tabla551857211411[[#This Row],[COSTO]] -> 3.8402459 | J17: =+VLOOKUP(Tabla551857211411[[#This Row],[ADICIONES]],Tabla77[#All],3,0) -> 5 | K17: =+D17/(100-70)*100 -> 7233.3332 | L17: =+K17/1.08*0.08 -> 535.80246 | M17: =+Tabla551857211411[[#This Row],[PRECIO SUGERIDO]]+Tabla551857211411[[#This Row],[ICO2]] -> 7769.1356 | O17: =+N17/1.08*0.08 -> 0 | P17: =+Tabla551857211411[[#This Row],[PRECIO N]]-Tabla551857211411[[#This Row],[ICO 8%2]] -> 0 | Q17: =+Tabla551857211411[[#This Row],[COSTO]]/Tabla551857211411[[#This Row],[CARTA]] -> #DIV/0! | R17: =+Tabla551857211411[[#This Row],[PRECIO N]]/Tabla551857211411[[#This Row],[COSTO]] -> 0
A18: 12 | B18: =+ADICIONES!A146 -> FILETE DE SALMON | D18: =+ADICIONES!J149 -> 0 | E18: =+ADICIONES!J150 -> 40000 | F18: =+E18/1.08*0.08 -> 2962.963 | G18: =+Tabla551857211411[[#This Row],[VENTA]]-Tabla551857211411[[#This Row],[ICO 8%]] -> 37037.037 | H18: =+Tabla551857211411[[#This Row],[COSTO]]/Tabla551857211411[[#This Row],[BASE]] -> 0 | I18: =+Tabla551857211411[[#This Row],[BASE]]/Tabla551857211411[[#This Row],[COSTO]] -> #DIV/0! | J18: =+VLOOKUP(Tabla551857211411[[#This Row],[ADICIONES]],Tabla77[#All],3,0) -> 2 | K18: =+D18/(100-70)*100 -> 0 | L18: =+K18/1.08*0.08 -> 0 | M18: =+Tabla551857211411[[#This Row],[PRECIO SUGERIDO]]+Tabla551857211411[[#This Row],[ICO2]] -> 0 | O18: =+N18/1.08*0.08 -> 0 | P18: =+Tabla551857211411[[#This Row],[PRECIO N]]-Tabla551857211411[[#This Row],[ICO 8%2]] -> 0 | Q18: =+Tabla551857211411[[#This Row],[COSTO]]/Tabla551857211411[[#This Row],[CARTA]] -> #DIV/0! | R18: =+Tabla551857211411[[#This Row],[PRECIO N]]/Tabla551857211411[[#This Row],[COSTO]] -> #DIV/0!
A19: 13 | B19: =+ADICIONES!A158 -> FILETE DE TILAPIA | D19: =+ADICIONES!J161 -> 5179.9999 | E19: =+ADICIONES!J162 -> 25000 | F19: =+E19/1.08*0.08 -> 1851.8519 | G19: =+Tabla551857211411[[#This Row],[VENTA]]-Tabla551857211411[[#This Row],[ICO 8%]] -> 23148.148 | H19: =+Tabla551857211411[[#This Row],[COSTO]]/Tabla551857211411[[#This Row],[BASE]] -> 0.22377599 | I19: =+Tabla551857211411[[#This Row],[BASE]]/Tabla551857211411[[#This Row],[COSTO]] -> 4.4687546 | J19: =+VLOOKUP(Tabla551857211411[[#This Row],[ADICIONES]],Tabla77[#All],3,0) -> 2 | K19: =+D19/(100-70)*100 -> 17266.666 | L19: =+K19/1.08*0.08 -> 1279.0123 | M19: =+Tabla551857211411[[#This Row],[PRECIO SUGERIDO]]+Tabla551857211411[[#This Row],[ICO2]] -> 18545.679 | O19: =+N19/1.08*0.08 -> 0 | P19: =+Tabla551857211411[[#This Row],[PRECIO N]]-Tabla551857211411[[#This Row],[ICO 8%2]] -> 0 | Q19: =+Tabla551857211411[[#This Row],[COSTO]]/Tabla551857211411[[#This Row],[CARTA]] -> #DIV/0! | R19: =+Tabla551857211411[[#This Row],[PRECIO N]]/Tabla551857211411[[#This Row],[COSTO]] -> 0
A20: 14 | B20: =+ADICIONES!A170 -> FRESA | D20: =+ADICIONES!J173 -> 361.66665 | E20: =+ADICIONES!J174 -> 4900 | F20: =+E20/1.08*0.08 -> 362.96296 | G20: =+Tabla551857211411[[#This Row],[VENTA]]-Tabla551857211411[[#This Row],[ICO 8%]] -> 4537.037 | H20: =+Tabla551857211411[[#This Row],[COSTO]]/Tabla551857211411[[#This Row],[BASE]] -> 0.079714281 | I20: =+Tabla551857211411[[#This Row],[BASE]]/Tabla551857211411[[#This Row],[COSTO]] -> 12.544804 | J20: =+VLOOKUP(Tabla551857211411[[#This Row],[ADICIONES]],Tabla77[#All],3,0) -> 1 | K20: =+D20/(100-70)*100 -> 1205.5555 | L20: =+K20/1.08*0.08 -> 89.300407 | M20: =+Tabla551857211411[[#This Row],[PRECIO SUGERIDO]]+Tabla551857211411[[#This Row],[ICO2]] -> 1294.8559 | O20: =+N20/1.08*0.08 -> 0 | P20: =+Tabla551857211411[[#This Row],[PRECIO N]]-Tabla551857211411[[#This Row],[ICO 8%2]] -> 0 | Q20: =+Tabla551857211411[[#This Row],[COSTO]]/Tabla551857211411[[#This Row],[CARTA]] -> #DIV/0! | R20: =+Tabla551857211411[[#This Row],[PRECIO N]]/Tabla551857211411[[#This Row],[COSTO]] -> 0
A21: 15 | B21: =+ADICIONES!A182 -> GUACAMOLE | D21: =+ADICIONES!J185 -> 781.33452 | E21: =+ADICIONES!J186 -> 2900 | F21: =+E21/1.08*0.08 -> 214.81481 | G21: =+Tabla551857211411[[#This Row],[VENTA]]-Tabla551857211411[[#This Row],[ICO 8%]] -> 2685.1852 | H21: =+Tabla551857211411[[#This Row],[COSTO]]/Tabla551857211411[[#This Row],[BASE]] -> 0.29097975 | I21: =+Tabla551857211411[[#This Row],[BASE]]/Tabla551857211411[[#This Row],[COSTO]] -> 3.4366652 | J21: =+VLOOKUP(Tabla551857211411[[#This Row],[ADICIONES]],Tabla77[#All],3,0) -> 7 | K21: =+D21/(100-70)*100 -> 2604.4484 | L21: =+K21/1.08*0.08 -> 192.9221 | M21: =+Tabla551857211411[[#This Row],[PRECIO SUGERIDO]]+Tabla551857211411[[#This Row],[ICO2]] -> 2797.3705 | O21: =+N21/1.08*0.08 -> 0 | P21: =+Tabla551857211411[[#This Row],[PRECIO N]]-Tabla551857211411[[#This Row],[ICO 8%2]] -> 0 | Q21: =+Tabla551857211411[[#This Row],[COSTO]]/Tabla551857211411[[#This Row],[CARTA]] -> #DIV/0! | R21: =+Tabla551857211411[[#This Row],[PRECIO N]]/Tabla551857211411[[#This Row],[COSTO]] -> 0
A22: 16 | B22: =+ADICIONES!A194 -> HELADO | D22: =+ADICIONES!J197 -> 780.2109 | E22: =+ADICIONES!J198 -> 12000 | F22: =+E22/1.08*0.08 -> 888.88889 | G22: =+Tabla551857211411[[#This Row],[VENTA]]-Tabla551857211411[[#This Row],[ICO 8%]] -> 11111.111 | H22: =+Tabla551857211411[[#This Row],[COSTO]]/Tabla551857211411[[#This Row],[BASE]] -> 0.070218981 | I22: =+Tabla551857211411[[#This Row],[BASE]]/Tabla551857211411[[#This Row],[COSTO]] -> 14.241164 | J22: =+VLOOKUP(Tabla551857211411[[#This Row],[ADICIONES]],Tabla77[#All],3,0) -> 8 | K22: =+D22/(100-70)*100 -> 2600.703 | L22: =+K22/1.08*0.08 -> 192.64467 | M22: =+Tabla551857211411[[#This Row],[PRECIO SUGERIDO]]+Tabla551857211411[[#This Row],[ICO2]] -> 2793.3477 | O22: =+N22/1.08*0.08 -> 0 | P22: =+Tabla551857211411[[#This Row],[PRECIO N]]-Tabla551857211411[[#This Row],[ICO 8%2]] -> 0 | Q22: =+Tabla551857211411[[#This Row],[COSTO]]/Tabla551857211411[[#This Row],[CARTA]] -> #DIV/0! | R22: =+Tabla551857211411[[#This Row],[PRECIO N]]/Tabla551857211411[[#This Row],[COSTO]] -> 0
A23: 17 | B23: =+ADICIONES!A207 -> HUEVO | D23: =+ADICIONES!J210 -> #N/A | E23: =+ADICIONES!J211 -> 1500 | F23: =+E23/1.08*0.08 -> 111.11111 | G23: =+Tabla551857211411[[#This Row],[VENTA]]-Tabla551857211411[[#This Row],[ICO 8%]] -> 1388.8889 | H23: =+Tabla551857211411[[#This Row],[COSTO]]/Tabla551857211411[[#This Row],[BASE]] -> #N/A | I23: =+Tabla551857211411[[#This Row],[BASE]]/Tabla551857211411[[#This Row],[COSTO]] -> #N/A | J23: =+VLOOKUP(Tabla551857211411[[#This Row],[ADICIONES]],Tabla77[#All],3,0) -> 229 | K23: =+D23/(100-70)*100 -> #N/A | L23: =+K23/1.08*0.08 -> #N/A | M23: =+Tabla551857211411[[#This Row],[PRECIO SUGERIDO]]+Tabla551857211411[[#This Row],[ICO2]] -> #N/A | O23: =+N23/1.08*0.08 -> 0 | P23: =+Tabla551857211411[[#This Row],[PRECIO N]]-Tabla551857211411[[#This Row],[ICO 8%2]] -> 0 | Q23: =+Tabla551857211411[[#This Row],[COSTO]]/Tabla551857211411[[#This Row],[CARTA]] -> #N/A | R23: =+Tabla551857211411[[#This Row],[PRECIO N]]/Tabla551857211411[[#This Row],[COSTO]] -> #N/A
A24: 18 | B24: =+ADICIONES!A221 -> LANGOSTINOS | D24: =+ADICIONES!J224 -> 6825 | E24: =+ADICIONES!J225 -> 25000 | F24: =+E24/1.08*0.08 -> 1851.8519 | G24: =+Tabla551857211411[[#This Row],[VENTA]]-Tabla551857211411[[#This Row],[ICO 8%]] -> 23148.148 | H24: =+Tabla551857211411[[#This Row],[COSTO]]/Tabla551857211411[[#This Row],[BASE]] -> 0.29484 | I24: =+Tabla551857211411[[#This Row],[BASE]]/Tabla551857211411[[#This Row],[COSTO]] -> 3.3916701 | J24: =+VLOOKUP(Tabla551857211411[[#This Row],[ADICIONES]],Tabla77[#All],3,0) -> 1 | K24: =+D24/(100-70)*100 -> 22750 | L24: =+K24/1.08*0.08 -> 1685.1852 | M24: =+Tabla551857211411[[#This Row],[PRECIO SUGERIDO]]+Tabla551857211411[[#This Row],[ICO2]] -> 24435.185 | O24: =+N24/1.08*0.08 -> 0 | P24: =+Tabla551857211411[[#This Row],[PRECIO N]]-Tabla551857211411[[#This Row],[ICO 8%2]] -> 0 | Q24: =+Tabla551857211411[[#This Row],[COSTO]]/Tabla551857211411[[#This Row],[CARTA]] -> #DIV/0! | R24: =+Tabla551857211411[[#This Row],[PRECIO N]]/Tabla551857211411[[#This Row],[COSTO]] -> 0
A25: 19 | B25: =+ADICIONES!A232 -> LECHE | D25: =+ADICIONES!J235 -> 2206.512 | E25: =+ADICIONES!J236 -> 2000 | F25: =+E25/1.08*0.08 -> 148.14815 | G25: =+Tabla551857211411[[#This Row],[VENTA]]-Tabla551857211411[[#This Row],[ICO 8%]] -> 1851.8519 | H25: =+Tabla551857211411[[#This Row],[COSTO]]/Tabla551857211411[[#This Row],[BASE]] -> 1.1915165 | I25: =+Tabla551857211411[[#This Row],[BASE]]/Tabla551857211411[[#This Row],[COSTO]] -> 0.83926661 | J25: =+VLOOKUP(Tabla551857211411[[#This Row],[ADICIONES]],Tabla77[#All],3,0) -> 11 | K25: =+D25/(100-70)*100 -> 7355.04 | L25: =+K25/1.08*0.08 -> 544.81778 | M25: =+Tabla551857211411[[#This Row],[PRECIO SUGERIDO]]+Tabla551857211411[[#This Row],[ICO2]] -> 7899.8578 | O25: =+N25/1.08*0.08 -> 0 | P25: =+Tabla551857211411[[#This Row],[PRECIO N]]-Tabla551857211411[[#This Row],[ICO 8%2]] -> 0 | Q25: =+Tabla551857211411[[#This Row],[COSTO]]/Tabla551857211411[[#This Row],[CARTA]] -> #DIV/0! | R25: =+Tabla551857211411[[#This Row],[PRECIO N]]/Tabla551857211411[[#This Row],[COSTO]] -> 0
A26: 20 | B26: =+ADICIONES!A245 -> LYCHE | D26: =+ADICIONES!J248 -> 1005.83 | E26: =+ADICIONES!J249 -> 4900 | F26: =+E26/1.08*0.08 -> 362.96296 | G26: =+Tabla551857211411[[#This Row],[VENTA]]-Tabla551857211411[[#This Row],[ICO 8%]] -> 4537.037 | H26: =+Tabla551857211411[[#This Row],[COSTO]]/Tabla551857211411[[#This Row],[BASE]] -> 0.22169314 | I26: =+Tabla551857211411[[#This Row],[BASE]]/Tabla551857211411[[#This Row],[COSTO]] -> 4.5107394 | J26: =+VLOOKUP(Tabla551857211411[[#This Row],[ADICIONES]],Tabla77[#All],3,0) -> 9 | K26: =+D26/(100-70)*100 -> 3352.7667 | L26: =+K26/1.08*0.08 -> 248.35309 | M26: =+Tabla551857211411[[#This Row],[PRECIO SUGERIDO]]+Tabla551857211411[[#This Row],[ICO2]] -> 3601.1198 | O26: =+N26/1.08*0.08 -> 0 | P26: =+Tabla551857211411[[#This Row],[PRECIO N]]-Tabla551857211411[[#This Row],[ICO 8%2]] -> 0 | Q26: =+Tabla551857211411[[#This Row],[COSTO]]/Tabla551857211411[[#This Row],[CARTA]] -> #DIV/0! | R26: =+Tabla551857211411[[#This Row],[PRECIO N]]/Tabla551857211411[[#This Row],[COSTO]] -> 0
A27: 21 | B27: =+ADICIONES!A257 -> MAYO ACEVICHADA | D27: =+ADICIONES!J260 -> 710.18289 | E27: =+ADICIONES!J261 -> 2900 | F27: =+E27/1.08*0.08 -> 214.81481 | G27: =+Tabla551857211411[[#This Row],[VENTA]]-Tabla551857211411[[#This Row],[ICO 8%]] -> 2685.1852 | H27: =+Tabla551857211411[[#This Row],[COSTO]]/Tabla551857211411[[#This Row],[BASE]] -> 0.2644819 | I27: =+Tabla551857211411[[#This Row],[BASE]]/Tabla551857211411[[#This Row],[COSTO]] -> 3.780977 | J27: =+VLOOKUP(Tabla551857211411[[#This Row],[ADICIONES]],Tabla77[#All],3,0) -> 15 | K27: =+D27/(100-70)*100 -> 2367.2763 | L27: =+K27/1.08*0.08 -> 175.3538 | M27: =+Tabla551857211411[[#This Row],[PRECIO SUGERIDO]]+Tabla551857211411[[#This Row],[ICO2]] -> 2542.6301 | O27: =+N27/1.08*0.08 -> 0 | P27: =+Tabla551857211411[[#This Row],[PRECIO N]]-Tabla551857211411[[#This Row],[ICO 8%2]] -> 0 | Q27: =+Tabla551857211411[[#This Row],[COSTO]]/Tabla551857211411[[#This Row],[CARTA]] -> #DIV/0! | R27: =+Tabla551857211411[[#This Row],[PRECIO N]]/Tabla551857211411[[#This Row],[COSTO]] -> 0
A28: 22 | B28: =+ADICIONES!A268 -> MEJILLONES | D28: =+ADICIONES!J271 -> 1699.32 | E28: =+ADICIONES!J272 -> 6000 | F28: =+E28/1.08*0.08 -> 444.44444 | G28: =+Tabla551857211411[[#This Row],[VENTA]]-Tabla551857211411[[#This Row],[ICO 8%]] -> 5555.5556 | H28: =+Tabla551857211411[[#This Row],[COSTO]]/Tabla551857211411[[#This Row],[BASE]] -> 0.3058776 | I28: =+Tabla551857211411[[#This Row],[BASE]]/Tabla551857211411[[#This Row],[COSTO]] -> 3.2692816 | J28: =+VLOOKUP(Tabla551857211411[[#This Row],[ADICIONES]],Tabla77[#All],3,0) -> #N/A | K28: =+D28/(100-70)*100 -> 5664.4 | L28: =+K28/1.08*0.08 -> 419.58519 | M28: =+Tabla551857211411[[#This Row],[PRECIO SUGERIDO]]+Tabla551857211411[[#This Row],[ICO2]] -> 6083.9852 | O28: =+N28/1.08*0.08 -> 0 | P28: =+Tabla551857211411[[#This Row],[PRECIO N]]-Tabla551857211411[[#This Row],[ICO 8%2]] -> 0 | Q28: =+Tabla551857211411[[#This Row],[COSTO]]/Tabla551857211411[[#This Row],[CARTA]] -> #DIV/0! | R28: =+Tabla551857211411[[#This Row],[PRECIO N]]/Tabla551857211411[[#This Row],[COSTO]] -> 0
A29: 23 | B29: =+ADICIONES!A279 -> MERMELADA DE AJI AMARILLO | D29: =+ADICIONES!J282 -> 900.37726 | E29: =+ADICIONES!J283 -> 3900 | F29: =+E29/1.08*0.08 -> 288.88889 | G29: =+Tabla551857211411[[#This Row],[VENTA]]-Tabla551857211411[[#This Row],[ICO 8%]] -> 3611.1111 | H29: =+Tabla551857211411[[#This Row],[COSTO]]/Tabla551857211411[[#This Row],[BASE]] -> 0.24933524 | I29: =+Tabla551857211411[[#This Row],[BASE]]/Tabla551857211411[[#This Row],[COSTO]] -> 4.0106645 | J29: =+VLOOKUP(Tabla551857211411[[#This Row],[ADICIONES]],Tabla77[#All],3,0) -> #N/A | K29: =+D29/(100-70)*100 -> 3001.2575 | L29: =+K29/1.08*0.08 -> 222.31537 | M29: =+Tabla551857211411[[#This Row],[PRECIO SUGERIDO]]+Tabla551857211411[[#This Row],[ICO2]] -> 3223.5729 | O29: =+N29/1.08*0.08 -> 0 | P29: =+Tabla551857211411[[#This Row],[PRECIO N]]-Tabla551857211411[[#This Row],[ICO 8%2]] -> 0 | Q29: =+Tabla551857211411[[#This Row],[COSTO]]/Tabla551857211411[[#This Row],[CARTA]] -> #DIV/0! | R29: =+Tabla551857211411[[#This Row],[PRECIO N]]/Tabla551857211411[[#This Row],[COSTO]] -> 0
A30: 24 | B30: =+ADICIONES!A292 -> PAPA A LA FRANCESA | D30: =+ADICIONES!J295 -> 2653.8727 | E30: =+ADICIONES!J296 -> 8000 | F30: =+E30/1.08*0.08 -> 592.59259 | G30: =+Tabla551857211411[[#This Row],[VENTA]]-Tabla551857211411[[#This Row],[ICO 8%]] -> 7407.4074 | H30: =+Tabla551857211411[[#This Row],[COSTO]]/Tabla551857211411[[#This Row],[BASE]] -> 0.35827281 | I30: =+Tabla551857211411[[#This Row],[BASE]]/Tabla551857211411[[#This Row],[COSTO]] -> 2.7911691 | J30: =+VLOOKUP(Tabla551857211411[[#This Row],[ADICIONES]],Tabla77[#All],3,0) -> 1164 | K30: =+D30/(100-70)*100 -> 8846.2423 | L30: =+K30/1.08*0.08 -> 655.27721 | M30: =+Tabla551857211411[[#This Row],[PRECIO SUGERIDO]]+Tabla551857211411[[#This Row],[ICO2]] -> 9501.5195 | O30: =+N30/1.08*0.08 -> 0 | P30: =+Tabla551857211411[[#This Row],[PRECIO N]]-Tabla551857211411[[#This Row],[ICO 8%2]] -> 0 | Q30: =+Tabla551857211411[[#This Row],[COSTO]]/Tabla551857211411[[#This Row],[CARTA]] -> #DIV/0! | R30: =+Tabla551857211411[[#This Row],[PRECIO N]]/Tabla551857211411[[#This Row],[COSTO]] -> 0
A31: 25 | B31: =+ADICIONES!A305 -> PAPA CRIOLLA | D31: =+ADICIONES!J308 -> 1400 | E31: =+ADICIONES!J309 -> 8000 | F31: =+E31/1.08*0.08 -> 592.59259 | G31: =+Tabla551857211411[[#This Row],[VENTA]]-Tabla551857211411[[#This Row],[ICO 8%]] -> 7407.4074 | H31: =+Tabla551857211411[[#This Row],[COSTO]]/Tabla551857211411[[#This Row],[BASE]] -> 0.189 | I31: =+Tabla551857211411[[#This Row],[BASE]]/Tabla551857211411[[#This Row],[COSTO]] -> 5.2910053 | J31: =+VLOOKUP(Tabla551857211411[[#This Row],[ADICIONES]],Tabla77[#All],3,0) -> 112 | K31: =+D31/(100-70)*100 -> 4666.6667 | L31: =+K31/1.08*0.08 -> 345.67901 | M31: =+Tabla551857211411[[#This Row],[PRECIO SUGERIDO]]+Tabla551857211411[[#This Row],[ICO2]] -> 5012.3457 | O31: =+N31/1.08*0.08 -> 0 | P31: =+Tabla551857211411[[#This Row],[PRECIO N]]-Tabla551857211411[[#This Row],[ICO 8%2]] -> 0 | Q31: =+Tabla551857211411[[#This Row],[COSTO]]/Tabla551857211411[[#This Row],[CARTA]] -> #DIV/0! | R31: =+Tabla551857211411[[#This Row],[PRECIO N]]/Tabla551857211411[[#This Row],[COSTO]] -> 0
A32: 26 | B32: =+ADICIONES!A316 -> PULPO | D32: =+ADICIONES!J319 -> 22002.947 | E32: =+ADICIONES!J320 -> 17000 | F32: =+E32/1.08*0.08 -> 1259.2593 | G32: =+Tabla551857211411[[#This Row],[VENTA]]-Tabla551857211411[[#This Row],[ICO 8%]] -> 15740.741 | H32: =+Tabla551857211411[[#This Row],[COSTO]]/Tabla551857211411[[#This Row],[BASE]] -> 1.3978343 | I32: =+Tabla551857211411[[#This Row],[BASE]]/Tabla551857211411[[#This Row],[COSTO]] -> 0.7153924 | J32: =+VLOOKUP(Tabla551857211411[[#This Row],[ADICIONES]],Tabla77[#All],3,0) -> 1 | K32: =+D32/(100-70)*100 -> 73343.156 | L32: =+K32/1.08*0.08 -> 5432.8263 | M32: =+Tabla551857211411[[#This Row],[PRECIO SUGERIDO]]+Tabla551857211411[[#This Row],[ICO2]] -> 78775.982 | O32: =+N32/1.08*0.08 -> 0 | P32: =+Tabla551857211411[[#This Row],[PRECIO N]]-Tabla551857211411[[#This Row],[ICO 8%2]] -> 0 | Q32: =+Tabla551857211411[[#This Row],[COSTO]]/Tabla551857211411[[#This Row],[CARTA]] -> #DIV/0! | R32: =+Tabla551857211411[[#This Row],[PRECIO N]]/Tabla551857211411[[#This Row],[COSTO]] -> 0
A33: 27 | B33: =+ADICIONES!A328 -> QUESO PARMESSANO | D33: =+ADICIONES!J331 -> 1280.7375 | E33: =+ADICIONES!J332 -> 8000 | F33: =+E33/1.08*0.08 -> 592.59259 | G33: =+Tabla551857211411[[#This Row],[VENTA]]-Tabla551857211411[[#This Row],[ICO 8%]] -> 7407.4074 | H33: =+Tabla551857211411[[#This Row],[COSTO]]/Tabla551857211411[[#This Row],[BASE]] -> 0.17289956 | I33: =+Tabla551857211411[[#This Row],[BASE]]/Tabla551857211411[[#This Row],[COSTO]] -> 5.7837046 | J33: =+VLOOKUP(Tabla551857211411[[#This Row],[ADICIONES]],Tabla77[#All],3,0) -> 10 | K33: =+D33/(100-70)*100 -> 4269.125 | L33: =+K33/1.08*0.08 -> 316.23148 | M33: =+Tabla551857211411[[#This Row],[PRECIO SUGERIDO]]+Tabla551857211411[[#This Row],[ICO2]] -> 4585.3565 | O33: =+N33/1.08*0.08 -> 0 | P33: =+Tabla551857211411[[#This Row],[PRECIO N]]-Tabla551857211411[[#This Row],[ICO 8%2]] -> 0 | Q33: =+Tabla551857211411[[#This Row],[COSTO]]/Tabla551857211411[[#This Row],[CARTA]] -> #DIV/0! | R33: =+Tabla551857211411[[#This Row],[PRECIO N]]/Tabla551857211411[[#This Row],[COSTO]] -> 0
A34: 28 | B34: =+ADICIONES!A341 -> SALSA A LA HUANCAINA | D34: =+ADICIONES!J344 -> 385.97473 | E34: =+ADICIONES!J345 -> 2900 | F34: =+E34/1.08*0.08 -> 214.81481 | G34: =+Tabla551857211411[[#This Row],[VENTA]]-Tabla551857211411[[#This Row],[ICO 8%]] -> 2685.1852 | H34: =+Tabla551857211411[[#This Row],[COSTO]]/Tabla551857211411[[#This Row],[BASE]] -> 0.14374231 | I34: =+Tabla551857211411[[#This Row],[BASE]]/Tabla551857211411[[#This Row],[COSTO]] -> 6.9568938 | J34: =+VLOOKUP(Tabla551857211411[[#This Row],[ADICIONES]],Tabla77[#All],3,0) -> 25 | K34: =+D34/(100-70)*100 -> 1286.5824 | L34: =+K34/1.08*0.08 -> 95.302402 | M34: =+Tabla551857211411[[#This Row],[PRECIO SUGERIDO]]+Tabla551857211411[[#This Row],[ICO2]] -> 1381.8848 | O34: =+N34/1.08*0.08 -> 0 | P34: =+Tabla551857211411[[#This Row],[PRECIO N]]-Tabla551857211411[[#This Row],[ICO 8%2]] -> 0 | Q34: =+Tabla551857211411[[#This Row],[COSTO]]/Tabla551857211411[[#This Row],[CARTA]] -> #DIV/0! | R34: =+Tabla551857211411[[#This Row],[PRECIO N]]/Tabla551857211411[[#This Row],[COSTO]] -> 0
A35: 29 | B35: =+ADICIONES!A354 -> SALSA CRIOLLA | D35: =+ADICIONES!J357 -> #N/A | E35: =+ADICIONES!J358 -> 2900 | F35: =+E35/1.08*0.08 -> 214.81481 | G35: =+Tabla551857211411[[#This Row],[VENTA]]-Tabla551857211411[[#This Row],[ICO 8%]] -> 2685.1852 | H35: =+Tabla551857211411[[#This Row],[COSTO]]/Tabla551857211411[[#This Row],[BASE]] -> #N/A | I35: =+Tabla551857211411[[#This Row],[BASE]]/Tabla551857211411[[#This Row],[COSTO]] -> #N/A | J35: =+VLOOKUP(Tabla551857211411[[#This Row],[ADICIONES]],Tabla77[#All],3,0) -> 13 | K35: =+D35/(100-70)*100 -> #N/A | L35: =+K35/1.08*0.08 -> #N/A | M35: =+Tabla551857211411[[#This Row],[PRECIO SUGERIDO]]+Tabla551857211411[[#This Row],[ICO2]] -> #N/A | O35: =+N35/1.08*0.08 -> 0 | P35: =+Tabla551857211411[[#This Row],[PRECIO N]]-Tabla551857211411[[#This Row],[ICO 8%2]] -> 0 | Q35: =+Tabla551857211411[[#This Row],[COSTO]]/Tabla551857211411[[#This Row],[CARTA]] -> #N/A | R35: =+Tabla551857211411[[#This Row],[PRECIO N]]/Tabla551857211411[[#This Row],[COSTO]] -> #N/A
A36: 30 | B36: =+ADICIONES!A367 -> SALSA DE TOMATE | D36: =+ADICIONES!J370 -> 593.09069 | E36: =+ADICIONES!J371 -> 3900 | F36: =+E36/1.08*0.08 -> 288.88889 | G36: =+Tabla551857211411[[#This Row],[VENTA]]-Tabla551857211411[[#This Row],[ICO 8%]] -> 3611.1111 | H36: =+Tabla551857211411[[#This Row],[COSTO]]/Tabla551857211411[[#This Row],[BASE]] -> 0.1642405 | I36: =+Tabla551857211411[[#This Row],[BASE]]/Tabla551857211411[[#This Row],[COSTO]] -> 6.0886323 | J36: =+VLOOKUP(Tabla551857211411[[#This Row],[ADICIONES]],Tabla77[#All],3,0) -> #N/A | K36: =+D36/(100-70)*100 -> 1976.969 | L36: =+K36/1.08*0.08 -> 146.44215 | M36: =+Tabla551857211411[[#This Row],[PRECIO SUGERIDO]]+Tabla551857211411[[#This Row],[ICO2]] -> 2123.4111 | O36: =+N36/1.08*0.08 -> 0 | P36: =+Tabla551857211411[[#This Row],[PRECIO N]]-Tabla551857211411[[#This Row],[ICO 8%2]] -> 0 | Q36: =+Tabla551857211411[[#This Row],[COSTO]]/Tabla551857211411[[#This Row],[CARTA]] -> #DIV/0! | R36: =+Tabla551857211411[[#This Row],[PRECIO N]]/Tabla551857211411[[#This Row],[COSTO]] -> 0
A37: 31 | B37: =+ADICIONES!A380 -> SALSA EMPANADAS | D37: =+ADICIONES!J383 -> 724.48306 | E37: =+ADICIONES!J384 -> 3900 | F37: =+E37/1.08*0.08 -> 288.88889 | G37: =+Tabla551857211411[[#This Row],[VENTA]]-Tabla551857211411[[#This Row],[ICO 8%]] -> 3611.1111 | H37: =+Tabla551857211411[[#This Row],[COSTO]]/Tabla551857211411[[#This Row],[BASE]] -> 0.20062608 | I37: =+Tabla551857211411[[#This Row],[BASE]]/Tabla551857211411[[#This Row],[COSTO]] -> 4.9843969 | J37: =+VLOOKUP(Tabla551857211411[[#This Row],[ADICIONES]],Tabla77[#All],3,0) -> 1 | K37: =+D37/(100-70)*100 -> 2414.9435 | L37: =+K37/1.08*0.08 -> 178.88471 | M37: =+Tabla551857211411[[#This Row],[PRECIO SUGERIDO]]+Tabla551857211411[[#This Row],[ICO2]] -> 2593.8282 | O37: =+N37/1.08*0.08 -> 0 | P37: =+Tabla551857211411[[#This Row],[PRECIO N]]-Tabla551857211411[[#This Row],[ICO 8%2]] -> 0 | Q37: =+Tabla551857211411[[#This Row],[COSTO]]/Tabla551857211411[[#This Row],[CARTA]] -> #DIV/0! | R37: =+Tabla551857211411[[#This Row],[PRECIO N]]/Tabla551857211411[[#This Row],[COSTO]] -> 0
A38: 32 | B38: =+ADICIONES!A393 -> SALSA HUACAINA | D38: =+ADICIONES!J396 -> 385.97473 | E38: =+ADICIONES!J397 -> 3900 | F38: =+E38/1.08*0.08 -> 288.88889 | G38: =+Tabla551857211411[[#This Row],[VENTA]]-Tabla551857211411[[#This Row],[ICO 8%]] -> 3611.1111 | H38: =+Tabla551857211411[[#This Row],[COSTO]]/Tabla551857211411[[#This Row],[BASE]] -> 0.10688531 | I38: =+Tabla551857211411[[#This Row],[BASE]]/Tabla551857211411[[#This Row],[COSTO]] -> 9.3558227 | J38: =+VLOOKUP(Tabla551857211411[[#This Row],[ADICIONES]],Tabla77[#All],3,0) -> 7 | K38: =+D38/(100-70)*100 -> 1286.5824 | L38: =+K38/1.08*0.08 -> 95.302402 | M38: =+Tabla551857211411[[#This Row],[PRECIO SUGERIDO]]+Tabla551857211411[[#This Row],[ICO2]] -> 1381.8848 | O38: =+N38/1.08*0.08 -> 0 | P38: =+Tabla551857211411[[#This Row],[PRECIO N]]-Tabla551857211411[[#This Row],[ICO 8%2]] -> 0 | Q38: =+Tabla551857211411[[#This Row],[COSTO]]/Tabla551857211411[[#This Row],[CARTA]] -> #DIV/0! | R38: =+Tabla551857211411[[#This Row],[PRECIO N]]/Tabla551857211411[[#This Row],[COSTO]] -> 0
A39: 33 | B39: =+ADICIONES!A405 -> SALSA MELCOCHA | D39: =+ADICIONES!J408 -> 2990.1656 | E39: =+ADICIONES!J409 -> 3900 | F39: =+E39/1.08*0.08 -> 288.88889 | G39: =+Tabla551857211411[[#This Row],[VENTA]]-Tabla551857211411[[#This Row],[ICO 8%]] -> 3611.1111 | H39: =+Tabla551857211411[[#This Row],[COSTO]]/Tabla551857211411[[#This Row],[BASE]] -> 0.82804587 | I39: =+Tabla551857211411[[#This Row],[BASE]]/Tabla551857211411[[#This Row],[COSTO]] -> 1.2076626 | J39: =+VLOOKUP(Tabla551857211411[[#This Row],[ADICIONES]],Tabla77[#All],3,0) -> 3 | K39: =+D39/(100-70)*100 -> 9967.2188 | L39: =+K39/1.08*0.08 -> 738.3125 | M39: =+Tabla551857211411[[#This Row],[PRECIO SUGERIDO]]+Tabla551857211411[[#This Row],[ICO2]] -> 10705.531 | O39: =+N39/1.08*0.08 -> 0 | P39: =+Tabla551857211411[[#This Row],[PRECIO N]]-Tabla551857211411[[#This Row],[ICO 8%2]] -> 0 | Q39: =+Tabla551857211411[[#This Row],[COSTO]]/Tabla551857211411[[#This Row],[CARTA]] -> #DIV/0! | R39: =+Tabla551857211411[[#This Row],[PRECIO N]]/Tabla551857211411[[#This Row],[COSTO]] -> 0
A40: 34 | B40: =+ADICIONES!A419 -> SALSA TERIYAKI | D40: =+ADICIONES!J422 -> 326.57 | E40: =+ADICIONES!J423 -> 4900 | F40: =+E40/1.08*0.08 -> 362.96296 | G40: =+Tabla551857211411[[#This Row],[VENTA]]-Tabla551857211411[[#This Row],[ICO 8%]] -> 4537.037 | H40: =+Tabla551857211411[[#This Row],[COSTO]]/Tabla551857211411[[#This Row],[BASE]] -> 0.071978694 | I40: =+Tabla551857211411[[#This Row],[BASE]]/Tabla551857211411[[#This Row],[COSTO]] -> 13.893 | J40: =+VLOOKUP(Tabla551857211411[[#This Row],[ADICIONES]],Tabla77[#All],3,0) -> 4 | K40: =+D40/(100-70)*100 -> 1088.5667 | L40: =+K40/1.08*0.08 -> 80.634568 | M40: =+Tabla551857211411[[#This Row],[PRECIO SUGERIDO]]+Tabla551857211411[[#This Row],[ICO2]] -> 1169.2012 | O40: =+N40/1.08*0.08 -> 0 | P40: =+Tabla551857211411[[#This Row],[PRECIO N]]-Tabla551857211411[[#This Row],[ICO 8%2]] -> 0 | Q40: =+Tabla551857211411[[#This Row],[COSTO]]/Tabla551857211411[[#This Row],[CARTA]] -> #DIV/0! | R40: =+Tabla551857211411[[#This Row],[PRECIO N]]/Tabla551857211411[[#This Row],[COSTO]] -> 0
A41: 35 | B41: =+ADICIONES!A431 -> SALSA WONTON | D41: =+ADICIONES!J434 -> 488.62371 | E41: =+ADICIONES!J435 -> 2900 | F41: =+E41/1.08*0.08 -> 214.81481 | G41: =+Tabla551857211411[[#This Row],[VENTA]]-Tabla551857211411[[#This Row],[ICO 8%]] -> 2685.1852 | H41: =+Tabla551857211411[[#This Row],[COSTO]]/Tabla551857211411[[#This Row],[BASE]] -> 0.18197021 | I41: =+Tabla551857211411[[#This Row],[BASE]]/Tabla551857211411[[#This Row],[COSTO]] -> 5.4954051 | J41: =+VLOOKUP(Tabla551857211411[[#This Row],[ADICIONES]],Tabla77[#All],3,0) -> #N/A | K41: =+D41/(100-70)*100 -> 1628.7457 | L41: =+K41/1.08*0.08 -> 120.64783 | M41: =+Tabla551857211411[[#This Row],[PRECIO SUGERIDO]]+Tabla551857211411[[#This Row],[ICO2]] -> 1749.3935 | O41: =+N41/1.08*0.08 -> 0 | P41: =+Tabla551857211411[[#This Row],[PRECIO N]]-Tabla551857211411[[#This Row],[ICO 8%2]] -> 0 | Q41: =+Tabla551857211411[[#This Row],[COSTO]]/Tabla551857211411[[#This Row],[CARTA]] -> #DIV/0! | R41: =+Tabla551857211411[[#This Row],[PRECIO N]]/Tabla551857211411[[#This Row],[COSTO]] -> 0
A42: 36 | B42: =+ADICIONES!A445 -> SHOT LECHE DE TIGRE | D42: =+ADICIONES!J448 -> 320.6541 | E42: =+ADICIONES!J449 -> 5000 | F42: =+E42/1.08*0.08 -> 370.37037 | G42: =+Tabla551857211411[[#This Row],[VENTA]]-Tabla551857211411[[#This Row],[ICO 8%]] -> 4629.6296 | H42: =+Tabla551857211411[[#This Row],[COSTO]]/Tabla551857211411[[#This Row],[BASE]] -> 0.069261287 | I42: =+Tabla551857211411[[#This Row],[BASE]]/Tabla551857211411[[#This Row],[COSTO]] -> 14.43808 | J42: =+VLOOKUP(Tabla551857211411[[#This Row],[ADICIONES]],Tabla77[#All],3,0) -> 7 | K42: =+D42/(100-70)*100 -> 1068.847 | L42: =+K42/1.08*0.08 -> 79.173853 | M42: =+Tabla551857211411[[#This Row],[PRECIO SUGERIDO]]+Tabla551857211411[[#This Row],[ICO2]] -> 1148.0209 | O42: =+N42/1.08*0.08 -> 0 | P42: =+Tabla551857211411[[#This Row],[PRECIO N]]-Tabla551857211411[[#This Row],[ICO 8%2]] -> 0 | Q42: =+Tabla551857211411[[#This Row],[COSTO]]/Tabla551857211411[[#This Row],[CARTA]] -> #DIV/0! | R42: =+Tabla551857211411[[#This Row],[PRECIO N]]/Tabla551857211411[[#This Row],[COSTO]] -> 0
A43: 37 | B43: =+ADICIONES!A457 -> SOLOMITO ROCOTO | D43: =+ADICIONES!J460 -> 12894 | E43: =+ADICIONES!J461 -> 11500 | F43: =+E43/1.08*0.08 -> 851.85185 | G43: =+Tabla551857211411[[#This Row],[VENTA]]-Tabla551857211411[[#This Row],[ICO 8%]] -> 10648.148 | H43: =+Tabla551857211411[[#This Row],[COSTO]]/Tabla551857211411[[#This Row],[BASE]] -> 1.2109148 | I43: =+Tabla551857211411[[#This Row],[BASE]]/Tabla551857211411[[#This Row],[COSTO]] -> 0.82582194 | J43: =+VLOOKUP(Tabla551857211411[[#This Row],[ADICIONES]],Tabla77[#All],3,0) -> 5 | K43: =+D43/(100-70)*100 -> 42980 | L43: =+K43/1.08*0.08 -> 3183.7037 | M43: =+Tabla551857211411[[#This Row],[PRECIO SUGERIDO]]+Tabla551857211411[[#This Row],[ICO2]] -> 46163.704 | O43: =+N43/1.08*0.08 -> 0 | P43: =+Tabla551857211411[[#This Row],[PRECIO N]]-Tabla551857211411[[#This Row],[ICO 8%2]] -> 0 | Q43: =+Tabla551857211411[[#This Row],[COSTO]]/Tabla551857211411[[#This Row],[CARTA]] -> #DIV/0! | R43: =+Tabla551857211411[[#This Row],[PRECIO N]]/Tabla551857211411[[#This Row],[COSTO]] -> 0
A44: 38 | B44: =+ADICIONES!A468 -> TUBOS DE CALAMAR | D44: =+ADICIONES!J471 -> 4202.1401 | E44: =+ADICIONES!J472 -> 15000 | F44: =+E44/1.08*0.08 -> 1111.1111 | G44: =+Tabla551857211411[[#This Row],[VENTA]]-Tabla551857211411[[#This Row],[ICO 8%]] -> 13888.889 | H44: =+Tabla551857211411[[#This Row],[COSTO]]/Tabla551857211411[[#This Row],[BASE]] -> 0.30255409 | I44: =+Tabla551857211411[[#This Row],[BASE]]/Tabla551857211411[[#This Row],[COSTO]] -> 3.3051941 | J44: =+VLOOKUP(Tabla551857211411[[#This Row],[ADICIONES]],Tabla77[#All],3,0) -> 3 | K44: =+D44/(100-70)*100 -> 14007.134 | L44: =+K44/1.08*0.08 -> 1037.5655 | M44: =+Tabla551857211411[[#This Row],[PRECIO SUGERIDO]]+Tabla551857211411[[#This Row],[ICO2]] -> 15044.699 | O44: =+N44/1.08*0.08 -> 0 | P44: =+Tabla551857211411[[#This Row],[PRECIO N]]-Tabla551857211411[[#This Row],[ICO 8%2]] -> 0 | Q44: =+Tabla551857211411[[#This Row],[COSTO]]/Tabla551857211411[[#This Row],[CARTA]] -> #DIV/0! | R44: =+Tabla551857211411[[#This Row],[PRECIO N]]/Tabla551857211411[[#This Row],[COSTO]] -> 0
A45: 39 | B45: =+ADICIONES!A479 -> VEGETALES SALTADOS (R) | D45: =+ADICIONES!J482 -> 2415 | E45: =+ADICIONES!J483 -> 8900 | F45: =+E45/1.08*0.08 -> 659.25926 | G45: =+Tabla551857211411[[#This Row],[VENTA]]-Tabla551857211411[[#This Row],[ICO 8%]] -> 8240.7407 | H45: =+Tabla551857211411[[#This Row],[COSTO]]/Tabla551857211411[[#This Row],[BASE]] -> 0.29305618 | I45: =+Tabla551857211411[[#This Row],[BASE]]/Tabla551857211411[[#This Row],[COSTO]] -> 3.412315 | J45: =+VLOOKUP(Tabla551857211411[[#This Row],[ADICIONES]],Tabla77[#All],3,0) -> 145 | K45: =+D45/(100-70)*100 -> 8050 | L45: =+K45/1.08*0.08 -> 596.29629 | M45: =+Tabla551857211411[[#This Row],[PRECIO SUGERIDO]]+Tabla551857211411[[#This Row],[ICO2]] -> 8646.2963 | O45: =+N45/1.08*0.08 -> 0 | P45: =+Tabla551857211411[[#This Row],[PRECIO N]]-Tabla551857211411[[#This Row],[ICO 8%2]] -> 0 | Q45: =+Tabla551857211411[[#This Row],[COSTO]]/Tabla551857211411[[#This Row],[CARTA]] -> #DIV/0! | R45: =+Tabla551857211411[[#This Row],[PRECIO N]]/Tabla551857211411[[#This Row],[COSTO]] -> 0
B46: =+ADICIONES!A491 -> ARROZ AL AJI AMARILLO | D46: =+ADICIONES!J494 -> 3055.7162 | E46: =+ADICIONES!J495 -> 8900 | F46: =+E46/1.08*0.08 -> 659.25926 | G46: =+Tabla551857211411[[#This Row],[VENTA]]-Tabla551857211411[[#This Row],[ICO 8%]] -> 8240.7407 | H46: =+Tabla551857211411[[#This Row],[COSTO]]/Tabla551857211411[[#This Row],[BASE]] -> 0.37080601 | I46: =+Tabla551857211411[[#This Row],[BASE]]/Tabla551857211411[[#This Row],[COSTO]] -> 2.6968279 | J46: =+VLOOKUP(Tabla551857211411[[#This Row],[ADICIONES]],Tabla77[#All],3,0) -> #N/A | K46: =+D46/(100-70)*100 -> 10185.721 | L46: =+K46/1.08*0.08 -> 754.49782 | M46: =+Tabla551857211411[[#This Row],[PRECIO SUGERIDO]]+Tabla551857211411[[#This Row],[ICO2]] -> 10940.218 | O46: =+N46/1.08*0.08 -> 0 | P46: =+Tabla551857211411[[#This Row],[PRECIO N]]-Tabla551857211411[[#This Row],[ICO 8%2]] -> 0 | Q46: =+Tabla551857211411[[#This Row],[COSTO]]/Tabla551857211411[[#This Row],[CARTA]] -> #DIV/0! | R46: =+Tabla551857211411[[#This Row],[PRECIO N]]/Tabla551857211411[[#This Row],[COSTO]] -> 0
B47: Total | H47: =SUBTOTAL(101,Tabla551857211411[%]) -> #DIV/0! | R47: =SUBTOTAL(109,Tabla551857211411[RATION]) -> #DIV/0!
E49: CARTA | K49: SUGERIDO COSTOS
B50: ENTRADAS | C50: DESCRIPCION | D50: COSTO | E50: VENTA | F50: ICO 8% | G50: BASE | H50: % | I50: RENTABILIDAD | J50: ROTACION | K50: PRECIO SUGERIDO | L50: ICO2 | M50: CARTA | N50: PRECIO N | O50: ICO 8%2 | P50: CARTA | Q50: % | R50: RATION
A51: 1 | B51: =+ENTRADAS!B6 -> TIRADITO TRES SABORES | C51: Finas láminas de atún fresco, salmón fresco y pesca blanca acompañados de tres diferentes salsas peruanas | D51: =+ENTRADAS!K9 -> 12979.944 | E51: =+ENTRADAS!K10 -> 57000 | F51: =+E51/1.08*0.08 -> 4222.2222 | G51: =+Tabla5518110[[#This Row],[VENTA]]-Tabla5518110[[#This Row],[ICO 8%]] -> 52777.778 | H51: =+Tabla5518110[[#This Row],[COSTO]]/Tabla5518110[[#This Row],[BASE]] -> 0.24593578 | I51: =+Tabla5518110[[#This Row],[BASE]]/Tabla5518110[[#This Row],[COSTO]] -> 4.0661022 | J51: =+VLOOKUP(Tabla5518110[[#This Row],[ENTRADAS]],Tabla77[#All],3,0) -> 199 | K51: =+D51/(100-70)*100 -> 43266.48 | L51: =+K51/1.08*0.08 -> 3204.9244 | M51: =+Tabla5518110[[#This Row],[PRECIO SUGERIDO]]+Tabla5518110[[#This Row],[ICO2]] -> 46471.404 | O51: =+N51/1.08*0.08 -> 0 | P51: =+Tabla5518110[[#This Row],[PRECIO N]]-Tabla5518110[[#This Row],[ICO 8%2]] -> 0 | Q51: =+Tabla5518110[[#This Row],[COSTO]]/Tabla5518110[[#This Row],[CARTA]] -> #DIV/0! | R51: =+Tabla5518110[[#This Row],[PRECIO N]]/Tabla5518110[[#This Row],[COSTO]] -> 0
A52: 2 | B52: =+ENTRADAS!B129 -> TARTAR DE LA CASA | C52: Trozos de salmón y pesca blanca, marinados en leche de tigre tradicional con palta, tomate concasse y toques de albaha montados sobre un espejo de mermelada de ají amarillo, acompañado con tostadas de wonton. | D52: =+ENTRADAS!K132 -> 11592.688 | E52: =+ENTRADAS!K133 -> 39000 | F52: =+E52/1.08*0.08 -> 2888.8889 | G52: =+Tabla5518110[[#This Row],[VENTA]]-Tabla5518110[[#This Row],[ICO 8%]] -> 36111.111 | H52: =+Tabla5518110[[#This Row],[COSTO]]/Tabla5518110[[#This Row],[BASE]] -> 0.32102829 | I52: =+Tabla5518110[[#This Row],[BASE]]/Tabla5518110[[#This Row],[COSTO]] -> 3.1149903 | J52: =+VLOOKUP(Tabla5518110[[#This Row],[ENTRADAS]],Tabla77[#All],3,0) -> 88 | K52: =+D52/(100-70)*100 -> 38642.294 | L52: =+K52/1.08*0.08 -> 2862.3922 | M52: =+Tabla5518110[[#This Row],[PRECIO SUGERIDO]]+Tabla5518110[[#This Row],[ICO2]] -> 41504.687 | O52: =+N52/1.08*0.08 -> 0 | P52: =+Tabla5518110[[#This Row],[PRECIO N]]-Tabla5518110[[#This Row],[ICO 8%2]] -> 0 | Q52: =+Tabla5518110[[#This Row],[COSTO]]/Tabla5518110[[#This Row],[CARTA]] -> #DIV/0! | R52: =+Tabla5518110[[#This Row],[PRECIO N]]/Tabla5518110[[#This Row],[COSTO]] -> 0
A53: 3 | B53: =+ENTRADAS!B117 -> TORNADO DE SALMÃ“N | C53: Bocados de salmón fresco, queso crema philadelphia, palta, wakame, salsa dinamita y teriyaki de maíz morado. | D53: =+ENTRADAS!K120 -> 8269.0671 | E53: =+ENTRADAS!K121 -> 43000 | F53: =+E53/1.08*0.08 -> 3185.1852 | G53: =+Tabla5518110[[#This Row],[VENTA]]-Tabla5518110[[#This Row],[ICO 8%]] -> 39814.815 | H53: =+Tabla5518110[[#This Row],[COSTO]]/Tabla5518110[[#This Row],[BASE]] -> 0.2076882 | I53: =+Tabla5518110[[#This Row],[BASE]]/Tabla5518110[[#This Row],[COSTO]] -> 4.8149101 | J53: =+VLOOKUP(Tabla5518110[[#This Row],[ENTRADAS]],Tabla77[#All],3,0) -> 105 | K53: =+D53/(100-70)*100 -> 27563.557 | L53: =+K53/1.08*0.08 -> 2041.745 | M53: =+Tabla5518110[[#This Row],[PRECIO SUGERIDO]]+Tabla5518110[[#This Row],[ICO2]] -> 29605.302 | O53: =+N53/1.08*0.08 -> 0 | P53: =+Tabla5518110[[#This Row],[PRECIO N]]-Tabla5518110[[#This Row],[ICO 8%2]] -> 0 | Q53: =+Tabla5518110[[#This Row],[COSTO]]/Tabla5518110[[#This Row],[CARTA]] -> #DIV/0! | R53: =+Tabla5518110[[#This Row],[PRECIO N]]/Tabla5518110[[#This Row],[COSTO]] -> 0
A54: 4 | B54: =+ENTRADAS!B36 -> CHICHARRONCITOS ACEVICHADOS | C54: Crujientes de chicharrón sobre una salsa cítrica de ají amarillo, acompañados de salsa criolla peruana, chips de plátano y palta. | D54: =+ENTRADAS!K39 -> 11845.561 | E54: =+ENTRADAS!K40 -> 49000 | F54: =+E54/1.08*0.08 -> 3629.6296 | G54: =+Tabla5518110[[#This Row],[VENTA]]-Tabla5518110[[#This Row],[ICO 8%]] -> 45370.37 | H54: =+Tabla5518110[[#This Row],[COSTO]]/Tabla5518110[[#This Row],[BASE]] -> 0.26108584 | I54: =+Tabla5518110[[#This Row],[BASE]]/Tabla5518110[[#This Row],[COSTO]] -> 3.8301579 | J54: =+VLOOKUP(Tabla5518110[[#This Row],[ENTRADAS]],Tabla77[#All],3,0) -> 628 | K54: =+D54/(100-70)*100 -> 39485.204 | L54: =+K54/1.08*0.08 -> 2924.8299 | M54: =+Tabla5518110[[#This Row],[PRECIO SUGERIDO]]+Tabla5518110[[#This Row],[ICO2]] -> 42410.034 | O54: =+N54/1.08*0.08 -> 0 | P54: =+Tabla5518110[[#This Row],[PRECIO N]]-Tabla5518110[[#This Row],[ICO 8%2]] -> 0 | Q54: =+Tabla5518110[[#This Row],[COSTO]]/Tabla5518110[[#This Row],[CARTA]] -> #DIV/0! | R54: =+Tabla5518110[[#This Row],[PRECIO N]]/Tabla5518110[[#This Row],[COSTO]] -> 0
A55: 5 | B55: =+ENTRADAS!B69 -> TORNADO TRUFADO | C55: Bocados de pesca blanca, rellenos con palta, queso crema philadelphia y pure de camote sobre una salsa cremosa de aji panca y trufa | D55: =+ENTRADAS!K72 -> 11555.125 | E55: =+ENTRADAS!K73 -> 42000 | F55: =+E55/1.08*0.08 -> 3111.1111 | G55: =+Tabla5518110[[#This Row],[VENTA]]-Tabla5518110[[#This Row],[ICO 8%]] -> 38888.889 | H55: =+Tabla5518110[[#This Row],[COSTO]]/Tabla5518110[[#This Row],[BASE]] -> 0.2971318 | I55: =+Tabla5518110[[#This Row],[BASE]]/Tabla5518110[[#This Row],[COSTO]] -> 3.3655099 | J55: =+VLOOKUP(Tabla5518110[[#This Row],[ENTRADAS]],Tabla77[#All],3,0) -> 79 | K55: =+D55/(100-70)*100 -> 38517.085 | L55: =+K55/1.08*0.08 -> 2853.1174 | M55: =+Tabla5518110[[#This Row],[PRECIO SUGERIDO]]+Tabla5518110[[#This Row],[ICO2]] -> 41370.202 | O55: =+N55/1.08*0.08 -> 0 | P55: =+Tabla5518110[[#This Row],[PRECIO N]]-Tabla5518110[[#This Row],[ICO 8%2]] -> 0 | Q55: =+Tabla5518110[[#This Row],[COSTO]]/Tabla5518110[[#This Row],[CARTA]] -> #DIV/0! | R55: =+Tabla5518110[[#This Row],[PRECIO N]]/Tabla5518110[[#This Row],[COSTO]] -> 0
A56: 6 | B56: =+ENTRADAS!B53 -> PULPO SALTADO | C56: Tentáculos de pulpo Parrillado en aceite de oliva y chimichurri, acompañado de papas criollas champiño, tomate cherry parrillado, cebolla y salsa huancaina | D56: =+ENTRADAS!K56 -> 30205.316 | E56: =+ENTRADAS!K57 -> 99000 | F56: =+E56/1.08*0.08 -> 7333.3333 | G56: =+Tabla5518110[[#This Row],[VENTA]]-Tabla5518110[[#This Row],[ICO 8%]] -> 91666.667 | H56: =+Tabla5518110[[#This Row],[COSTO]]/Tabla5518110[[#This Row],[BASE]] -> 0.32951254 | I56: =+Tabla5518110[[#This Row],[BASE]]/Tabla5518110[[#This Row],[COSTO]] -> 3.0347859 | J56: =+VLOOKUP(Tabla5518110[[#This Row],[ENTRADAS]],Tabla77[#All],3,0) -> 238 | K56: =+D56/(100-70)*100 -> 100684.39 | L56: =+K56/1.08*0.08 -> 7458.1027 | M56: =+Tabla5518110[[#This Row],[PRECIO SUGERIDO]]+Tabla5518110[[#This Row],[ICO2]] -> 108142.49 | O56: =+N56/1.08*0.08 -> 0 | P56: =+Tabla5518110[[#This Row],[PRECIO N]]-Tabla5518110[[#This Row],[ICO 8%2]] -> 0 | Q56: =+Tabla5518110[[#This Row],[COSTO]]/Tabla5518110[[#This Row],[CARTA]] -> #DIV/0! | R56: =+Tabla5518110[[#This Row],[PRECIO N]]/Tabla5518110[[#This Row],[COSTO]] -> 0
A57: 7 | B57: =+ENTRADAS!B105 -> LANGOSTINOS CROCANTES | C57: 5 langostinos apanados en queso parmesano, acompañados con crema melcocha y mezclum. | D57: =+ENTRADAS!K108 -> 16391.165 | E57: =+ENTRADAS!K109 -> 59000 | F57: =+E57/1.08*0.08 -> 4370.3704 | G57: =+Tabla5518110[[#This Row],[VENTA]]-Tabla5518110[[#This Row],[ICO 8%]] -> 54629.63 | H57: =+Tabla5518110[[#This Row],[COSTO]]/Tabla5518110[[#This Row],[BASE]] -> 0.30004166 | I57: =+Tabla5518110[[#This Row],[BASE]]/Tabla5518110[[#This Row],[COSTO]] -> 3.3328705 | J57: =+VLOOKUP(Tabla5518110[[#This Row],[ENTRADAS]],Tabla77[#All],3,0) -> 229 | K57: =+D57/(100-70)*100 -> 54637.216 | L57: =+K57/1.08*0.08 -> 4047.2012 | M57: =+Tabla5518110[[#This Row],[PRECIO SUGERIDO]]+Tabla5518110[[#This Row],[ICO2]] -> 58684.418 | O57: =+N57/1.08*0.08 -> 0 | P57: =+Tabla5518110[[#This Row],[PRECIO N]]-Tabla5518110[[#This Row],[ICO 8%2]] -> 0 | Q57: =+Tabla5518110[[#This Row],[COSTO]]/Tabla5518110[[#This Row],[CARTA]] -> #DIV/0! | R57: =+Tabla5518110[[#This Row],[PRECIO N]]/Tabla5518110[[#This Row],[COSTO]] -> 0
A58: 8 | B58: =+ENTRADAS!B82 -> SPRING ROLLS AJÃ DE GALLINA | C58: Clásica preparación peruana de pollo al ají de gallina envueltos en masa crocante, servidos con salsa huancaína | D58: =+ENTRADAS!K85 -> 10080.636 | E58: =+ENTRADAS!K86 -> 32000 | F58: =+E58/1.08*0.08 -> 2370.3704 | G58: =+Tabla5518110[[#This Row],[VENTA]]-Tabla5518110[[#This Row],[ICO 8%]] -> 29629.63 | H58: =+Tabla5518110[[#This Row],[COSTO]]/Tabla5518110[[#This Row],[BASE]] -> 0.34022147 | I58: =+Tabla5518110[[#This Row],[BASE]]/Tabla5518110[[#This Row],[COSTO]] -> 2.9392619 | J58: =+VLOOKUP(Tabla5518110[[#This Row],[ENTRADAS]],Tabla77[#All],3,0) -> 183 | K58: =+D58/(100-70)*100 -> 33602.121 | L58: =+K58/1.08*0.08 -> 2489.046 | M58: =+Tabla5518110[[#This Row],[PRECIO SUGERIDO]]+Tabla5518110[[#This Row],[ICO2]] -> 36091.167 | O58: =+N58/1.08*0.08 -> 0 | P58: =+Tabla5518110[[#This Row],[PRECIO N]]-Tabla5518110[[#This Row],[ICO 8%2]] -> 0 | Q58: =+Tabla5518110[[#This Row],[COSTO]]/Tabla5518110[[#This Row],[CARTA]] -> #DIV/0! | R58: =+Tabla5518110[[#This Row],[PRECIO N]]/Tabla5518110[[#This Row],[COSTO]] -> 0
A59: 9 | B59: =+ENTRADAS!B93 -> EMPANADAS ROCOTO | C59: Empanadas de maíz pintadas con tinta de calamar, rellenas de pollo al ají de gallina, servidas con salsa criolla picosa | D59: =+ENTRADAS!K96 -> 7345.8781 | E59: =+ENTRADAS!K97 -> 45000 | F59: =+E59/1.08*0.08 -> 3333.3333 | G59: =+Tabla5518110[[#This Row],[VENTA]]-Tabla5518110[[#This Row],[ICO 8%]] -> 41666.667 | H59: =+Tabla5518110[[#This Row],[COSTO]]/Tabla5518110[[#This Row],[BASE]] -> 0.17630107 | I59: =+Tabla5518110[[#This Row],[BASE]]/Tabla5518110[[#This Row],[COSTO]] -> 5.6721152 | J59: =+VLOOKUP(Tabla5518110[[#This Row],[ENTRADAS]],Tabla77[#All],3,0) -> 253 | K59: =+D59/(100-70)*100 -> 24486.26 | L59: =+K59/1.08*0.08 -> 1813.7971 | M59: =+Tabla5518110[[#This Row],[PRECIO SUGERIDO]]+Tabla5518110[[#This Row],[ICO2]] -> 26300.057 | O59: =+N59/1.08*0.08 -> 0 | P59: =+Tabla5518110[[#This Row],[PRECIO N]]-Tabla5518110[[#This Row],[ICO 8%2]] -> 0 | Q59: =+Tabla5518110[[#This Row],[COSTO]]/Tabla5518110[[#This Row],[CARTA]] -> #DIV/0! | R59: =+Tabla5518110[[#This Row],[PRECIO N]]/Tabla5518110[[#This Row],[COSTO]] -> 0
A60: 10 | B60: =+ENTRADAS!B25 -> CHIPS | C60: Crocantes de yuca y plátano con salsa huancaína y guacamole de la casa. | D60: =+ENTRADAS!K28 -> 2060.5958 | E60: =+ENTRADAS!K29 -> 29900 | F60: =+E60/1.08*0.08 -> 2214.8148 | G60: =+Tabla5518110[[#This Row],[VENTA]]-Tabla5518110[[#This Row],[ICO 8%]] -> 27685.185 | H60: =+Tabla5518110[[#This Row],[COSTO]]/Tabla5518110[[#This Row],[BASE]] -> 0.074429549 | I60: =+Tabla5518110[[#This Row],[BASE]]/Tabla5518110[[#This Row],[COSTO]] -> 13.435524 | J60: =+VLOOKUP(Tabla5518110[[#This Row],[ENTRADAS]],Tabla77[#All],3,0) -> 289 | K60: =+D60/(100-70)*100 -> 6868.6528 | L60: =+K60/1.08*0.08 -> 508.7891 | M60: =+Tabla5518110[[#This Row],[PRECIO SUGERIDO]]+Tabla5518110[[#This Row],[ICO2]] -> 7377.4419 | O60: =+N60/1.08*0.08 -> 0 | P60: =+Tabla5518110[[#This Row],[PRECIO N]]-Tabla5518110[[#This Row],[ICO 8%2]] -> 0 | Q60: =+Tabla5518110[[#This Row],[COSTO]]/Tabla5518110[[#This Row],[CARTA]] -> #DIV/0! | R60: =+Tabla5518110[[#This Row],[PRECIO N]]/Tabla5518110[[#This Row],[COSTO]] -> 0
A61: 11 | B61: =+ENTRADAS!B142 -> TRILOGIA DE CAUSAS | D61: =+ENTRADAS!K145 -> 12817.125 | E61: =+ENTRADAS!K146 -> 58000 | F61: =+E61/1.08*0.08 -> 4296.2963 | G61: =+Tabla5518110[[#This Row],[VENTA]]-Tabla5518110[[#This Row],[ICO 8%]] -> 53703.704 | H61: =+Tabla5518110[[#This Row],[COSTO]]/Tabla5518110[[#This Row],[BASE]] -> 0.2386637 | I61: =+Tabla5518110[[#This Row],[BASE]]/Tabla5518110[[#This Row],[COSTO]] -> 4.1899962 | J61: =+VLOOKUP(Tabla5518110[[#This Row],[ENTRADAS]],Tabla77[#All],3,0) -> 136 | K61: =+D61/(100-70)*100 -> 42723.749 | L61: =+K61/1.08*0.08 -> 3164.7221 | M61: =+Tabla5518110[[#This Row],[PRECIO SUGERIDO]]+Tabla5518110[[#This Row],[ICO2]] -> 45888.471 | O61: =+N61/1.08*0.08 -> 0 | P61: =+Tabla5518110[[#This Row],[PRECIO N]]-Tabla5518110[[#This Row],[ICO 8%2]] -> 0 | Q61: =+Tabla5518110[[#This Row],[COSTO]]/Tabla5518110[[#This Row],[CARTA]] -> #DIV/0! | R61: =+Tabla5518110[[#This Row],[PRECIO N]]/Tabla5518110[[#This Row],[COSTO]] -> 0
B62: Total | H62: =SUBTOTAL(101,Tabla5518110[%]) -> 0.25382181 | R62: =SUBTOTAL(109,Tabla5518110[RATION]) -> 0
E64: CARTA | K64: SUGERIDO COSTOS
B65: PARA COMPARTIR | C65: DESCRIPCION | D65: COSTO | E65: VENTA | F65: ICO 8% | G65: BASE | H65: % | I65: RENTABILIDAD | J65: ROTACION | K65: PRECIO SUGERIDO | L65: ICO2 | M65: CARTA | N65: PRECIO N | O65: ICO 8%2 | P65: CARTA | Q65: % | R65: RATION
B66: =+'PARA COMPARTIR'!B6 -> JALEA MIXTA | C66: Crocante de pescado, camarones y calamares, acompañados de yuca frita y chifles de plátano. Servida con salsa huancaína, salsa acevichada y salsa criolla. | D66: =+'PARA COMPARTIR'!K9 -> #N/A | E66: =+'PARA COMPARTIR'!K10 -> 99000 | F66: =+E66/1.08*0.08 -> 7333.3333 | G66: =+Tabla551857211[[#This Row],[VENTA]]-Tabla551857211[[#This Row],[ICO 8%]] -> 91666.667 | H66: =+Tabla551857211[[#This Row],[COSTO]]/Tabla551857211[[#This Row],[BASE]] -> #N/A | I66: =+Tabla551857211[[#This Row],[BASE]]/Tabla551857211[[#This Row],[COSTO]] -> #N/A | J66: =+VLOOKUP(Tabla551857211[[#This Row],[PARA COMPARTIR]],Tabla77[#All],3,0) -> #N/A | K66: =+D66/(100-70)*100 -> #N/A | L66: =+K66/1.08*0.08 -> #N/A | M66: =+Tabla551857211[[#This Row],[PRECIO SUGERIDO]]+Tabla551857211[[#This Row],[ICO2]] -> #N/A | N66: 99000 | O66: =+N66/1.08*0.08 -> 7333.3333 | P66: =+Tabla551857211[[#This Row],[PRECIO N]]-Tabla551857211[[#This Row],[ICO 8%2]] -> 91666.667 | Q66: =+Tabla551857211[[#This Row],[COSTO]]/Tabla551857211[[#This Row],[CARTA]] -> #N/A | R66: =+Tabla551857211[[#This Row],[PRECIO N]]/Tabla551857211[[#This Row],[COSTO]] -> #N/A
B67: =+'PARA COMPARTIR'!B24 -> PIQUEO DE MAR | C67: Ceviche de pesca blanca en leche de tigre tradicional, causa de camaron, ceviche de camarones con palta y langostinos crocantes bañados en tamarindo. | D67: =+'PARA COMPARTIR'!K26 -> 20782.775 | E67: =+'PARA COMPARTIR'!K27 -> 85000 | F67: =+E67/1.08*0.08 -> 6296.2963 | G67: =+Tabla551857211[[#This Row],[VENTA]]-Tabla551857211[[#This Row],[ICO 8%]] -> 78703.704 | H67: =+Tabla551857211[[#This Row],[COSTO]]/Tabla551857211[[#This Row],[BASE]] -> 0.26406349 | I67: =+Tabla551857211[[#This Row],[BASE]]/Tabla551857211[[#This Row],[COSTO]] -> 3.786968 | J67: =+VLOOKUP(Tabla551857211[[#This Row],[PARA COMPARTIR]],Tabla77[#All],3,0) -> 256 | K67: =+D67/(100-70)*100 -> 69275.916 | L67: =+K67/1.08*0.08 -> 5131.5494 | M67: =+Tabla551857211[[#This Row],[PRECIO SUGERIDO]]+Tabla551857211[[#This Row],[ICO2]] -> 74407.466 | O67: =+N67/1.08*0.08 -> 0 | P67: =+Tabla551857211[[#This Row],[PRECIO N]]-Tabla551857211[[#This Row],[ICO 8%2]] -> 0 | Q67: =+Tabla551857211[[#This Row],[COSTO]]/Tabla551857211[[#This Row],[CARTA]] -> #DIV/0! | R67: =+Tabla551857211[[#This Row],[PRECIO N]]/Tabla551857211[[#This Row],[COSTO]] -> 0
B68: =+'PARA COMPARTIR'!B50 -> PARRILLA MAR Y TIERRA | C68: Clásica preparación limeña de pollo desmechado, servido sobre una base de papas, bañado con una crema de ají amarillo y pecanas. Finalizado con huevo de codorniz y aceitunas | D68: =+'PARA COMPARTIR'!K53 -> 88635.967 | E68: =+'PARA COMPARTIR'!K54 -> 299000 | F68: =+E68/1.08*0.08 -> 22148.148 | G68: =+Tabla551857211[[#This Row],[VENTA]]-Tabla551857211[[#This Row],[ICO 8%]] -> 276851.85 | H68: =+Tabla551857211[[#This Row],[COSTO]]/Tabla551857211[[#This Row],[BASE]] -> 0.32015667 | I68: =+Tabla551857211[[#This Row],[BASE]]/Tabla551857211[[#This Row],[COSTO]] -> 3.1234708 | J68: =+VLOOKUP(Tabla551857211[[#This Row],[PARA COMPARTIR]],Tabla77[#All],3,0) -> 16 | K68: =+D68/(100-70)*100 -> 295453.22 | L68: =+K68/1.08*0.08 -> 21885.424 | M68: =+Tabla551857211[[#This Row],[PRECIO SUGERIDO]]+Tabla551857211[[#This Row],[ICO2]] -> 317338.65 | O68: =+N68/1.08*0.08 -> 0 | P68: =+Tabla551857211[[#This Row],[PRECIO N]]-Tabla551857211[[#This Row],[ICO 8%2]] -> 0 | Q68: =+Tabla551857211[[#This Row],[COSTO]]/Tabla551857211[[#This Row],[CARTA]] -> #DIV/0! | R68: =+Tabla551857211[[#This Row],[PRECIO N]]/Tabla551857211[[#This Row],[COSTO]] -> 0
B69: Total | H69: =SUBTOTAL(101,Tabla551857211[%]) -> #N/A | R69: =SUBTOTAL(109,Tabla551857211[RATION]) -> #N/A
E73: CARTA | K73: SUGERIDO COSTOS
B74: CEVICHES | C74: DESCRIPCION | D74: COSTO | E74: VENTA | F74: ICO 8% | G74: BASE | H74: % | I74: RENTABILIDAD | J74: ROTACION | K74: PRECIO SUGERIDO | L74: ICO2 | M74: CARTA | N74: PRECIO N | O74: ICO 8%2 | P74: CARTA | Q74: % | R74: RATION
A75: 1 | B75: =+CEVICHES!B6 -> CHEVICHE PARRILLADO | C75: Camarones, pulpo y cubos de pescado sellados a la parrilla con leche de tigre al ají amarillo, acompañado de palta, maíz choclo, chips de yuca y papa criolla crocante. | D75: =+CEVICHES!K9 -> 24518.676 | E75: =+CEVICHES!K10 -> 79000 | F75: =+E75/1.08*0.08 -> 5851.8519 | G75: =+Tabla551857178[[#This Row],[VENTA]]-Tabla551857178[[#This Row],[ICO 8%]] -> 73148.148 | H75: =+Tabla551857178[[#This Row],[COSTO]]/Tabla551857178[[#This Row],[BASE]] -> 0.33519203 | I75: =+Tabla551857178[[#This Row],[BASE]]/Tabla551857178[[#This Row],[COSTO]] -> 2.9833645 | J75: =+VLOOKUP(Tabla551857178[[#This Row],[CEVICHES]],Tabla77[#All],3,0) -> 227 | K75: =+D75/(100-70)*100 -> 81728.92 | L75: =+K75/1.08*0.08 -> 6053.9941 | M75: =+Tabla551857178[[#This Row],[PRECIO SUGERIDO]]+Tabla551857178[[#This Row],[ICO2]] -> 87782.915 | N75: 79000 | O75: =+N75/1.08*0.08 -> 5851.8519 | P75: =+Tabla551857178[[#This Row],[PRECIO N]]-Tabla551857178[[#This Row],[ICO 8%2]] -> 73148.148 | Q75: =+Tabla551857178[[#This Row],[COSTO]]/Tabla551857178[[#This Row],[CARTA]] -> 0.33519203 | R75: =+Tabla551857178[[#This Row],[PRECIO N]]/Tabla551857178[[#This Row],[COSTO]] -> 3.2220337
A76: 2 | B76: =+CEVICHES!B22 -> CEVICHE ROCOTO | C76: Pescado, calamar, camarón y palta en leche de tigre al ají rocoto, acompañado de pescado crocante | D76: =+CEVICHES!K24 -> 16550.452 | E76: =+CEVICHES!K25 -> 62000 | F76: =+E76/1.08*0.08 -> 4592.5926 | G76: =+Tabla551857178[[#This Row],[VENTA]]-Tabla551857178[[#This Row],[ICO 8%]] -> 57407.407 | H76: =+Tabla551857178[[#This Row],[COSTO]]/Tabla551857178[[#This Row],[BASE]] -> 0.28829819 | I76: =+Tabla551857178[[#This Row],[BASE]]/Tabla551857178[[#This Row],[COSTO]] -> 3.4686308 | J76: =+VLOOKUP(Tabla551857178[[#This Row],[CEVICHES]],Tabla77[#All],3,0) -> 229 | K76: =+D76/(100-70)*100 -> 55168.173 | L76: =+K76/1.08*0.08 -> 4086.5313 | M76: =+Tabla551857178[[#This Row],[PRECIO SUGERIDO]]+Tabla551857178[[#This Row],[ICO2]] -> 59254.704 | O76: =+N76/1.08*0.08 -> 0 | P76: =+Tabla551857178[[#This Row],[PRECIO N]]-Tabla551857178[[#This Row],[ICO 8%2]] -> 0 | Q76: =+Tabla551857178[[#This Row],[COSTO]]/Tabla551857178[[#This Row],[CARTA]] -> #DIV/0! | R76: =+Tabla551857178[[#This Row],[PRECIO N]]/Tabla551857178[[#This Row],[COSTO]] -> 0
A77: 3 | B77: =+CEVICHES!B61 -> MIXTO TRADICIONAL | C77: Pescado, calamar, camarón, camote, mango y maíz choclo en leche de tigre tradicional, acompañado de calamares crocantes y camote. | D77: =+CEVICHES!K64 -> 15690.988 | E77: =+CEVICHES!K65 -> 52000 | F77: =+E77/1.08*0.08 -> 3851.8519 | G77: =+Tabla551857178[[#This Row],[VENTA]]-Tabla551857178[[#This Row],[ICO 8%]] -> 48148.148 | H77: =+Tabla551857178[[#This Row],[COSTO]]/Tabla551857178[[#This Row],[BASE]] -> 0.32588976 | I77: =+Tabla551857178[[#This Row],[BASE]]/Tabla551857178[[#This Row],[COSTO]] -> 3.0685223 | J77: =+VLOOKUP(Tabla551857178[[#This Row],[CEVICHES]],Tabla77[#All],3,0) -> 360 | K77: =+D77/(100-70)*100 -> 52303.294 | L77: =+K77/1.08*0.08 -> 3874.3181 | M77: =+Tabla551857178[[#This Row],[PRECIO SUGERIDO]]+Tabla551857178[[#This Row],[ICO2]] -> 56177.612 | O77: =+N77/1.08*0.08 -> 0 | P77: =+Tabla551857178[[#This Row],[PRECIO N]]-Tabla551857178[[#This Row],[ICO 8%2]] -> 0 | Q77: =+Tabla551857178[[#This Row],[COSTO]]/Tabla551857178[[#This Row],[CARTA]] -> #DIV/0! | R77: =+Tabla551857178[[#This Row],[PRECIO N]]/Tabla551857178[[#This Row],[COSTO]] -> 0
A78: 4 | B78: =+CEVICHES!B82 -> CEVICHE PERUANO | C78: Pescado fresco del día en leche de tigre tradicional, maíz choclo, cancha y camote | D78: =+CEVICHES!K85 -> 9247.1729 | E78: =+CEVICHES!K86 -> 39900 | F78: =+E78/1.08*0.08 -> 2955.5556 | G78: =+Tabla551857178[[#This Row],[VENTA]]-Tabla551857178[[#This Row],[ICO 8%]] -> 36944.444 | H78: =+Tabla551857178[[#This Row],[COSTO]]/Tabla551857178[[#This Row],[BASE]] -> 0.25029942 | I78: =+Tabla551857178[[#This Row],[BASE]]/Tabla551857178[[#This Row],[COSTO]] -> 3.9952151 | J78: =+VLOOKUP(Tabla551857178[[#This Row],[CEVICHES]],Tabla77[#All],3,0) -> 297 | K78: =+D78/(100-70)*100 -> 30823.91 | L78: =+K78/1.08*0.08 -> 2283.2526 | M78: =+Tabla551857178[[#This Row],[PRECIO SUGERIDO]]+Tabla551857178[[#This Row],[ICO2]] -> 33107.162 | O78: =+N78/1.08*0.08 -> 0 | P78: =+Tabla551857178[[#This Row],[PRECIO N]]-Tabla551857178[[#This Row],[ICO 8%2]] -> 0 | Q78: =+Tabla551857178[[#This Row],[COSTO]]/Tabla551857178[[#This Row],[CARTA]] -> #DIV/0! | R78: =+Tabla551857178[[#This Row],[PRECIO N]]/Tabla551857178[[#This Row],[COSTO]] -> 0
A79: 5 | B79: =+CEVICHES!B114 -> CEVICHE DE CHAMPIÑON | D79: =+CEVICHES!K118 -> 9003.4438 | E79: =+CEVICHES!K119 -> 39000 | F79: =+E79/1.08*0.08 -> 2888.8889 | G79: =+Tabla551857178[[#This Row],[VENTA]]-Tabla551857178[[#This Row],[ICO 8%]] -> 36111.111 | H79: =+Tabla551857178[[#This Row],[COSTO]]/Tabla551857178[[#This Row],[BASE]] -> 0.24932614 | I79: =+Tabla551857178[[#This Row],[BASE]]/Tabla551857178[[#This Row],[COSTO]] -> 4.010811 | J79: =+VLOOKUP(Tabla551857178[[#This Row],[CEVICHES]],Tabla77[#All],3,0) -> #N/A | K79: =+D79/(100-70)*100 -> 30011.479 | L79: =+K79/1.08*0.08 -> 2223.0725 | M79: =+Tabla551857178[[#This Row],[PRECIO SUGERIDO]]+Tabla551857178[[#This Row],[ICO2]] -> 32234.552 | O79: =+N79/1.08*0.08 -> 0 | P79: =+Tabla551857178[[#This Row],[PRECIO N]]-Tabla551857178[[#This Row],[ICO 8%2]] -> 0 | Q79: =+Tabla551857178[[#This Row],[COSTO]]/Tabla551857178[[#This Row],[CARTA]] -> #DIV/0! | R79: =+Tabla551857178[[#This Row],[PRECIO N]]/Tabla551857178[[#This Row],[COSTO]] -> 0
A80: 6 | B80: =+CEVICHES!B96 -> LECHE DE TIGRE 2.0 | C80: Abundante jugo de ceviche con pescado, tempura de calamar, camote, cancha y chips de platano. | D80: =+CEVICHES!K99 -> 12929.167 | E80: =+CEVICHES!K100 -> 49900 | F80: =+E80/1.08*0.08 -> 3696.2963 | G80: =+Tabla551857178[[#This Row],[VENTA]]-Tabla551857178[[#This Row],[ICO 8%]] -> 46203.704 | H80: =+Tabla551857178[[#This Row],[COSTO]]/Tabla551857178[[#This Row],[BASE]] -> 0.27982966 | I80: =+Tabla551857178[[#This Row],[BASE]]/Tabla551857178[[#This Row],[COSTO]] -> 3.5736026 | J80: =+VLOOKUP(Tabla551857178[[#This Row],[CEVICHES]],Tabla77[#All],3,0) -> 120 | K80: =+D80/(100-70)*100 -> 43097.222 | L80: =+K80/1.08*0.08 -> 3192.3868 | M80: =+Tabla551857178[[#This Row],[PRECIO SUGERIDO]]+Tabla551857178[[#This Row],[ICO2]] -> 46289.609 | O80: =+N80/1.08*0.08 -> 0 | P80: =+Tabla551857178[[#This Row],[PRECIO N]]-Tabla551857178[[#This Row],[ICO 8%2]] -> 0 | Q80: =+Tabla551857178[[#This Row],[COSTO]]/Tabla551857178[[#This Row],[CARTA]] -> #DIV/0! | R80: =+Tabla551857178[[#This Row],[PRECIO N]]/Tabla551857178[[#This Row],[COSTO]] -> 0
B81: =+CEVICHES!B132 -> CEVICHE DE CAMARONES | D81: =+CEVICHES!K135 -> 9876.2447 | F81: =+E81/1.08*0.08 -> 0 | G81: =+Tabla551857178[[#This Row],[VENTA]]-Tabla551857178[[#This Row],[ICO 8%]] -> 0 | H81: =+Tabla551857178[[#This Row],[COSTO]]/Tabla551857178[[#This Row],[BASE]] -> #DIV/0! | I81: =+Tabla551857178[[#This Row],[BASE]]/Tabla551857178[[#This Row],[COSTO]] -> 0 | J81: =+VLOOKUP(Tabla551857178[[#This Row],[CEVICHES]],Tabla77[#All],3,0) -> 8 | K81: =+D81/(100-70)*100 -> 32920.816 | L81: =+K81/1.08*0.08 -> 2438.5789 | M81: =+Tabla551857178[[#This Row],[PRECIO SUGERIDO]]+Tabla551857178[[#This Row],[ICO2]] -> 35359.395 | N81: 39000 | O81: =+N81/1.08*0.08 -> 2888.8889 | P81: =+Tabla551857178[[#This Row],[PRECIO N]]-Tabla551857178[[#This Row],[ICO 8%2]] -> 36111.111 | Q81: =+Tabla551857178[[#This Row],[COSTO]]/Tabla551857178[[#This Row],[CARTA]] -> 0.27349601 | R81: =+Tabla551857178[[#This Row],[PRECIO N]]/Tabla551857178[[#This Row],[COSTO]] -> 3.9488693
B82: Total | H82: =SUBTOTAL(101,Tabla551857178[%]) -> #DIV/0! | R82: =SUBTOTAL(109,Tabla551857178[RATION]) -> 7.170903
E86: CARTA | K86: SUGERIDO COSTOS
B87: CAUSAS | C87: DESCRIPCION | D87: COSTO | E87: VENTA | F87: ICO 8% | G87: BASE | H87: % | I87: RENTABILIDAD | J87: ROTACION | K87: PRECIO SUGERIDO | L87: ICO2 | M87: CARTA | N87: PRECIO N | O87: ICO 8%2 | P87: CARTA | Q87: % | R87: RATION
A88: 1 | B88: =+CAUSAS!B49 -> CAUSA ACEVICHADA | C88: Causa de ají amarillo y cilantro rellena de pulpo en mayonesa al olivo (aceitunas moradas ) y palta. | D88: =+CAUSAS!K52 -> 5023.5549 | E88: =+CAUSAS!#REF! -> #REF! | F88: =+E88/1.08*0.08 -> #REF! | G88: =+Tabla5518100179[[#This Row],[VENTA]]-Tabla5518100179[[#This Row],[ICO 8%]] -> #REF! | H88: =+Tabla5518100179[[#This Row],[COSTO]]/Tabla5518100179[[#This Row],[BASE]] -> #REF! | I88: =+Tabla5518100179[[#This Row],[BASE]]/Tabla5518100179[[#This Row],[COSTO]] -> #REF! | J88: =+VLOOKUP(Tabla5518100179[[#This Row],[CAUSAS]],Tabla77[#All],3,0) -> #N/A | K88: =+D88/(100-70)*100 -> 16745.183 | L88: =+K88/1.08*0.08 -> 1240.3839 | M88: =+Tabla5518100179[[#This Row],[PRECIO SUGERIDO]]+Tabla5518100179[[#This Row],[ICO2]] -> 17985.567 | N88: 45900 | O88: =+N88/1.08*0.08 -> 3400 | P88: =+Tabla5518100179[[#This Row],[PRECIO N]]-Tabla5518100179[[#This Row],[ICO 8%2]] -> 42500 | Q88: =+Tabla5518100179[[#This Row],[COSTO]]/Tabla5518100179[[#This Row],[CARTA]] -> 0.11820129 | R88: =+Tabla5518100179[[#This Row],[PRECIO N]]/Tabla5518100179[[#This Row],[COSTO]] -> 9.136956
A89: 2 | B89: CAUSA LIMEÑA | D89: =+CAUSAS!K10 -> 5023.5549 | E89: =+CAUSAS!K11 -> 37000 | F89: =+E89/1.08*0.08 -> 2740.7407 | G89: =+Tabla5518100179[[#This Row],[VENTA]]-Tabla5518100179[[#This Row],[ICO 8%]] -> 34259.259 | H89: =+Tabla5518100179[[#This Row],[COSTO]]/Tabla5518100179[[#This Row],[BASE]] -> 0.14663349 | I89: =+Tabla5518100179[[#This Row],[BASE]]/Tabla5518100179[[#This Row],[COSTO]] -> 6.8197243 | J89: =+VLOOKUP(Tabla5518100179[[#This Row],[CAUSAS]],Tabla77[#All],3,0) -> #N/A | K89: =+D89/(100-70)*100 -> 16745.183 | L89: =+K89/1.08*0.08 -> 1240.3839 | M89: =+Tabla5518100179[[#This Row],[PRECIO SUGERIDO]]+Tabla5518100179[[#This Row],[ICO2]] -> 17985.567 | N89: 40900 | O89: =+N89/1.08*0.08 -> 3029.6296 | P89: =+Tabla5518100179[[#This Row],[PRECIO N]]-Tabla5518100179[[#This Row],[ICO 8%2]] -> 37870.37 | Q89: =+Tabla5518100179[[#This Row],[COSTO]]/Tabla5518100179[[#This Row],[CARTA]] -> 0.13265133 | R89: =+Tabla5518100179[[#This Row],[PRECIO N]]/Tabla5518100179[[#This Row],[COSTO]] -> 8.1416449
A90: 3 | B90: =+CAUSAS!B20 -> CAUSA DE ATUN | D90: =+CAUSAS!K23 -> 4214.7779 | E90: =+CAUSAS!K24 -> 37000 | F90: =+E90/1.08*0.08 -> 2740.7407 | G90: =+Tabla5518100179[[#This Row],[VENTA]]-Tabla5518100179[[#This Row],[ICO 8%]] -> 34259.259 | H90: =+Tabla5518100179[[#This Row],[COSTO]]/Tabla5518100179[[#This Row],[BASE]] -> 0.12302595 | I90: =+Tabla5518100179[[#This Row],[BASE]]/Tabla5518100179[[#This Row],[COSTO]] -> 8.1283665 | J90: =+VLOOKUP(Tabla5518100179[[#This Row],[CAUSAS]],Tabla77[#All],3,0) -> #N/A | K90: =+D90/(100-70)*100 -> 14049.26 | L90: =+K90/1.08*0.08 -> 1040.6859 | M90: =+Tabla5518100179[[#This Row],[PRECIO SUGERIDO]]+Tabla5518100179[[#This Row],[ICO2]] -> 15089.945 | N90: 40900 | O90: =+N90/1.08*0.08 -> 3029.6296 | P90: =+Tabla5518100179[[#This Row],[PRECIO N]]-Tabla5518100179[[#This Row],[ICO 8%2]] -> 37870.37 | Q90: =+Tabla5518100179[[#This Row],[COSTO]]/Tabla5518100179[[#This Row],[CARTA]] -> 0.11129487 | R90: =+Tabla5518100179[[#This Row],[PRECIO N]]/Tabla5518100179[[#This Row],[COSTO]] -> 9.7039515
A91: 4 | B91: =+CAUSAS!B35 -> CAUSA DE CAMARONES | D91: =+CAUSAS!K38 -> 9143.55 | E91: =+CAUSAS!K39 -> 37000 | F91: =+E91/1.08*0.08 -> 2740.7407 | G91: =+Tabla5518100179[[#This Row],[VENTA]]-Tabla5518100179[[#This Row],[ICO 8%]] -> 34259.259 | H91: =+Tabla5518100179[[#This Row],[COSTO]]/Tabla5518100179[[#This Row],[BASE]] -> 0.26689281 | I91: =+Tabla5518100179[[#This Row],[BASE]]/Tabla5518100179[[#This Row],[COSTO]] -> 3.7468225 | J91: =+VLOOKUP(Tabla5518100179[[#This Row],[CAUSAS]],Tabla77[#All],3,0) -> #N/A | K91: =+D91/(100-70)*100 -> 30478.5 | L91: =+K91/1.08*0.08 -> 2257.6667 | M91: =+Tabla5518100179[[#This Row],[PRECIO SUGERIDO]]+Tabla5518100179[[#This Row],[ICO2]] -> 32736.167 | N91: 40900 | O91: =+N91/1.08*0.08 -> 3029.6296 | P91: =+Tabla5518100179[[#This Row],[PRECIO N]]-Tabla5518100179[[#This Row],[ICO 8%2]] -> 37870.37 | Q91: =+Tabla5518100179[[#This Row],[COSTO]]/Tabla5518100179[[#This Row],[CARTA]] -> 0.24144337 | R91: =+Tabla5518100179[[#This Row],[PRECIO N]]/Tabla5518100179[[#This Row],[COSTO]] -> 4.4730985
B92: =+CAUSAS!B69 -> CAUSA DE SALMON ACEVICHADA | D92: =+CAUSAS!K72 -> 7822.0197 | F92: =+E92/1.08*0.08 -> 0 | G92: =+Tabla5518100179[[#This Row],[VENTA]]-Tabla5518100179[[#This Row],[ICO 8%]] -> 0 | H92: =+Tabla5518100179[[#This Row],[COSTO]]/Tabla5518100179[[#This Row],[BASE]] -> #DIV/0! | I92: =+Tabla5518100179[[#This Row],[BASE]]/Tabla5518100179[[#This Row],[COSTO]] -> 0 | J92: =+VLOOKUP(Tabla5518100179[[#This Row],[CAUSAS]],Tabla77[#All],3,0) -> #N/A | K92: =+D92/(100-70)*100 -> 26073.399 | L92: =+K92/1.08*0.08 -> 1931.3629 | M92: =+Tabla5518100179[[#This Row],[PRECIO SUGERIDO]]+Tabla5518100179[[#This Row],[ICO2]] -> 28004.762 | N92: 42500 | O92: =+N92/1.08*0.08 -> 3148.1481 | P92: =+Tabla5518100179[[#This Row],[PRECIO N]]-Tabla5518100179[[#This Row],[ICO 8%2]] -> 39351.852 | Q92: =+Tabla5518100179[[#This Row],[COSTO]]/Tabla5518100179[[#This Row],[CARTA]] -> 0.19877132 | R92: =+Tabla5518100179[[#This Row],[PRECIO N]]/Tabla5518100179[[#This Row],[COSTO]] -> 5.4333793
B93: Total | H93: =SUBTOTAL(101,Tabla5518100179[%]) -> #REF! | R93: =SUBTOTAL(109,Tabla5518100179[RATION]) -> 36.88903
E96: CARTA | K96: SUGERIDO COSTOS
B97: PESCADOS Y MARISCOS | C97: DESCRIPCION | D97: COSTO | E97: VENTA | F97: ICO 8% | G97: BASE | H97: % | I97: RENTABILIDAD | J97: ROTACION | K97: PRECIO SUGERIDO | L97: ICO2 | M97: CARTA | N97: PRECIO N | O97: ICO 8%2 | P97: CARTA | Q97: % | R97: RATION
A98: 1 | B98: =+'PESCADOS Y MARISCOS'!B7 -> PESCADO MACHO | C98: Filete de salmón a la plancha bañado en salsa cremosa de camarones, servido sobre una cama de arroz meloso al ají amarillo con tomates cherry y puerros crocantes. | D98: =+'PESCADOS Y MARISCOS'!K10 -> 23110.948 | E98: =+'PESCADOS Y MARISCOS'!K11 -> 69900 | F98: =+E98/1.08*0.08 -> 5177.7778 | G98: =+Tabla5518110158[[#This Row],[VENTA]]-Tabla5518110158[[#This Row],[ICO 8%]] -> 64722.222 | H98: =+Tabla5518110158[[#This Row],[COSTO]]/Tabla5518110158[[#This Row],[BASE]] -> 0.35707903 | I98: =+Tabla5518110158[[#This Row],[BASE]]/Tabla5518110158[[#This Row],[COSTO]] -> 2.8005005 | J98: =+VLOOKUP(Tabla5518110158[[#This Row],[PESCADOS Y MARISCOS]],Tabla77[#All],3,0) -> 242 | K98: =+D98/(100-70)*100 -> 77036.495 | L98: =+K98/1.08*0.08 -> 5706.407 | M98: =+Tabla5518110158[[#This Row],[PRECIO SUGERIDO]]+Tabla5518110158[[#This Row],[ICO2]] -> 82742.902 | O98: =+N98/1.08*0.08 -> 0 | P98: =+Tabla5518110158[[#This Row],[PRECIO N]]-Tabla5518110158[[#This Row],[ICO 8%2]] -> 0 | Q98: =+Tabla5518110158[[#This Row],[COSTO]]/Tabla5518110158[[#This Row],[CARTA]] -> #DIV/0! | R98: =+Tabla5518110158[[#This Row],[PRECIO N]]/Tabla5518110158[[#This Row],[COSTO]] -> 0
A99: 2 | B99: =+'PESCADOS Y MARISCOS'!B33 -> SALMON MALIBU | C99: Filete de salmón a la plancha bañado en salsa cremosa de camarones, servido sobre una cama de arroz meloso al ají amarillo con tomates cherry y puerros crocantes. | D99: =+'PESCADOS Y MARISCOS'!K36 -> #N/A | E99: =+'PESCADOS Y MARISCOS'!K37 -> 72900 | F99: =+E99/1.08*0.08 -> 5400 | G99: =+Tabla5518110158[[#This Row],[VENTA]]-Tabla5518110158[[#This Row],[ICO 8%]] -> 67500 | H99: =+Tabla5518110158[[#This Row],[COSTO]]/Tabla5518110158[[#This Row],[BASE]] -> #N/A | I99: =+Tabla5518110158[[#This Row],[BASE]]/Tabla5518110158[[#This Row],[COSTO]] -> #N/A | J99: =+VLOOKUP(Tabla5518110158[[#This Row],[PESCADOS Y MARISCOS]],Tabla77[#All],3,0) -> 505 | K99: =+D99/(100-70)*100 -> #N/A | L99: =+K99/1.08*0.08 -> #N/A | M99: =+Tabla5518110158[[#This Row],[PRECIO SUGERIDO]]+Tabla5518110158[[#This Row],[ICO2]] -> #N/A | O99: =+N99/1.08*0.08 -> 0 | P99: =+Tabla5518110158[[#This Row],[PRECIO N]]-Tabla5518110158[[#This Row],[ICO 8%2]] -> 0 | Q99: =+Tabla5518110158[[#This Row],[COSTO]]/Tabla5518110158[[#This Row],[CARTA]] -> #N/A | R99: =+Tabla5518110158[[#This Row],[PRECIO N]]/Tabla5518110158[[#This Row],[COSTO]] -> #N/A
A100: 3 | B100: =+'PESCADOS Y MARISCOS'!B54 -> ATUN DE LA CASA | C100: Filete de atún maguro sellado con ajonjolí negro, servido sobre una cama de arroz cremoso en leche de coco, chimichurri peruano y puerros crocantes | D100: =+'PESCADOS Y MARISCOS'!K57 -> #N/A | E100: =+'PESCADOS Y MARISCOS'!K58 -> 58900 | F100: =+E100/1.08*0.08 -> 4362.963 | G100: =+Tabla5518110158[[#This Row],[VENTA]]-Tabla5518110158[[#This Row],[ICO 8%]] -> 54537.037 | H100: =+Tabla5518110158[[#This Row],[COSTO]]/Tabla5518110158[[#This Row],[BASE]] -> #N/A | I100: =+Tabla5518110158[[#This Row],[BASE]]/Tabla5518110158[[#This Row],[COSTO]] -> #N/A | J100: =+VLOOKUP(Tabla5518110158[[#This Row],[PESCADOS Y MARISCOS]],Tabla77[#All],3,0) -> 465 | K100: =+D100/(100-70)*100 -> #N/A | L100: =+K100/1.08*0.08 -> #N/A | M100: =+Tabla5518110158[[#This Row],[PRECIO SUGERIDO]]+Tabla5518110158[[#This Row],[ICO2]] -> #N/A | O100: =+N100/1.08*0.08 -> 0 | P100: =+Tabla5518110158[[#This Row],[PRECIO N]]-Tabla5518110158[[#This Row],[ICO 8%2]] -> 0 | Q100: =+Tabla5518110158[[#This Row],[COSTO]]/Tabla5518110158[[#This Row],[CARTA]] -> #N/A | R100: =+Tabla5518110158[[#This Row],[PRECIO N]]/Tabla5518110158[[#This Row],[COSTO]] -> #N/A
A101: 4 | B101: =+'PESCADOS Y MARISCOS'!B73 -> PESCADO CHORRILLANA | C101: Clásica preparación peruana, Filete de pescado blanco rebosado en salsa al escabeche, huevos codorniz y aceitunas moradas. Acompañado con arroz blanco y yuca | D101: =+'PESCADOS Y MARISCOS'!K76 -> #N/A | E101: =+'PESCADOS Y MARISCOS'!K77 -> 54500 | F101: =+E101/1.08*0.08 -> 4037.037 | G101: =+Tabla5518110158[[#This Row],[VENTA]]-Tabla5518110158[[#This Row],[ICO 8%]] -> 50462.963 | H101: =+Tabla5518110158[[#This Row],[COSTO]]/Tabla5518110158[[#This Row],[BASE]] -> #N/A | I101: =+Tabla5518110158[[#This Row],[BASE]]/Tabla5518110158[[#This Row],[COSTO]] -> #N/A | J101: =+VLOOKUP(Tabla5518110158[[#This Row],[PESCADOS Y MARISCOS]],Tabla77[#All],3,0) -> 92 | K101: =+D101/(100-70)*100 -> #N/A | L101: =+K101/1.08*0.08 -> #N/A | M101: =+Tabla5518110158[[#This Row],[PRECIO SUGERIDO]]+Tabla5518110158[[#This Row],[ICO2]] -> #N/A | O101: =+N101/1.08*0.08 -> 0 | P101: =+Tabla5518110158[[#This Row],[PRECIO N]]-Tabla5518110158[[#This Row],[ICO 8%2]] -> 0 | Q101: =+Tabla5518110158[[#This Row],[COSTO]]/Tabla5518110158[[#This Row],[CARTA]] -> #N/A | R101: =+Tabla5518110158[[#This Row],[PRECIO N]]/Tabla5518110158[[#This Row],[COSTO]] -> #N/A
A102: 5 | B102: =+'PESCADOS Y MARISCOS'!B96 -> TRILOGÃA PERÃš | C102: Arroz peruano de camarones, ceviche tradicional de pescado y chicharrón de calamar con salsa huancaína. | D102: =+'PESCADOS Y MARISCOS'!K99 -> 15708.337 | E102: =+'PESCADOS Y MARISCOS'!K100 -> 62000 | F102: =+E102/1.08*0.08 -> 4592.5926 | G102: =+Tabla5518110158[[#This Row],[VENTA]]-Tabla5518110158[[#This Row],[ICO 8%]] -> 57407.407 | H102: =+Tabla5518110158[[#This Row],[COSTO]]/Tabla5518110158[[#This Row],[BASE]] -> 0.2736291 | I102: =+Tabla5518110158[[#This Row],[BASE]]/Tabla5518110158[[#This Row],[COSTO]] -> 3.654582 | J102: =+VLOOKUP(Tabla5518110158[[#This Row],[PESCADOS Y MARISCOS]],Tabla77[#All],3,0) -> 490 | K102: =+D102/(100-70)*100 -> 52361.125 | L102: =+K102/1.08*0.08 -> 3878.6018 | M102: =+Tabla5518110158[[#This Row],[PRECIO SUGERIDO]]+Tabla5518110158[[#This Row],[ICO2]] -> 56239.727 | O102: =+N102/1.08*0.08 -> 0 | P102: =+Tabla5518110158[[#This Row],[PRECIO N]]-Tabla5518110158[[#This Row],[ICO 8%2]] -> 0 | Q102: =+Tabla5518110158[[#This Row],[COSTO]]/Tabla5518110158[[#This Row],[CARTA]] -> #DIV/0! | R102: =+Tabla5518110158[[#This Row],[PRECIO N]]/Tabla5518110158[[#This Row],[COSTO]] -> 0
B103: Total | H103: =SUBTOTAL(101,Tabla5518110158[%]) -> #N/A | R103: =SUBTOTAL(109,Tabla5518110158[RATION]) -> #N/A
E105: CARTA | K105: SUGERIDO COSTOS
B106: ARROCES | C106: DESCRIPCION | D106: COSTO | E106: VENTA | F106: ICO 8% | G106: BASE | H106: % | I106: RENTABILIDAD | J106: ROTACION | K106: PRECIO SUGERIDO | L106: ICO2 | M106: CARTA | N106: PRECIO N | O106: ICO 8%2 | P106: CARTA | Q106: % | R106: RATION
A107: 1 | B107: =+ARROCES!B135 -> ARROZ CHAUFA SOLOMITO | D107: =+ARROCES!K138 -> 21781.999 | E107: =+ARROCES!K139 -> 62000 | F107: =+E107/1.08*0.08 -> 4592.5926 | G107: =+Tabla55[[#This Row],[VENTA]]-Tabla55[[#This Row],[ICO 8%]] -> 57407.407 | H107: =+Tabla55[[#This Row],[COSTO]]/Tabla55[[#This Row],[BASE]] -> 0.37942837 | I107: =+Tabla55[[#This Row],[BASE]]/Tabla55[[#This Row],[COSTO]] -> 2.6355436 | J107: =+VLOOKUP(Tabla55[[#This Row],[ARROCES]],Tabla77[#All],3,0) -> 6 | K107: =+D107/(100-65)*100 -> 62234.282 | L107: =+K107/1.08*0.08 -> 4609.9468 | M107: =+Tabla55[[#This Row],[PRECIO SUGERIDO]]+Tabla55[[#This Row],[ICO2]] -> 66844.229 | N107: 68000 | O107: =+N107/1.08*0.08 -> 5037.037 | P107: =+Tabla55[[#This Row],[PRECIO N]]-Tabla55[[#This Row],[ICO 8%2]] -> 62962.963 | Q107: =+Tabla55[[#This Row],[COSTO]]/Tabla55[[#This Row],[CARTA]] -> 0.34594939 | R107: =+Tabla55[[#This Row],[PRECIO N]]/Tabla55[[#This Row],[COSTO]] -> 3.1218439
A108: 2 | B108: =+ARROCES!B152 -> ARROZ CHAUFA POLLO | D108: =+ARROCES!K155 -> 12271.658 | E108: =+ARROCES!K156 -> 62000 | F108: =+E108/1.08*0.08 -> 4592.5926 | G108: =+Tabla55[[#This Row],[VENTA]]-Tabla55[[#This Row],[ICO 8%]] -> 57407.407 | H108: =+Tabla55[[#This Row],[COSTO]]/Tabla55[[#This Row],[BASE]] -> 0.21376437 | I108: =+Tabla55[[#This Row],[BASE]]/Tabla55[[#This Row],[COSTO]] -> 4.6780481 | J108: =+VLOOKUP(Tabla55[[#This Row],[ARROCES]],Tabla77[#All],3,0) -> 18 | K108: =+D108/(100-65)*100 -> 35061.88 | L108: =+K108/1.08*0.08 -> 2597.1763 | M108: =+Tabla55[[#This Row],[PRECIO SUGERIDO]]+Tabla55[[#This Row],[ICO2]] -> 37659.057 | O108: =+N108/1.08*0.08 -> 0 | P108: =+Tabla55[[#This Row],[PRECIO N]]-Tabla55[[#This Row],[ICO 8%2]] -> 0 | Q108: =+Tabla55[[#This Row],[COSTO]]/Tabla55[[#This Row],[CARTA]] -> #DIV/0! | R108: =+Tabla55[[#This Row],[PRECIO N]]/Tabla55[[#This Row],[COSTO]] -> 0
A109: 3 | B109: =+ARROCES!B170 -> ARROZ CHAUFA CAMARON | D109: =+ARROCES!K173 -> 15678.394 | E109: =+ARROCES!K174 -> 62000 | F109: =+E109/1.08*0.08 -> 4592.5926 | G109: =+Tabla55[[#This Row],[VENTA]]-Tabla55[[#This Row],[ICO 8%]] -> 57407.407 | H109: =+Tabla55[[#This Row],[COSTO]]/Tabla55[[#This Row],[BASE]] -> 0.2731075 | I109: =+Tabla55[[#This Row],[BASE]]/Tabla55[[#This Row],[COSTO]] -> 3.6615618 | J109: =+VLOOKUP(Tabla55[[#This Row],[ARROCES]],Tabla77[#All],3,0) -> #N/A | K109: =+D109/(100-65)*100 -> 44795.41 | L109: =+K109/1.08*0.08 -> 3318.1785 | M109: =+Tabla55[[#This Row],[PRECIO SUGERIDO]]+Tabla55[[#This Row],[ICO2]] -> 48113.589 | O109: =+N109/1.08*0.08 -> 0 | P109: =+Tabla55[[#This Row],[PRECIO N]]-Tabla55[[#This Row],[ICO 8%2]] -> 0 | Q109: =+Tabla55[[#This Row],[COSTO]]/Tabla55[[#This Row],[CARTA]] -> #DIV/0! | R109: =+Tabla55[[#This Row],[PRECIO N]]/Tabla55[[#This Row],[COSTO]] -> 0
A110: 4 | B110: =+ARROCES!B203 -> ARROZ DE CHANCHO | C110: Arroz meloso con vegetales,palta parrillada,chalaquita acevichada,platanito maduro y tocino crocante | D110: =+ARROCES!K206 -> 17927.628 | E110: =+ARROCES!K207 -> 62000 | F110: =+E110/1.08*0.08 -> 4592.5926 | G110: =+Tabla55[[#This Row],[VENTA]]-Tabla55[[#This Row],[ICO 8%]] -> 57407.407 | H110: =+Tabla55[[#This Row],[COSTO]]/Tabla55[[#This Row],[BASE]] -> 0.31228771 | I110: =+Tabla55[[#This Row],[BASE]]/Tabla55[[#This Row],[COSTO]] -> 3.2021754 | J110: =+VLOOKUP(Tabla55[[#This Row],[ARROCES]],Tabla77[#All],3,0) -> 74 | K110: =+D110/(100-65)*100 -> 51221.793 | L110: =+K110/1.08*0.08 -> 3794.2069 | M110: =+Tabla55[[#This Row],[PRECIO SUGERIDO]]+Tabla55[[#This Row],[ICO2]] -> 55016 | O110: =+N110/1.08*0.08 -> 0 | P110: =+Tabla55[[#This Row],[PRECIO N]]-Tabla55[[#This Row],[ICO 8%2]] -> 0 | Q110: =+Tabla55[[#This Row],[COSTO]]/Tabla55[[#This Row],[CARTA]] -> #DIV/0! | R110: =+Tabla55[[#This Row],[PRECIO N]]/Tabla55[[#This Row],[COSTO]] -> 0
A111: 6 | B111: =+ARROCES!B30 -> ARROZ PERUANO | C111: Arroz con mariscos y crocante de pescado al estilo peruano elaborado con ají amarillo, acompañado de salsa criolla. | D111: =+ARROCES!K33 -> 18315.141 | E111: =+ARROCES!K34 -> 64000 | F111: =+E111/1.08*0.08 -> 4740.7407 | G111: =+Tabla55[[#This Row],[VENTA]]-Tabla55[[#This Row],[ICO 8%]] -> 59259.259 | H111: =+Tabla55[[#This Row],[COSTO]]/Tabla55[[#This Row],[BASE]] -> 0.30906801 | I111: =+Tabla55[[#This Row],[BASE]]/Tabla55[[#This Row],[COSTO]] -> 3.2355339 | J111: =+VLOOKUP(Tabla55[[#This Row],[ARROCES]],Tabla77[#All],3,0) -> #N/A | K111: =+D111/(100-65)*100 -> 52328.975 | L111: =+K111/1.08*0.08 -> 3876.2203 | M111: =+Tabla55[[#This Row],[PRECIO SUGERIDO]]+Tabla55[[#This Row],[ICO2]] -> 56205.195 | O111: =+N111/1.08*0.08 -> 0 | P111: =+Tabla55[[#This Row],[PRECIO N]]-Tabla55[[#This Row],[ICO 8%2]] -> 0 | Q111: =+Tabla55[[#This Row],[COSTO]]/Tabla55[[#This Row],[CARTA]] -> #DIV/0! | R111: =+Tabla55[[#This Row],[PRECIO N]]/Tabla55[[#This Row],[COSTO]] -> 0
A112: 7 | B112: =+ARROCES!B112 -> ARROZ CREMOSO | C112: Arroz cremoso de mariscos en de leche de coco, queso parmesano, acompañado de fosforitos de papa. | D112: =+ARROCES!K115 -> #N/A | E112: =+ARROCES!K116 -> 64000 | F112: =+E112/1.08*0.08 -> 4740.7407 | G112: =+Tabla55[[#This Row],[VENTA]]-Tabla55[[#This Row],[ICO 8%]] -> 59259.259 | H112: =+Tabla55[[#This Row],[COSTO]]/Tabla55[[#This Row],[BASE]] -> #N/A | I112: =+Tabla55[[#This Row],[BASE]]/Tabla55[[#This Row],[COSTO]] -> #N/A | J112: =+VLOOKUP(Tabla55[[#This Row],[ARROCES]],Tabla77[#All],3,0) -> 318 | K112: =+D112/(100-65)*100 -> #N/A | L112: =+K112/1.08*0.08 -> #N/A | M112: =+Tabla55[[#This Row],[PRECIO SUGERIDO]]+Tabla55[[#This Row],[ICO2]] -> #N/A | O112: =+N112/1.08*0.08 -> 0 | P112: =+Tabla55[[#This Row],[PRECIO N]]-Tabla55[[#This Row],[ICO 8%2]] -> 0 | Q112: =+Tabla55[[#This Row],[COSTO]]/Tabla55[[#This Row],[CARTA]] -> #N/A | R112: =+Tabla55[[#This Row],[PRECIO N]]/Tabla55[[#This Row],[COSTO]] -> #N/A
A113: 10 | B113: =+ARROCES!B6 -> ARROZ ROCOTO | C113: Arroz con mariscos, elaborado con una salsa a base de cerveza negra y ají panca, acompañado con y un langostino crocante y chips de plátano. | D113: =+ARROCES!K9 -> #N/A | E113: =+ARROCES!K10 -> 70000 | F113: =+E113/1.08*0.08 -> 5185.1852 | G113: =+Tabla55[[#This Row],[VENTA]]-Tabla55[[#This Row],[ICO 8%]] -> 64814.815 | H113: =+Tabla55[[#This Row],[COSTO]]/Tabla55[[#This Row],[BASE]] -> #N/A | I113: =+Tabla55[[#This Row],[BASE]]/Tabla55[[#This Row],[COSTO]] -> #N/A | J113: =+VLOOKUP(Tabla55[[#This Row],[ARROCES]],Tabla77[#All],3,0) -> 276 | K113: =+D113/(100-65)*100 -> #N/A | L113: =+K113/1.08*0.08 -> #N/A | M113: =+Tabla55[[#This Row],[PRECIO SUGERIDO]]+Tabla55[[#This Row],[ICO2]] -> #N/A | N113: 75000 | O113: =+N113/1.08*0.08 -> 5555.5556 | P113: =+Tabla55[[#This Row],[PRECIO N]]-Tabla55[[#This Row],[ICO 8%2]] -> 69444.444 | Q113: =+Tabla55[[#This Row],[COSTO]]/Tabla55[[#This Row],[CARTA]] -> #N/A | R113: =+Tabla55[[#This Row],[PRECIO N]]/Tabla55[[#This Row],[COSTO]] -> #N/A
A114: 11 | B114: =+ARROCES!B93 -> ARROZ CHAUFA POLLO Y SOLOMO | D114: =+ARROCES!K96 -> 17833.359 | E114: =+ARROCES!K97 -> 68000 | F114: =+E114/1.08*0.08 -> 5037.037 | G114: =+Tabla55[[#This Row],[VENTA]]-Tabla55[[#This Row],[ICO 8%]] -> 62962.963 | H114: =+Tabla55[[#This Row],[COSTO]]/Tabla55[[#This Row],[BASE]] -> 0.2832357 | I114: =+Tabla55[[#This Row],[BASE]]/Tabla55[[#This Row],[COSTO]] -> 3.5306283 | J114: =+VLOOKUP(Tabla55[[#This Row],[ARROCES]],Tabla77[#All],3,0) -> 279 | K114: =+D114/(100-65)*100 -> 50952.455 | L114: =+K114/1.08*0.08 -> 3774.2559 | M114: =+Tabla55[[#This Row],[PRECIO SUGERIDO]]+Tabla55[[#This Row],[ICO2]] -> 54726.711 | O114: =+N114/1.08*0.08 -> 0 | P114: =+Tabla55[[#This Row],[PRECIO N]]-Tabla55[[#This Row],[ICO 8%2]] -> 0 | Q114: =+Tabla55[[#This Row],[COSTO]]/Tabla55[[#This Row],[CARTA]] -> #DIV/0! | R114: =+Tabla55[[#This Row],[PRECIO N]]/Tabla55[[#This Row],[COSTO]] -> 0
A115: 12 | B115: =+ARROCES!B75 -> CHAUFA VEGETARIANA | D115: =+ARROCES!K78 -> 11002.182 | E115: =+ARROCES!K79 -> 62000 | F115: =+E115/1.08*0.08 -> 4592.5926 | G115: =+Tabla55[[#This Row],[VENTA]]-Tabla55[[#This Row],[ICO 8%]] -> 57407.407 | H115: =+Tabla55[[#This Row],[COSTO]]/Tabla55[[#This Row],[BASE]] -> 0.19165092 | I115: =+Tabla55[[#This Row],[BASE]]/Tabla55[[#This Row],[COSTO]] -> 5.2178201 | J115: =+VLOOKUP(Tabla55[[#This Row],[ARROCES]],Tabla77[#All],3,0) -> 15 | K115: =+D115/(100-65)*100 -> 31434.806 | L115: =+K115/1.08*0.08 -> 2328.5042 | M115: =+Tabla55[[#This Row],[PRECIO SUGERIDO]]+Tabla55[[#This Row],[ICO2]] -> 33763.31 | O115: =+N115/1.08*0.08 -> 0 | P115: =+Tabla55[[#This Row],[PRECIO N]]-Tabla55[[#This Row],[ICO 8%2]] -> 0 | Q115: =+Tabla55[[#This Row],[COSTO]]/Tabla55[[#This Row],[CARTA]] -> #DIV/0! | R115: =+Tabla55[[#This Row],[PRECIO N]]/Tabla55[[#This Row],[COSTO]] -> 0
...

Sheet MEDELLIN GOURMET
B3: Entradas | D3: 1
B4: =+'MATRIZ CARTA'!B58 -> SPRING ROLLS AJÃ DE GALLINA | C4: =+'MATRIZ CARTA'!D58 -> 10080.636 | D4: 35000 | F4: =+C6*D3 -> 7822.0197 | K4: 35000 | L4: =+K4*1 -> 35000
B5: =+'MATRIZ CARTA'!B79 -> CEVICHE DE CHAMPIÑON | C5: =+'MATRIZ CARTA'!D79 -> 9003.4438
B6: =+'MATRIZ CARTA'!B92 -> CAUSA DE SALMON ACEVICHADA | C6: =+'MATRIZ CARTA'!D92 -> 7822.0197
B8: Fuertes | D8: 2
B9: =+'MATRIZ CARTA'!B110 -> ARROZ DE CHANCHO | C9: =+'MATRIZ CARTA'!D110 -> 17927.628
B10: =+'MATRIZ CARTA'!B124 -> LOMO ANTICUCHERO | C10: =+'MATRIZ CARTA'!D124 -> 22470.295 | D10: 67900 | F10: =+C9+C10 -> 40397.922 | K10: 67900 | L10: =+K10*2 -> 135800
B11: =+'MATRIZ CARTA'!B77 -> MIXTO TRADICIONAL | C11: =+'MATRIZ CARTA'!D77 -> 15690.988
B13: Postre | D13: 1 | F13: =+C15*D13 -> 2983.0285
B14: =+'MATRIZ CARTA'!B140 -> SPRING ROLLS DE NUTELLA | C14: =+'MATRIZ CARTA'!D140 -> 7851.0826
B15: =+'MATRIZ CARTA'!B141 -> SUSPIRO ROCOTO | C15: =+'MATRIZ CARTA'!D141 -> 2983.0285
B16: =+'MATRIZ CARTA'!B142 -> TORTA DE CHOCOLATE | C16: =+'MATRIZ CARTA'!D142 -> 9655.6686 | D16: 27000 | K16: 27000 | L16: =+K16*1 -> 27000
B18: Bebidas | H18: ANALISIS RECETA
B19: Te Hatsu | C19: 3334 | D19: 1 | E19: 15000 | F19: =+D19*C19 -> 3334 | H19: COSTO DEL PLATO | I19: =+F24 -> 61777.971 | K19: 15000 | L19: =+K19*2 -> 30000
B20: Cerveza | C20: 3333 | D20: 2 | E20: 15000 | F20: =+D20*C20 -> 6666 | H20: MARGEN DE ERROR DEL 5% | K20: 15000 | L20: =+K20*1 -> 15000
B21: Café | C21: 575 | D21: 1 | E21: 6000 | F21: =+D21*C21 -> 575 | H21: COSTO + MARGEN ERROR | I21: =+F24 -> 61777.971 | K21: 6000 | L21: =+K21*1 -> 6000
H22: VALOR DE VENTA | I22: 159000
H23: IPOCONSUMO | I23: =+I22/1.08*0.08 -> 11777.778
F24: =+F4+F10+F13+F19+F20+F21 -> 61777.971 | H24: VALOR ANTES DE IPO | I24: =+I22-I23 -> 147222.22 | L24: =SUM(L4:L22) -> 248800
H25: MARGEN. | I25: =+I21/I24 -> 0.41962395
H26: GANANCIA | I26: =+I24-I21 -> 85444.252 | L26: =+L24*35% -> 87080
H27: MARGEN PORCENTUAL | I27: =+I26/I21 -> 1.3830861

Sheet CAUSAS
B7: CAUSA LIMEÃ‘A | J7: ANALISIS RECETA
B8: Ingrediente | C8: Und | D8: Unidades Netas | E8: % Merma | F8: Unidades | G8: Costo | H8: Total costo | J8: COSTO DEL PLATO | K8: =+H9+3851 -> 4784.338
B9: AGUACATE CHOCKETTE X KILO | C9: g | D9: 50 | E9: 25 | F9: 66.667 | G9: =+VLOOKUP(Tabla1103453454455456479108131138145424430432[[#This Row],[Ingrediente]],Tabla34[#All],3,0) -> 14 | H9: =+Tabla1103453454455456479108131138145424430432[[#This Row],[Costo]]*Tabla1103453454455456479108131138145424430432[[#This Row],[Unidades]] -> 933.338 | J9: MARGEN DE ERROR DEL 5% | K9: =+K8*5% -> 239.2169
B10: CILANTRO LIMPIO X KILO | C10: g | D10: 1 | E10: 40 | F10: 1.667 | G10: =+VLOOKUP(Tabla1103453454455456479108131138145424430432[[#This Row],[Ingrediente]],Tabla34[#All],3,0) -> 5.5 | H10: =+Tabla1103453454455456479108131138145424430432[[#This Row],[Costo]]*Tabla1103453454455456479108131138145424430432[[#This Row],[Unidades]] -> 9.1685 | J10: COSTO + MARGEN ERROR | K10: =+K8+K9 -> 5023.5549
B11: HUEVO DE CODORNIZ *24UND | C11: uds | D11: 1 | E11: 0 | F11: 1 | G11: =+VLOOKUP(Tabla1103453454455456479108131138145424430432[[#This Row],[Ingrediente]],Tabla34[#All],3,0) -> 354.16667 | H11: =+Tabla1103453454455456479108131138145424430432[[#This Row],[Costo]]*Tabla1103453454455456479108131138145424430432[[#This Row],[Unidades]] -> 354.16667 | J11: VALOR DE VENTA | K11: 37000
B12: SUB. CAUSA AJI AMARILLO | C12: g | D12: 80 | E12: 0 | F12: 80 | G12: =+VLOOKUP(Tabla1103453454455456479108131138145424430432[[#This Row],[Ingrediente]],Tabla34[#All],3,0) -> 1.2544167 | H12: =+Tabla1103453454455456479108131138145424430432[[#This Row],[Costo]]*Tabla1103453454455456479108131138145424430432[[#This Row],[Unidades]] -> 100.35333 | J12: IPOCONSUMO | K12: =+K11/1.08*0.08 -> 2740.7407
B13: SUB. HUANCAINA | C13: g | D13: 15 | E13: 0 | F13: 15 | G13: =+VLOOKUP(Tabla1103453454455456479108131138145424430432[[#This Row],[Ingrediente]],Tabla34[#All],3,0) -> 12.253166 | H13: =+Tabla1103453454455456479108131138145424430432[[#This Row],[Costo]]*Tabla1103453454455456479108131138145424430432[[#This Row],[Unidades]] -> 183.79749 | J13: VALOR ANTES DE IPO | K13: =+K11-K12 -> 34259.259
B14: SUB. MAYONESA ACEVICHADA | C14: g | D14: 10 | E14: 0 | F14: 10 | G14: =+VLOOKUP(Tabla1103453454455456479108131138145424430432[[#This Row],[Ingrediente]],Tabla34[#All],3,0) -> 22.545489 | H14: =+Tabla1103453454455456479108131138145424430432[[#This Row],[Costo]]*Tabla1103453454455456479108131138145424430432[[#This Row],[Unidades]] -> 225.45489 | J14: MARGEN. | K14: =+K10/K13 -> 0.14663349
B15: SUB. POLLO LIMEÃ‘O | C15: uds | D15: 1 | E15: 0 | F15: 1 | G15: =+VLOOKUP(Tabla1103453454455456479108131138145424430432[[#This Row],[Ingrediente]],Tabla34[#All],3,0) -> 1563.6235 | H15: =+Tabla1103453454455456479108131138145424430432[[#This Row],[Costo]]*Tabla1103453454455456479108131138145424430432[[#This Row],[Unidades]] -> 1563.6235 | J15: GANANCIA | K15: =+K13-K10 -> 29235.704
B16: TOGARASHI HACHI 300 GR | C16: g | D16: 1 | E16: 0 | F16: 1 | G16: =+VLOOKUP(Tabla1103453454455456479108131138145424430432[[#This Row],[Ingrediente]],Tabla34[#All],3,0) -> 99.166667 | H16: =+Tabla1103453454455456479108131138145424430432[[#This Row],[Costo]]*Tabla1103453454455456479108131138145424430432[[#This Row],[Unidades]] -> 99.166667 | J16: MARGEN PORCENTUAL | K16: =+K15/K10 -> 5.8197243
B17: TOMATE CHERRY X KILO | C17: g | D17: 20 | E17: 10 | F17: 22.222 | G17: =+VLOOKUP(Tabla1103453454455456479108131138145424430432[[#This Row],[Ingrediente]],Tabla34[#All],3,0) -> 5 | H17: =+Tabla1103453454455456479108131138145424430432[[#This Row],[Costo]]*Tabla1103453454455456479108131138145424430432[[#This Row],[Unidades]] -> 111.11
H18: =SUBTOTAL(109,Tabla1103453454455456479108131138145424430432[Total costo]) -> 3580.179
B20: CAUSA DE ATUN | J20: ANALISIS RECETA
B21: Ingrediente | C21: Und | D21: Unidades Netas | E21: % Merma | F21: Unidades | G21: Costo | H21: Total costo | J21: COSTO DEL PLATO | K21: =+H22+3851 -> 4014.0742
B22: SUB. CAUSA AJI AMARILLO | C22: g | D22: 130 | E22: 0 | F22: 130 | G22: =+VLOOKUP(Tabla110345345445545647910813113814542443043241[[#This Row],[Ingrediente]],Tabla34[#All],3,0) -> 1.2544167 | H22: =+Tabla110345345445545647910813113814542443043241[[#This Row],[Costo]]*Tabla110345345445545647910813113814542443043241[[#This Row],[Unidades]] -> 163.07416 | J22: MARGEN DE ERROR DEL 5% | K22: =+K21*5% -> 200.70371
B23: AGUACATE CHOCKETTE X KILO | C23: g | D23: 60 | E23: 25 | F23: 80 | G23: =+VLOOKUP(Tabla110345345445545647910813113814542443043241[[#This Row],[Ingrediente]],Tabla34[#All],3,0) -> 14 | H23: =+Tabla110345345445545647910813113814542443043241[[#This Row],[Costo]]*Tabla110345345445545647910813113814542443043241[[#This Row],[Unidades]] -> 1120 | J23: COSTO + MARGEN ERROR | K23: =+K21+K22 -> 4214.7779
B24: SUB. CAUSA DE ATUN | C24: g | D24: 100 | E24: 0 | F24: 100 | G24: =+VLOOKUP(Tabla110345345445545647910813113814542443043241[[#This Row],[Ingrediente]],Tabla34[#All],3,0) -> 32.346781 | H24: =+Tabla110345345445545647910813113814542443043241[[#This Row],[Costo]]*Tabla110345345445545647910813113814542443043241[[#This Row],[Unidades]] -> 3234.6781 | J24: VALOR DE VENTA | K24: 37000
B25: FLORES COMESTIBLES (PENSAMIENTOS) | C25: g | D25: 1 | E25: 0 | F25: 1 | G25: =+VLOOKUP(Tabla110345345445545647910813113814542443043241[[#This Row],[Ingrediente]],Tabla34[#All],3,0) -> 180 | H25: =+Tabla110345345445545647910813113814542443043241[[#This Row],[Costo]]*Tabla110345345445545647910813113814542443043241[[#This Row],[Unidades]] -> 180 | J25: IPOCONSUMO | K25: =+K24/1.08*0.08 -> 2740.7407
B26: TOGARASHI HACHI 300 GR | C26: g | D26: 1 | E26: 0 | F26: 1 | G26: =+VLOOKUP(Tabla110345345445545647910813113814542443043241[[#This Row],[Ingrediente]],Tabla34[#All],3,0) -> 99.166667 | H26: =+Tabla110345345445545647910813113814542443043241[[#This Row],[Costo]]*Tabla110345345445545647910813113814542443043241[[#This Row],[Unidades]] -> 99.166667 | J26: VALOR ANTES DE IPO | K26: =+K24-K25 -> 34259.259
B27: CILANTRO LIMPIO X KILO | C27: g | D27: 1 | E27: 40 | F27: 1.667 | G27: =+VLOOKUP(Tabla110345345445545647910813113814542443043241[[#This Row],[Ingrediente]],Tabla34[#All],3,0) -> 5.5 | H27: =+Tabla110345345445545647910813113814542443043241[[#This Row],[Costo]]*Tabla110345345445545647910813113814542443043241[[#This Row],[Unidades]] -> 9.1685 | J27: MARGEN. | K27: =+K23/K26 -> 0.12302595
B28: SUB. BASE DE MAYO ACEVICHADA (ROCOTO) | C28: g | D28: 20 | E28: 0 | F28: 20 | G28: =+VLOOKUP(Tabla110345345445545647910813113814542443043241[[#This Row],[Ingrediente]],Tabla34[#All],3,0) -> 19.796649 | H28: =+Tabla110345345445545647910813113814542443043241[[#This Row],[Costo]]*Tabla110345345445545647910813113814542443043241[[#This Row],[Unidades]] -> 395.93298 | J28: GANANCIA | K28: =+K26-K23 -> 30044.481
H29: =SUBTOTAL(109,Tabla110345345445545647910813113814542443043241[Total costo]) -> 5202.0204 | J29: MARGEN PORCENTUAL | K29: =+K28/K23 -> 7.1283665
B35: CAUSA DE CAMARONES | J35: ANALISIS RECETA
B36: Ingrediente | C36: Und | D36: Unidades Netas | E36: % Merma | F36: Unidades | G36: Costo | H36: Total costo | J36: COSTO DEL PLATO | K36: =+H37+3851 -> 8708.1429
B37: CAMARON CRUDO 41-50 0% PORCIONX 7UND PAQUETE POR 10 PORCIONES | C37: uds | D37: 10 | E37: 0 | F37: 10 | G37: =+VLOOKUP(Tabla11034534544554564791081311381454244304324179[[#This Row],[Ingrediente]],Tabla34[#All],3,0) -> 485.71429 | H37: =+Tabla11034534544554564791081311381454244304324179[[#This Row],[Costo]]*Tabla11034534544554564791081311381454244304324179[[#This Row],[Unidades]] -> 4857.1429 | J37: MARGEN DE ERROR DEL 5% | K37: =+K36*5% -> 435.40714
B38: CILANTRO LIMPIO X KILO | C38: g | D38: 5 | E38: 40 | F38: 8.333 | G38: =+VLOOKUP(Tabla11034534544554564791081311381454244304324179[[#This Row],[Ingrediente]],Tabla34[#All],3,0) -> 5.5 | H38: =+Tabla11034534544554564791081311381454244304324179[[#This Row],[Costo]]*Tabla11034534544554564791081311381454244304324179[[#This Row],[Unidades]] -> 45.8315 | J38: COSTO + MARGEN ERROR | K38: =+K36+K37 -> 9143.55
B39: HUEVO DE CODORNIZ *24UND | C39: uds | D39: 1.5 | E39: 0 | F39: 1.5 | G39: =+VLOOKUP(Tabla11034534544554564791081311381454244304324179[[#This Row],[Ingrediente]],Tabla34[#All],3,0) -> 354.16667 | H39: =+Tabla11034534544554564791081311381454244304324179[[#This Row],[Costo]]*Tabla11034534544554564791081311381454244304324179[[#This Row],[Unidades]] -> 531.25 | J39: VALOR DE VENTA | K39: 37000
B40: SUB. CAUSA AJI AMARILLO | C40: g | D40: 130 | E40: 0 | F40: 130 | G40: =+VLOOKUP(Tabla11034534544554564791081311381454244304324179[[#This Row],[Ingrediente]],Tabla34[#All],3,0) -> 1.2544167 | H40: =+Tabla11034534544554564791081311381454244304324179[[#This Row],[Costo]]*Tabla11034534544554564791081311381454244304324179[[#This Row],[Unidades]] -> 163.07416 | J40: IPOCONSUMO | K40: =+K39/1.08*0.08 -> 2740.7407
B41: SUB. CHALACA | C41: g | D41: 25 | E41: 0 | F41: 25 | G41: =+VLOOKUP(Tabla11034534544554564791081311381454244304324179[[#This Row],[Ingrediente]],Tabla34[#All],3,0) -> 11.132676 | H41: =+Tabla11034534544554564791081311381454244304324179[[#This Row],[Costo]]*Tabla11034534544554564791081311381454244304324179[[#This Row],[Unidades]] -> 278.31689 | J41: VALOR ANTES DE IPO | K41: =+K39-K40 -> 34259.259
B42: SUB. GUACAMOLE (ROCOTO) | C42: g | D42: 10 | E42: 0 | F42: 10 | G42: =+VLOOKUP(Tabla11034534544554564791081311381454244304324179[[#This Row],[Ingrediente]],Tabla34[#All],3,0) -> 24.804271 | H42: =+Tabla11034534544554564791081311381454244304324179[[#This Row],[Costo]]*Tabla11034534544554564791081311381454244304324179[[#This Row],[Unidades]] -> 248.04271 | J42: MARGEN. | K42: =+K38/K41 -> 0.26689281
B43: SUB. MAYONESA ACEVICHADA | C43: g | D43: 20 | E43: 0 | F43: 20 | G43: =+VLOOKUP(Tabla11034534544554564791081311381454244304324179[[#This Row],[Ingrediente]],Tabla34[#All],3,0) -> 22.545489 | H43: =+Tabla11034534544554564791081311381454244304324179[[#This Row],[Costo]]*Tabla11034534544554564791081311381454244304324179[[#This Row],[Unidades]] -> 450.90977 | J43: GANANCIA | K43: =+K41-K38 -> 25115.709
B44: SUB. QUINUA POP | C44: g | D44: 5 | E44: 0 | F44: 5 | G44: =+VLOOKUP(Tabla11034534544554564791081311381454244304324179[[#This Row],[Ingrediente]],Tabla34[#All],3,0) -> 5.9757462 | H44: =+Tabla11034534544554564791081311381454244304324179[[#This Row],[Costo]]*Tabla11034534544554564791081311381454244304324179[[#This Row],[Unidades]] -> 29.878731 | J44: MARGEN PORCENTUAL | K44: =+K43/K38 -> 2.7468225
B45: SUB. SALSA GOLF | C45: g | D45: 60 | E45: 0 | F45: 60 | G45: =+VLOOKUP(Tabla11034534544554564791081311381454244304324179[[#This Row],[Ingrediente]],Tabla34[#All],3,0) -> 25.084593 | H45: =+Tabla11034534544554564791081311381454244304324179[[#This Row],[Costo]]*Tabla11034534544554564791081311381454244304324179[[#This Row],[Unidades]] -> 1505.0756
B46: TOMATE CHERRY X KILO | C46: g | D46: 20 | E46: 10 | F46: 22.222 | G46: =+VLOOKUP(Tabla11034534544554564791081311381454244304324179[[#This Row],[Ingrediente]],Tabla34[#All],3,0) -> 5 | H46: =+Tabla11034534544554564791081311381454244304324179[[#This Row],[Costo]]*Tabla11034534544554564791081311381454244304324179[[#This Row],[Unidades]] -> 111.11
H47: =SUBTOTAL(109,Tabla11034534544554564791081311381454244304324179[Total costo]) -> 8220.6322
B49: CAUSA ACEVICHADA | J49: ANALISIS RECETA
B50: Ingrediente | C50: Und | D50: Unidades Netas | E50: % Merma | F50: Unidades | G50: Costo | H50: Total costo | J50: COSTO DEL PLATO | K50: =+H51+3851 -> 4784.338
B51: AGUACATE CHOCKETTE X KILO | C51: g | D51: 50 | E51: 25 | F51: 66.667 | G51: =+VLOOKUP(Tabla11034534544554564791081311381454244304324179216[[#This Row],[Ingrediente]],Tabla34[#All],3,0) -> 14 | H51: =+Tabla11034534544554564791081311381454244304324179216[[#This Row],[Costo]]*Tabla11034534544554564791081311381454244304324179216[[#This Row],[Unidades]] -> 933.338 | J51: MARGEN DE ERROR DEL 5% | K51: =+K50*5% -> 239.2169
B52: AJI ROCOTO X KILO | C52: g | D52: 5 | E52: 60 | F52: 12.5 | G52: =+VLOOKUP(Tabla11034534544554564791081311381454244304324179216[[#This Row],[Ingrediente]],Tabla34[#All],3,0) -> 14 | H52: =+Tabla11034534544554564791081311381454244304324179216[[#This Row],[Costo]]*Tabla11034534544554564791081311381454244304324179216[[#This Row],[Unidades]] -> 175 | J52: COSTO + MARGEN ERROR | K52: =+K50+K51 -> 5023.5549
B53: CEBOLLA MORADA LIMPIA | C53: g | D53: 20 | E53: 10 | F53: 22.222 | G53: =+VLOOKUP(Tabla11034534544554564791081311381454244304324179216[[#This Row],[Ingrediente]],Tabla34[#All],3,0) -> 3.8 | H53: =+Tabla11034534544554564791081311381454244304324179216[[#This Row],[Costo]]*Tabla11034534544554564791081311381454244304324179216[[#This Row],[Unidades]] -> 84.4436 | J53: VALOR DE VENTA | K53: 37000
B54: CILANTRO LIMPIO X KILO | C54: g | D54: 5 | E54: 40 | F54: 8.333 | G54: =+VLOOKUP(Tabla11034534544554564791081311381454244304324179216[[#This Row],[Ingrediente]],Tabla34[#All],3,0) -> 5.5 | H54: =+Tabla11034534544554564791081311381454244304324179216[[#This Row],[Costo]]*Tabla11034534544554564791081311381454244304324179216[[#This Row],[Unidades]] -> 45.8315 | J54: IPOCONSUMO | K54: =+K53/1.08*0.08 -> 2740.7407
B55: FILETE DE ATUN ENTERO KG | C55: g | D55: 100 | E55: 10 | F55: 111.111 | G55: =+VLOOKUP(Tabla11034534544554564791081311381454244304324179216[[#This Row],[Ingrediente]],Tabla34[#All],3,0) -> 51.296296 | H55: =+Tabla11034534544554564791081311381454244304324179216[[#This Row],[Costo]]*Tabla11034534544554564791081311381454244304324179216[[#This Row],[Unidades]] -> 5699.5828 | J55: VALOR ANTES DE IPO | K55: =+K53-K54 -> 34259.259
B56: HARINA DE TRIGO HAZ DE OROS BOLSA X550g | C56: g | D56: 2 | E56: 0 | F56: 2 | G56: =+VLOOKUP(Tabla11034534544554564791081311381454244304324179216[[#This Row],[Ingrediente]],Tabla34[#All],3,0) -> 4.746 | H56: =+Tabla11034534544554564791081311381454244304324179216[[#This Row],[Costo]]*Tabla11034534544554564791081311381454244304324179216[[#This Row],[Unidades]] -> 9.492 | J56: MARGEN. | K56: =+K52/K55 -> 0.14663349
B57: MAYOESA ALASENA X475G | C57: g | D57: 15 | E57: 0 | F57: 15 | G57: =+VLOOKUP(Tabla11034534544554564791081311381454244304324179216[[#This Row],[Ingrediente]],Tabla34[#All],3,0) -> 32 | H57: =+Tabla11034534544554564791081311381454244304324179216[[#This Row],[Costo]]*Tabla11034534544554564791081311381454244304324179216[[#This Row],[Unidades]] -> 480 | J57: GANANCIA | K57: =+K55-K52 -> 29235.704
B58: PIMIENTA NEGRA MOLIDA BADIA 453GR | C58: g | D58: 1 | E58: 0 | F58: 1 | G58: =+VLOOKUP(Tabla11034534544554564791081311381454244304324179216[[#This Row],[Ingrediente]],Tabla34[#All],3,0) -> 94.613742 | H58: =+Tabla11034534544554564791081311381454244304324179216[[#This Row],[Costo]]*Tabla11034534544554564791081311381454244304324179216[[#This Row],[Unidades]] -> 94.613742 | J58: MARGEN PORCENTUAL | K58: =+K57/K52 -> 5.8197243
B59: SAL REFISAL X 1000G | C59: g | D59: 1 | E59: 0 | F59: 1 | G59: =+VLOOKUP(Tabla11034534544554564791081311381454244304324179216[[#This Row],[Ingrediente]],Tabla34[#All],3,0) -> 2.6999076 | H59: =+Tabla11034534544554564791081311381454244304324179216[[#This Row],[Costo]]*Tabla11034534544554564791081311381454244304324179216[[#This Row],[Unidades]] -> 2.6999076
B60: SUB. BASE LECHE DE TIGRE | C60: g | D60: 100 | E60: 0 | F60: 100 | G60: =+VLOOKUP(Tabla11034534544554564791081311381454244304324179216[[#This Row],[Ingrediente]],Tabla34[#All],3,0) -> 10.179495 | H60: =+Tabla11034534544554564791081311381454244304324179216[[#This Row],[Costo]]*Tabla11034534544554564791081311381454244304324179216[[#This Row],[Unidades]] -> 1017.9495
B61: SUB. CAUSA AJI AMARILLO | C61: g | D61: 100 | E61: 0 | F61: 100 | G61: =+VLOOKUP(Tabla11034534544554564791081311381454244304324179216[[#This Row],[Ingrediente]],Tabla34[#All],3,0) -> 1.2544167 | H61: =+Tabla11034534544554564791081311381454244304324179216[[#This Row],[Costo]]*Tabla11034534544554564791081311381454244304324179216[[#This Row],[Unidades]] -> 125.44167
B62: SUB. HUEVO BATIDO | C62: g | D62: 10 | E62: 0 | F62: 10 | G62: =+VLOOKUP(Tabla11034534544554564791081311381454244304324179216[[#This Row],[Ingrediente]],Tabla34[#All],3,0) -> 23.747278 | H62: =+Tabla11034534544554564791081311381454244304324179216[[#This Row],[Costo]]*Tabla11034534544554564791081311381454244304324179216[[#This Row],[Unidades]] -> 237.47278
B63: SUB. PASTA DE AJO | C63: g | D63: 5 | E63: 0 | F63: 5 | G63: =+VLOOKUP(Tabla11034534544554564791081311381454244304324179216[[#This Row],[Ingrediente]],Tabla34[#All],3,0) -> 10.625185 | H63: =+Tabla11034534544554564791081311381454244304324179216[[#This Row],[Costo]]*Tabla11034534544554564791081311381454244304324179216[[#This Row],[Unidades]] -> 53.125927
B64: SUB. PULPO MEXICANO (ROCOTO)*150G | C64: uds | D64: 0.4 | E64: 0 | F64: 0.4 | G64: =+VLOOKUP(Tabla11034534544554564791081311381454244304324179216[[#This Row],[Ingrediente]],Tabla34[#All],3,0) -> 20955.187 | H64: =+Tabla11034534544554564791081311381454244304324179216[[#This Row],[Costo]]*Tabla11034534544554564791081311381454244304324179216[[#This Row],[Unidades]] -> 8382.0749
H65: =SUBTOTAL(109,Tabla11034534544554564791081311381454244304324179216[Total costo]) -> 17341.066
B69: CAUSA DE SALMON ACEVICHADA | J69: ANALISIS RECETA
B70: Ingrediente | C70: Und | D70: Unidades Netas | E70: % Merma | F70: Unidades | G70: Costo | H70: Total costo | J70: COSTO DEL PLATO | K70: =+Tabla11034534544554564791081311381454244304324179216143[[#Totals],[Total costo]] -> 7449.5426
B71: SUB. CAUSA AJI AMARILLO | C71: g | D71: 80 | E71: 0 | F71: 80 | G71: =+VLOOKUP(Tabla11034534544554564791081311381454244304324179216143[[#This Row],[Ingrediente]],Tabla34[#All],3,0) -> 1.2544167 | H71: =+Tabla11034534544554564791081311381454244304324179216143[[#This Row],[Costo]]*Tabla11034534544554564791081311381454244304324179216143[[#This Row],[Unidades]] -> 100.35333 | J71: MARGEN DE ERROR DEL 5% | K71: =+K70*5% -> 372.47713
B72: SUB. TARTAR DE SALMON | C72: g | D72: 103 | E72: 0 | F72: 103 | G72: =+VLOOKUP(Tabla11034534544554564791081311381454244304324179216143[[#This Row],[Ingrediente]],Tabla34[#All],3,0) -> 51.411917 | H72: =+Tabla11034534544554564791081311381454244304324179216143[[#This Row],[Costo]]*Tabla11034534544554564791081311381454244304324179216143[[#This Row],[Unidades]] -> 5295.4275 | J72: COSTO + MARGEN ERROR | K72: =+K70+K71 -> 7822.0197
B73: SUB. CHALACA | C73: g | D73: 25 | E73: 0 | F73: 25 | G73: =+VLOOKUP(Tabla11034534544554564791081311381454244304324179216143[[#This Row],[Ingrediente]],Tabla34[#All],3,0) -> 11.132676 | H73: =+Tabla11034534544554564791081311381454244304324179216143[[#This Row],[Costo]]*Tabla11034534544554564791081311381454244304324179216143[[#This Row],[Unidades]] -> 278.31689 | J73: VALOR DE VENTA
B74: AGUACATE CHOCKETTE X KILO | C74: g | D74: 60 | E74: 25 | F74: 80 | G74: =+VLOOKUP(Tabla11034534544554564791081311381454244304324179216143[[#This Row],[Ingrediente]],Tabla34[#All],3,0) -> 14 | H74: =+Tabla11034534544554564791081311381454244304324179216143[[#This Row],[Costo]]*Tabla11034534544554564791081311381454244304324179216143[[#This Row],[Unidades]] -> 1120 | J74: IPOCONSUMO | K74: =+K73/1.08*0.08 -> 0
B75: SUB. BASE DE MAYO ACEVICHADA (ROCOTO) | C75: g | D75: 25 | E75: 0 | F75: 25 | G75: =+VLOOKUP(Tabla11034534544554564791081311381454244304324179216143[[#This Row],[Ingrediente]],Tabla34[#All],3,0) -> 19.796649 | H75: =+Tabla11034534544554564791081311381454244304324179216143[[#This Row],[Costo]]*Tabla11034534544554564791081311381454244304324179216143[[#This Row],[Unidades]] -> 494.91623 | J75: VALOR ANTES DE IPO | K75: =+K73-K74 -> 0
B76: TOGARASHI HACHI 300 GR | C76: g | D76: 1 | E76: 0 | F76: 1 | G76: =+VLOOKUP(Tabla11034534544554564791081311381454244304324179216143[[#This Row],[Ingrediente]],Tabla34[#All],3,0) -> 99.166667 | H76: =+Tabla11034534544554564791081311381454244304324179216143[[#This Row],[Costo]]*Tabla11034534544554564791081311381454244304324179216143[[#This Row],[Unidades]] -> 99.166667 | J76: MARGEN. | K76: =+K72/K75 -> #DIV/0!
B77: LIMON TAHITI X KILO | C77: g | D77: 3 | E77: 78 | F77: 13.636 | G77: =+VLOOKUP(Tabla11034534544554564791081311381454244304324179216143[[#This Row],[Ingrediente]],Tabla34[#All],3,0) -> 4.5 | H77: =+Tabla11034534544554564791081311381454244304324179216143[[#This Row],[Costo]]*Tabla11034534544554564791081311381454244304324179216143[[#This Row],[Unidades]] -> 61.362 | J77: GANANCIA | K77: =+K75-K72 -> -7822.0197
H78: =SUBTOTAL(109,Tabla11034534544554564791081311381454244304324179216143[Total costo]) -> 7449.5426 | J78: MARGEN PORCENTUAL | K78: =+K77/K72 -> -1
J83: ANALISIS RECETA
B84: Ingrediente | C84: Und | D84: Unidades Netas | E84: % Merma | F84: Unidades | G84: Costo | H84: Total costo | J84: COSTO DEL PLATO | K84: =+Tabla11034534544554564791081311381454244304324179216143217[[#Totals],[Total costo]] -> 13380.385
B85: SUB. CAUSA AJI AMARILLO | C85: g | D85: 120 | E85: 0 | F85: 120 | G85: =+VLOOKUP(Tabla11034534544554564791081311381454244304324179216143217[[#This Row],[Ingrediente]],Tabla34[#All],3,0) -> 1.2544167 | H85: =+Tabla11034534544554564791081311381454244304324179216143217[[#This Row],[Costo]]*Tabla11034534544554564791081311381454244304324179216143217[[#This Row],[Unidades]] -> 150.53 | J85: MARGEN DE ERROR DEL 5% | K85: =+K84*5% -> 669.01924
B86: AGUACATE CHOCKETTE X KILO | C86: g | D86: 60 | E86: 25 | F86: 80 | G86: =+VLOOKUP(Tabla11034534544554564791081311381454244304324179216143217[[#This Row],[Ingrediente]],Tabla34[#All],3,0) -> 14 | H86: =+Tabla11034534544554564791081311381454244304324179216143217[[#This Row],[Costo]]*Tabla11034534544554564791081311381454244304324179216143217[[#This Row],[Unidades]] -> 1120 | J86: COSTO + MARGEN ERROR | K86: =+K84+K85 -> 14049.404
B87: SUB. PULPA DE CANGREJO | C87: uds | D87: 1 | E87: 0 | F87: 1 | G87: =+VLOOKUP(Tabla11034534544554564791081311381454244304324179216143217[[#This Row],[Ingrediente]],Tabla34[#All],3,0) -> 10536.305 | H87: =+Tabla11034534544554564791081311381454244304324179216143217[[#This Row],[Costo]]*Tabla11034534544554564791081311381454244304324179216143217[[#This Row],[Unidades]] -> 10536.305 | J87: VALOR DE VENTA | K87: 45900
B88: SUB. MAYONESA ACEVICHADA | C88: g | D88: 20 | E88: 0 | F88: 20 | G88: =+VLOOKUP(Tabla11034534544554564791081311381454244304324179216143217[[#This Row],[Ingrediente]],Tabla34[#All],3,0) -> 22.545489 | H88: =+Tabla11034534544554564791081311381454244304324179216143217[[#This Row],[Costo]]*Tabla11034534544554564791081311381454244304324179216143217[[#This Row],[Unidades]] -> 450.90977 | J88: IPOCONSUMO | K88: =+K87/1.08*0.08 -> 3400
B89: MAYOESA ALASENA X475G | C89: g | D89: 10 | E89: 0 | F89: 10 | G89: =+VLOOKUP(Tabla11034534544554564791081311381454244304324179216143217[[#This Row],[Ingrediente]],Tabla34[#All],3,0) -> 32 | H89: =+Tabla11034534544554564791081311381454244304324179216143217[[#This Row],[Costo]]*Tabla11034534544554564791081311381454244304324179216143217[[#This Row],[Unidades]] -> 320 | J89: VALOR ANTES DE IPO | K89: =+K87-K88 -> 42500
B90: TOMATE CHERRY X KILO | C90: g | D90: 14 | E90: 0 | F90: 14 | G90: =+VLOOKUP(Tabla11034534544554564791081311381454244304324179216143217[[#This Row],[Ingrediente]],Tabla34[#All],3,0) -> 5 | H90: =+Tabla11034534544554564791081311381454244304324179216143217[[#This Row],[Costo]]*Tabla11034534544554564791081311381454244304324179216143217[[#This Row],[Unidades]] -> 70 | J90: MARGEN. | K90: =+K86/K89 -> 0.33057421
B91: CILANTRO LIMPIO X KILO | C91: g | D91: 2 | E91: 40 | F91: 3.333 | G91: =+VLOOKUP(Tabla11034534544554564791081311381454244304324179216143217[[#This Row],[Ingrediente]],Tabla34[#All],3,0) -> 5.5 | H91: =+Tabla11034534544554564791081311381454244304324179216143217[[#This Row],[Costo]]*Tabla11034534544554564791081311381454244304324179216143217[[#This Row],[Unidades]] -> 18.3315 | J91: GANANCIA | K91: =+K89-K86 -> 28450.596
B92: HUEVO DE CODORNIZ *24UND | C92: uds | D92: 2 | E92: 0 | F92: 2 | G92: =+VLOOKUP(Tabla11034534544554564791081311381454244304324179216143217[[#This Row],[Ingrediente]],Tabla34[#All],3,0) -> 354.16667 | H92: =+Tabla11034534544554564791081311381454244304324179216143217[[#This Row],[Costo]]*Tabla11034534544554564791081311381454244304324179216143217[[#This Row],[Unidades]] -> 708.33333 | J92: MARGEN PORCENTUAL | K92: =+K91/K86 -> 2.0250393
B93: SUB. QUINUA POP | C93: g | D93: 1 | E93: 0 | F93: 1 | G93: =+VLOOKUP(Tabla11034534544554564791081311381454244304324179216143217[[#This Row],[Ingrediente]],Tabla34[#All],3,0) -> 5.9757462 | H93: =+Tabla11034534544554564791081311381454244304324179216143217[[#This Row],[Costo]]*Tabla11034534544554564791081311381454244304324179216143217[[#This Row],[Unidades]] -> 5.9757462
H94: =SUBTOTAL(109,Tabla11034534544554564791081311381454244304324179216143217[Total costo]) -> 13380.385

Sheet CEVICHES
B6: CHEVICHE PARRILLADO | J6: ANALISIS RECETA
B7: Ingrediente | C7: Und | D7: Unidades Netas | E7: % Merma | F7: Unidades | G7: Costo | H7: Total costo | J7: COSTO DEL PLATO | K7: =SUM(Tabla1103453454455456479108135149[Total costo]) -> 23351.12
B8: ACEITE VEGETAL X 20LT | C8: g | D8: 15 | E8: 0 | F8: 15 | G8: =+VLOOKUP(Tabla1103453454455456479108135149[[#This Row],[Ingrediente]],Tabla34[#All],3,0) -> 8.2499667 | H8: =+Tabla1103453454455456479108135149[[#This Row],[Costo]]*Tabla1103453454455456479108135149[[#This Row],[Unidades]] -> 123.7495 | J8: MARGEN DE ERROR DEL 5% | K8: =+K7*5% -> 1167.556
B9: AGUACATE CHOCKETTE X KILO | C9: g | D9: 80 | E9: 25 | F9: 106.667 | G9: =+VLOOKUP(Tabla1103453454455456479108135149[[#This Row],[Ingrediente]],Tabla34[#All],3,0) -> 14 | H9: =+Tabla1103453454455456479108135149[[#This Row],[Costo]]*Tabla1103453454455456479108135149[[#This Row],[Unidades]] -> 1493.338 | J9: COSTO + MARGEN ERROR | K9: =+K7+K8 -> 24518.676
B10: CAMARON CRUDO 41-50 0% PORCIONX 7UND PAQUETE POR 10 PORCIONES | C10: uds | D10: 7 | E10: 0 | F10: 7 | G10: =+VLOOKUP(Tabla1103453454455456479108135149[[#This Row],[Ingrediente]],Tabla34[#All],3,0) -> 485.71429 | H10: =+Tabla1103453454455456479108135149[[#This Row],[Costo]]*Tabla1103453454455456479108135149[[#This Row],[Unidades]] -> 3400 | J10: VALOR DE VENTA | K10: 79000
B11: CEBOLLA MORADA LIMPIA | C11: g | D11: 40 | E11: 27 | F11: 54.795 | G11: =+VLOOKUP(Tabla1103453454455456479108135149[[#This Row],[Ingrediente]],Tabla34[#All],3,0) -> 3.8 | H11: =+Tabla1103453454455456479108135149[[#This Row],[Costo]]*Tabla1103453454455456479108135149[[#This Row],[Unidades]] -> 208.221 | J11: IPOCONSUMO | K11: =+K10/1.08*0.08 -> 5851.8519
B12: CILANTRO LIMPIO X KILO | C12: g | D12: 3 | E12: 40 | F12: 5 | G12: =+VLOOKUP(Tabla1103453454455456479108135149[[#This Row],[Ingrediente]],Tabla34[#All],3,0) -> 5.5 | H12: =+Tabla1103453454455456479108135149[[#This Row],[Costo]]*Tabla1103453454455456479108135149[[#This Row],[Unidades]] -> 27.5 | J12: VALOR ANTES DE IPO | K12: =+K10-K11 -> 73148.148
B13: FILETE DE TILAPIA FRESCA LO | C13: g | D13: 150 | E13: 10 | F13: 166.667 | G13: =+VLOOKUP(Tabla1103453454455456479108135149[[#This Row],[Ingrediente]],Tabla34[#All],3,0) -> 37 | H13: =+Tabla1103453454455456479108135149[[#This Row],[Costo]]*Tabla1103453454455456479108135149[[#This Row],[Unidades]] -> 6166.679 | J13: MARGEN. | K13: =+K9/K12 -> 0.33519203
B14: MAIZ TIERNO METOO VACUMX 340G DRE 285G | C14: g | D14: 24 | E14: 0 | F14: 24 | G14: =+VLOOKUP(Tabla1103453454455456479108135149[[#This Row],[Ingrediente]],Tabla34[#All],3,0) -> 21.754386 | H14: =+Tabla1103453454455456479108135149[[#This Row],[Costo]]*Tabla1103453454455456479108135149[[#This Row],[Unidades]] -> 522.10526 | J14: GANANCIA | K14: =+K12-K9 -> 48629.472
B15: PAPA CRIOLLA BALIN O CHIRIYA | C15: g | D15: 150 | E15: 5 | F15: 157.895 | G15: =+VLOOKUP(Tabla1103453454455456479108135149[[#This Row],[Ingrediente]],Tabla34[#All],3,0) -> 4.5 | H15: =+Tabla1103453454455456479108135149[[#This Row],[Costo]]*Tabla1103453454455456479108135149[[#This Row],[Unidades]] -> 710.5275 | J15: MARGEN PORCENTUAL | K15: =+K14/K9 -> 1.9833645
B16: SALSA DE SOYA X 2O LITROS | C16: g | D16: 10 | E16: 0 | F16: 10 | G16: =+VLOOKUP(Tabla1103453454455456479108135149[[#This Row],[Ingrediente]],Tabla34[#All],3,0) -> 8.925 | H16: =+Tabla1103453454455456479108135149[[#This Row],[Costo]]*Tabla1103453454455456479108135149[[#This Row],[Unidades]] -> 89.25
B17: SUB. CHIPS DE YUCA | C17: g | D17: 40 | E17: 0 | F17: 40 | G17: =+VLOOKUP(Tabla1103453454455456479108135149[[#This Row],[Ingrediente]],Tabla34[#All],3,0) -> 11.478188 | H17: =+Tabla1103453454455456479108135149[[#This Row],[Costo]]*Tabla1103453454455456479108135149[[#This Row],[Unidades]] -> 459.12754
B18: SUB. PULPO MEXICANO (ROCOTO)*150G | C18: uds | D18: 0.4 | E18: 0 | F18: 0.4 | G18: =+VLOOKUP(Tabla1103453454455456479108135149[[#This Row],[Ingrediente]],Tabla34[#All],3,0) -> 20955.187 | H18: =+Tabla1103453454455456479108135149[[#This Row],[Costo]]*Tabla1103453454455456479108135149[[#This Row],[Unidades]] -> 8382.0749
B19: SUB. SALSA DE CHICHARRONES | C19: g | D19: 100 | E19: 0 | F19: 100 | G19: =+VLOOKUP(Tabla1103453454455456479108135149[[#This Row],[Ingrediente]],Tabla34[#All],3,0) -> 17.685474 | H19: =+Tabla1103453454455456479108135149[[#This Row],[Costo]]*Tabla1103453454455456479108135149[[#This Row],[Unidades]] -> 1768.5474 | K19: =50/150 -> 0.33333333
H20: =SUBTOTAL(109,Tabla1103453454455456479108135149[Total costo]) -> 23351.12
J21: ANALISIS RECETA
B22: CEVICHE ROCOTO | J22: COSTO DEL PLATO | K22: =SUM(Tabla1103453454455456479108130137151[Total costo]) -> 15762.335
B23: Ingrediente | C23: Und | D23: Unidades Netas | E23: % Merma | F23: Unidades | G23: Costo | H23: Total costo | J23: MARGEN DE ERROR DEL 5% | K23: =+K22*5% -> 788.11676
B24: AGUACATE CHOCKETTE X KILO | C24: g | D24: 40 | E24: 25 | F24: 53.333 | G24: =+VLOOKUP(Tabla1103453454455456479108130137151[[#This Row],[Ingrediente]],Tabla34[#All],3,0) -> 14 | H24: =+Tabla1103453454455456479108130137151[[#This Row],[Costo]]*Tabla1103453454455456479108130137151[[#This Row],[Unidades]] -> 746.662 | J24: COSTO + MARGEN ERROR | K24: =+K22+K23 -> 16550.452
B25: AJI DULCE X KILO | C25: g | D25: 2 | E25: 10 | F25: 2.222 | G25: =+VLOOKUP(Tabla1103453454455456479108130137151[[#This Row],[Ingrediente]],Tabla34[#All],3,0) -> 8 | H25: =+Tabla1103453454455456479108130137151[[#This Row],[Costo]]*Tabla1103453454455456479108130137151[[#This Row],[Unidades]] -> 17.776 | J25: VALOR DE VENTA | K25: 62000
B26: AJONJOLI BLANCO TOSTADO *500G | C26: g | D26: 2 | E26: 0 | F26: 2 | G26: =+VLOOKUP(Tabla1103453454455456479108130137151[[#This Row],[Ingrediente]],Tabla34[#All],3,0) -> 18.139 | H26: =+Tabla1103453454455456479108130137151[[#This Row],[Costo]]*Tabla1103453454455456479108130137151[[#This Row],[Unidades]] -> 36.278 | J26: IPOCONSUMO | K26: =+K25/1.08*0.08 -> 4592.5926
B27: AJONJOLI NEGRO X 500GR | C27: g | D27: 2 | E27: 0 | F27: 2 | G27: =+VLOOKUP(Tabla1103453454455456479108130137151[[#This Row],[Ingrediente]],Tabla34[#All],3,0) -> 40.97 | H27: =+Tabla1103453454455456479108130137151[[#This Row],[Costo]]*Tabla1103453454455456479108130137151[[#This Row],[Unidades]] -> 81.94 | J27: VALOR ANTES DE IPO | K27: =+K25-K26 -> 57407.407
B28: BROTES DE RABANO 50 | C28: g | D28: 1 | E28: 0 | F28: 1 | G28: =+VLOOKUP(Tabla1103453454455456479108130137151[[#This Row],[Ingrediente]],Tabla34[#All],3,0) -> 328.34 | H28: =+Tabla1103453454455456479108130137151[[#This Row],[Costo]]*Tabla1103453454455456479108130137151[[#This Row],[Unidades]] -> 328.34 | J28: MARGEN. | K28: =+K24/K27 -> 0.28829819
B29: CAMARON CRUDO 41-50 0% PORCIONX 7UND PAQUETE POR 10 PORCIONES | C29: uds | D29: 7 | E29: 0 | F29: 7 | G29: =+VLOOKUP(Tabla1103453454455456479108130137151[[#This Row],[Ingrediente]],Tabla34[#All],3,0) -> 485.71429 | H29: =+Tabla1103453454455456479108130137151[[#This Row],[Costo]]*Tabla1103453454455456479108130137151[[#This Row],[Unidades]] -> 3400 | J29: GANANCIA | K29: =+K27-K24 -> 40856.956
B30: CEBOLLA MORADA LIMPIA | C30: g | D30: 50 | E30: 27 | F30: 68.493 | G30: =+VLOOKUP(Tabla1103453454455456479108130137151[[#This Row],[Ingrediente]],Tabla34[#All],3,0) -> 3.8 | H30: =+Tabla1103453454455456479108130137151[[#This Row],[Costo]]*Tabla1103453454455456479108130137151[[#This Row],[Unidades]] -> 260.2734 | J30: MARGEN PORCENTUAL | K30: =+K29/K24 -> 2.4686308
B31: CILANTRO LIMPIO X KILO | C31: g | D31: 2 | E31: 40 | F31: 3.333 | G31: =+VLOOKUP(Tabla1103453454455456479108130137151[[#This Row],[Ingrediente]],Tabla34[#All],3,0) -> 5.5 | H31: =+Tabla1103453454455456479108130137151[[#This Row],[Costo]]*Tabla1103453454455456479108130137151[[#This Row],[Unidades]] -> 18.3315
B32: COGOLLO EUROPEO *250 | C32: g | D32: 5 | E32: 0 | F32: 5 | G32: =+VLOOKUP(Tabla1103453454455456479108130137151[[#This Row],[Ingrediente]],Tabla34[#All],3,0) -> 24 | H32: =+Tabla1103453454455456479108130137151[[#This Row],[Costo]]*Tabla1103453454455456479108130137151[[#This Row],[Unidades]] -> 120
B33: FILETE DE TILAPIA FRESCA LO | C33: g | D33: 120 | E33: 10 | F33: 133.333 | G33: =+VLOOKUP(Tabla1103453454455456479108130137151[[#This Row],[Ingrediente]],Tabla34[#All],3,0) -> 37 | H33: =+Tabla1103453454455456479108130137151[[#This Row],[Costo]]*Tabla1103453454455456479108130137151[[#This Row],[Unidades]] -> 4933.321
B34: HARINA DE TRIGO HAZ DE OROS BOLSA X550g | C34: g | D34: 2 | E34: 0 | F34: 2 | G34: =+VLOOKUP(Tabla1103453454455456479108130137151[[#This Row],[Ingrediente]],Tabla34[#All],3,0) -> 4.746 | H34: =+Tabla1103453454455456479108130137151[[#This Row],[Costo]]*Tabla1103453454455456479108130137151[[#This Row],[Unidades]] -> 9.492
B35: LIMON TAHITI X KILO | C35: g | D35: 20 | E35: 78 | F35: 90.909 | G35: =+VLOOKUP(Tabla1103453454455456479108130137151[[#This Row],[Ingrediente]],Tabla34[#All],3,0) -> 4.5 | H35: =+Tabla1103453454455456479108130137151[[#This Row],[Costo]]*Tabla1103453454455456479108130137151[[#This Row],[Unidades]] -> 409.0905
B36: MIGA DE PAN PANKO BLANCO X 20 KILOS | C36: g | D36: 20 | E36: 0 | F36: 20 | G36: =+VLOOKUP(Tabla1103453454455456479108130137151[[#This Row],[Ingrediente]],Tabla34[#All],3,0) -> 13.05 | H36: =+Tabla1103453454455456479108130137151[[#This Row],[Costo]]*Tabla1103453454455456479108130137151[[#This Row],[Unidades]] -> 261
B37: SAL REFISAL X 1000G | C37: g | D37: 1 | E37: 0 | F37: 1 | G37: =+VLOOKUP(Tabla1103453454455456479108130137151[[#This Row],[Ingrediente]],Tabla34[#All],3,0) -> 2.6999076 | H37: =+Tabla1103453454455456479108130137151[[#This Row],[Costo]]*Tabla1103453454455456479108130137151[[#This Row],[Unidades]] -> 2.6999076
B38: SUB. ACEITE DE CILANTRO | C38: g | D38: 2 | E38: 0 | F38: 2 | G38: =+VLOOKUP(Tabla1103453454455456479108130137151[[#This Row],[Ingrediente]],Tabla34[#All],3,0) -> 16.110971 | H38: =+Tabla1103453454455456479108130137151[[#This Row],[Costo]]*Tabla1103453454455456479108130137151[[#This Row],[Unidades]] -> 32.221943
B39: SUB. BASE LECHE DE TIGRE | C39: g | D39: 80 | E39: 0 | F39: 80 | G39: =+VLOOKUP(Tabla1103453454455456479108130137151[[#This Row],[Ingrediente]],Tabla34[#All],3,0) -> 10.179495 | H39: =+Tabla1103453454455456479108130137151[[#This Row],[Costo]]*Tabla1103453454455456479108130137151[[#This Row],[Unidades]] -> 814.35963
B40: SUB. CALAMAR CEVICHERIA | C40: g | D40: 40 | E40: 0 | F40: 40 | G40: =+VLOOKUP(Tabla1103453454455456479108130137151[[#This Row],[Ingrediente]],Tabla34[#All],3,0) -> 76.437956 | H40: =+Tabla1103453454455456479108130137151[[#This Row],[Costo]]*Tabla1103453454455456479108130137151[[#This Row],[Unidades]] -> 3057.5182
B41: SUB. HUEVO BATIDO | C41: g | D41: 10 | E41: 0 | F41: 10 | G41: =+VLOOKUP(Tabla1103453454455456479108130137151[[#This Row],[Ingrediente]],Tabla34[#All],3,0) -> 23.747278 | H41: =+Tabla1103453454455456479108130137151[[#This Row],[Costo]]*Tabla1103453454455456479108130137151[[#This Row],[Unidades]] -> 237.47278
B42: SUB. PASTA DE AJI ROCOTO (PC) | C42: g | D42: 80 | E42: 0 | F42: 80 | G42: =+VLOOKUP(Tabla1103453454455456479108130137151[[#This Row],[Ingrediente]],Tabla34[#All],3,0) -> 12.444478 | H42: =+Tabla1103453454455456479108130137151[[#This Row],[Costo]]*Tabla1103453454455456479108130137151[[#This Row],[Unidades]] -> 995.55824
H43: =SUBTOTAL(109,Tabla1103453454455456479108130137151[Total costo]) -> 15762.335
B45: CEVICHE ANDINO | J45: ANALISIS RECETA
B46: Ingrediente | C46: Und | D46: Unidades Netas | E46: % Merma | F46: Unidades | G46: Costo | H46: Total costo | J46: COSTO DEL PLATO | K46: =SUM(Tabla1103453454455456479108131138152[Total costo]) -> 14813.429
B47: AGUACATE CHOCKETTE X KILO | C47: g | D47: 60 | E47: 25 | F47: 80 | G47: =+VLOOKUP(Tabla1103453454455456479108131138152[[#This Row],[Ingrediente]],Tabla34[#All],3,0) -> 14 | H47: =+Tabla1103453454455456479108131138152[[#This Row],[Costo]]*Tabla1103453454455456479108131138152[[#This Row],[Unidades]] -> 1120 | J47: MARGEN DE ERROR DEL 5% | K47: =+K46*5% -> 740.67147
B48: CAMARON CRUDO 41-50 0% PORCIONX 7UND PAQUETE POR 10 PORCIONES | C48: uds | D48: 7 | E48: 0 | F48: 7 | G48: =+VLOOKUP(Tabla1103453454455456479108131138152[[#This Row],[Ingrediente]],Tabla34[#All],3,0) -> 485.71429 | H48: =+Tabla1103453454455456479108131138152[[#This Row],[Costo]]*Tabla1103453454455456479108131138152[[#This Row],[Unidades]] -> 3400 | J48: COSTO + MARGEN ERROR | K48: =+K46+K47 -> 15554.101
B49: CEBOLLA MORADA LIMPIA | C49: g | D49: 50 | E49: 27 | F49: 68.49315 | G49: =+VLOOKUP(Tabla1103453454455456479108131138152[[#This Row],[Ingrediente]],Tabla34[#All],3,0) -> 3.8 | H49: =+Tabla1103453454455456479108131138152[[#This Row],[Costo]]*Tabla1103453454455456479108131138152[[#This Row],[Unidades]] -> 260.27397 | J49: VALOR DE VENTA | K49: 47900
B50: CILANTRO LIMPIO X KILO | C50: g | D50: 2 | E50: 40 | F50: 3.3333333 | G50: =+VLOOKUP(Tabla1103453454455456479108131138152[[#This Row],[Ingrediente]],Tabla34[#All],3,0) -> 5.5 | H50: =+Tabla1103453454455456479108131138152[[#This Row],[Costo]]*Tabla1103453454455456479108131138152[[#This Row],[Unidades]] -> 18.333333 | J50: IPOCONSUMO | K50: =+K49/1.08*0.08 -> 3548.1481
B51: FILETE DE TILAPIA FRESCA LO | C51: g | D51: 59.999998 | E51: 10 | F51: 66.666664 | G51: =+VLOOKUP(Tabla1103453454455456479108131138152[[#This Row],[Ingrediente]],Tabla34[#All],3,0) -> 37 | H51: =+Tabla1103453454455456479108131138152[[#This Row],[Costo]]*Tabla1103453454455456479108131138152[[#This Row],[Unidades]] -> 2466.6666 | J51: VALOR ANTES DE IPO | K51: =+K49-K50 -> 44351.852
B52: LIMON TAHITI X KILO | C52: g | D52: 20 | E52: 78 | F52: 90.90909 | G52: =+VLOOKUP(Tabla1103453454455456479108131138152[[#This Row],[Ingrediente]],Tabla34[#All],3,0) -> 4.5 | H52: =+Tabla1103453454455456479108131138152[[#This Row],[Costo]]*Tabla1103453454455456479108131138152[[#This Row],[Unidades]] -> 409.09091 | J52: MARGEN. | K52: =+K48/K51 -> 0.35069789
B53: PALMITO KANIKAMA PREMIUM X 30UND | C53: uds | D53: 1 | E53: 0 | F53: 1 | G53: =+VLOOKUP(Tabla1103453454455456479108131138152[[#This Row],[Ingrediente]],Tabla34[#All],3,0) -> 773.5 | H53: =+Tabla1103453454455456479108131138152[[#This Row],[Costo]]*Tabla1103453454455456479108131138152[[#This Row],[Unidades]] -> 773.5 | J53: GANANCIA | K53: =+K51-K48 -> 28797.751
B54: SAL REFISAL X 1000G | C54: g | D54: 1 | E54: 0 | F54: 1 | G54: =+VLOOKUP(Tabla1103453454455456479108131138152[[#This Row],[Ingrediente]],Tabla34[#All],3,0) -> 2.6999076 | H54: =+Tabla1103453454455456479108131138152[[#This Row],[Costo]]*Tabla1103453454455456479108131138152[[#This Row],[Unidades]] -> 2.6999076 | J54: MARGEN PORCENTUAL | K54: =+K53/K48 -> 1.8514571
B55: SUB. CALAMAR CEVICHERIA | C55: g | D55: 40 | E55: 0 | F55: 40 | G55: =+VLOOKUP(Tabla1103453454455456479108131138152[[#This Row],[Ingrediente]],Tabla34[#All],3,0) -> 76.437956 | H55: =+Tabla1103453454455456479108131138152[[#This Row],[Costo]]*Tabla1103453454455456479108131138152[[#This Row],[Unidades]] -> 3057.5182
B56: SUB. LECHE DE TIGRE | C56: g | D56: 50 | E56: 0 | F56: 50 | G56: =+VLOOKUP(Tabla1103453454455456479108131138152[[#This Row],[Ingrediente]],Tabla34[#All],3,0) -> 28.798283 | H56: =+Tabla1103453454455456479108131138152[[#This Row],[Costo]]*Tabla1103453454455456479108131138152[[#This Row],[Unidades]] -> 1439.9141
B57: SUB. PASTA DE AJI AMARILLO (ROCOTO) | C57: g | D57: 80 | E57: 0 | F57: 80 | G57: =+VLOOKUP(Tabla1103453454455456479108131138152[[#This Row],[Ingrediente]],Tabla34[#All],3,0) -> 23.317904 | H57: =+Tabla1103453454455456479108131138152[[#This Row],[Costo]]*Tabla1103453454455456479108131138152[[#This Row],[Unidades]] -> 1865.4323
B58: TINTA DE CALAMAR SQUID INK X 500 GR | C58: g | D58: 2 | E58: 0 | F58: 2 | G58: =+VLOOKUP(Tabla1103453454455456479108131138152[[#This Row],[Ingrediente]],Tabla34[#All],3,0) -> 0 | H58: =+Tabla1103453454455456479108131138152[[#This Row],[Costo]]*Tabla1103453454455456479108131138152[[#This Row],[Unidades]] -> 0
H59: =SUBTOTAL(109,Tabla1103453454455456479108131138152[Total costo]) -> 14813.429
B61: MIXTO TRADICIONAL | J61: ANALISIS RECETA
B62: Ingrediente | C62: Und | D62: Unidades Netas | E62: % Merma | F62: Unidades | G62: Costo | H62: Total costo | J62: COSTO DEL PLATO | K62: =SUM(Tabla1103453454455456479108132139153[Total costo]) -> 14943.798
B63: AJI DULCE X KILO | C63: g | D63: 2 | E63: 10 | F63: 2.222 | G63: =+VLOOKUP(Tabla1103453454455456479108132139153[[#This Row],[Ingrediente]],Tabla34[#All],3,0) -> 8 | H63: =+Tabla1103453454455456479108132139153[[#This Row],[Costo]]*Tabla1103453454455456479108132139153[[#This Row],[Unidades]] -> 17.776 | J63: MARGEN DE ERROR DEL 5% | K63: =+K62*5% -> 747.18992
B64: BROTES DE RABANO 50 | C64: g | D64: 1 | E64: 0 | F64: 1 | G64: =+VLOOKUP(Tabla1103453454455456479108132139153[[#This Row],[Ingrediente]],Tabla34[#All],3,0) -> 328.34 | H64: =+Tabla1103453454455456479108132139153[[#This Row],[Costo]]*Tabla1103453454455456479108132139153[[#This Row],[Unidades]] -> 328.34 | J64: COSTO + MARGEN ERROR | K64: =+K62+K63 -> 15690.988
B65: CAMARON CRUDO 41-50 0% PORCIONX 7UND PAQUETE POR 10 PORCIONES | C65: uds | D65: 7 | E65: 0 | F65: 7 | G65: =+VLOOKUP(Tabla1103453454455456479108132139153[[#This Row],[Ingrediente]],Tabla34[#All],3,0) -> 485.71429 | H65: =+Tabla1103453454455456479108132139153[[#This Row],[Costo]]*Tabla1103453454455456479108132139153[[#This Row],[Unidades]] -> 3400 | J65: VALOR DE VENTA | K65: 52000
B66: CEBOLLA MORADA LIMPIA | C66: g | D66: 50 | E66: 27 | F66: 68.493 | G66: =+VLOOKUP(Tabla1103453454455456479108132139153[[#This Row],[Ingrediente]],Tabla34[#All],3,0) -> 3.8 | H66: =+Tabla1103453454455456479108132139153[[#This Row],[Costo]]*Tabla1103453454455456479108132139153[[#This Row],[Unidades]] -> 260.2734 | J66: IPOCONSUMO | K66: =+K65/1.08*0.08 -> 3851.8519
B67: CILANTRO LIMPIO X KILO | C67: g | D67: 2 | E67: 40 | F67: 3.333 | G67: =+VLOOKUP(Tabla1103453454455456479108132139153[[#This Row],[Ingrediente]],Tabla34[#All],3,0) -> 5.5 | H67: =+Tabla1103453454455456479108132139153[[#This Row],[Costo]]*Tabla1103453454455456479108132139153[[#This Row],[Unidades]] -> 18.3315 | J67: VALOR ANTES DE IPO | K67: =+K65-K66 -> 48148.148
B68: FILETE DE TILAPIA FRESCA LO | C68: g | D68: 60 | E68: 10 | F68: 66.667 | G68: =+VLOOKUP(Tabla1103453454455456479108132139153[[#This Row],[Ingrediente]],Tabla34[#All],3,0) -> 37 | H68: =+Tabla1103453454455456479108132139153[[#This Row],[Costo]]*Tabla1103453454455456479108132139153[[#This Row],[Unidades]] -> 2466.679 | J68: MARGEN. | K68: =+K64/K67 -> 0.32588976
B69: HARINA DE TRIGO HAZ DE OROS BOLSA X550g | C69: g | D69: 5 | E69: 0 | F69: 5 | G69: =+VLOOKUP(Tabla1103453454455456479108132139153[[#This Row],[Ingrediente]],Tabla34[#All],3,0) -> 4.746 | H69: =+Tabla1103453454455456479108132139153[[#This Row],[Costo]]*Tabla1103453454455456479108132139153[[#This Row],[Unidades]] -> 23.73 | J69: GANANCIA | K69: =+K67-K64 -> 32457.16
B70: LIMON TAHITI X KILO | C70: g | D70: 20 | E70: 78 | F70: 90.909 | G70: =+VLOOKUP(Tabla1103453454455456479108132139153[[#This Row],[Ingrediente]],Tabla34[#All],3,0) -> 4.5 | H70: =+Tabla1103453454455456479108132139153[[#This Row],[Costo]]*Tabla1103453454455456479108132139153[[#This Row],[Unidades]] -> 409.0905 | J70: MARGEN PORCENTUAL | K70: =+K69/K64 -> 2.0685223
B71: MAIZ TIERNO METOO VACUMX 340G DRE 285G | C71: g | D71: 15 | E71: 0 | F71: 15 | G71: =+VLOOKUP(Tabla1103453454455456479108132139153[[#This Row],[Ingrediente]],Tabla34[#All],3,0) -> 21.754386 | H71: =+Tabla1103453454455456479108132139153[[#This Row],[Costo]]*Tabla1103453454455456479108132139153[[#This Row],[Unidades]] -> 326.31579
B72: MANGO TOMMY X KILO | C72: g | D72: 20 | E72: 30 | F72: 28.571 | G72: =+VLOOKUP(Tabla1103453454455456479108132139153[[#This Row],[Ingrediente]],Tabla34[#All],3,0) -> 3 | H72: =+Tabla1103453454455456479108132139153[[#This Row],[Costo]]*Tabla1103453454455456479108132139153[[#This Row],[Unidades]] -> 85.713
B73: SUB. BASE LECHE DE TIGRE | C73: g | D73: 80 | E73: 0 | F73: 80 | G73: =+VLOOKUP(Tabla1103453454455456479108132139153[[#This Row],[Ingrediente]],Tabla34[#All],3,0) -> 10.179495 | H73: =+Tabla1103453454455456479108132139153[[#This Row],[Costo]]*Tabla1103453454455456479108132139153[[#This Row],[Unidades]] -> 814.35963
B74: SUB. CALAMAR CEVICHERIA | C74: g | D74: 80 | E74: 0 | F74: 80 | G74: =+VLOOKUP(Tabla1103453454455456479108132139153[[#This Row],[Ingrediente]],Tabla34[#All],3,0) -> 76.437956 | H74: =+Tabla1103453454455456479108132139153[[#This Row],[Costo]]*Tabla1103453454455456479108132139153[[#This Row],[Unidades]] -> 6115.0365
B75: SUB. CAMOTE GLASEADO | C75: g | D75: 30 | E75: 0 | F75: 30 | G75: =+VLOOKUP(Tabla1103453454455456479108132139153[[#This Row],[Ingrediente]],Tabla34[#All],3,0) -> 11.90893 | H75: =+Tabla1103453454455456479108132139153[[#This Row],[Costo]]*Tabla1103453454455456479108132139153[[#This Row],[Unidades]] -> 357.26791
B76: SUB. CANCHA CHULPI | C76: g | D76: 5 | E76: 0 | F76: 5 | G76: =+VLOOKUP(Tabla1103453454455456479108132139153[[#This Row],[Ingrediente]],Tabla34[#All],3,0) -> 16.68247 | H76: =+Tabla1103453454455456479108132139153[[#This Row],[Costo]]*Tabla1103453454455456479108132139153[[#This Row],[Unidades]] -> 83.412351
B77: SUB. HUEVO BATIDO | C77: g | D77: 10 | E77: 0 | F77: 10 | G77: =+VLOOKUP(Tabla1103453454455456479108132139153[[#This Row],[Ingrediente]],Tabla34[#All],3,0) -> 23.747278 | H77: =+Tabla1103453454455456479108132139153[[#This Row],[Costo]]*Tabla1103453454455456479108132139153[[#This Row],[Unidades]] -> 237.47278
H78: =SUBTOTAL(109,Tabla1103453454455456479108132139153[Total costo]) -> 14943.798
B82: CEVICHE PERUANO | J82: ANALISIS RECETA
B83: Ingrediente | C83: Und | D83: Unidades Netas | E83: % Merma | F83: Unidades | G83: Costo | H83: Total costo | J83: COSTO DEL PLATO | K83: =SUM(Tabla1103453454455456479108133140154[Total costo]) -> 8806.8313
B84: AJI DULCE X KILO | C84: g | D84: 2 | E84: 10 | F84: 2.222 | G84: =+VLOOKUP(Tabla1103453454455456479108133140154[[#This Row],[Ingrediente]],Tabla34[#All],3,0) -> 8 | H84: =+Tabla1103453454455456479108133140154[[#This Row],[Costo]]*Tabla1103453454455456479108133140154[[#This Row],[Unidades]] -> 17.776 | J84: MARGEN DE ERROR DEL 5% | K84: =+K83*5% -> 440.34157
B85: BROTES DE RABANO 50 | C85: g | D85: 1 | E85: 0 | F85: 1 | G85: =+VLOOKUP(Tabla1103453454455456479108133140154[[#This Row],[Ingrediente]],Tabla34[#All],3,0) -> 328.34 | H85: =+Tabla1103453454455456479108133140154[[#This Row],[Costo]]*Tabla1103453454455456479108133140154[[#This Row],[Unidades]] -> 328.34 | J85: COSTO + MARGEN ERROR | K85: =+K83+K84 -> 9247.1729
B86: CEBOLLA MORADA LIMPIA | C86: g | D86: 50 | E86: 27 | F86: 68.493 | G86: =+VLOOKUP(Tabla1103453454455456479108133140154[[#This Row],[Ingrediente]],Tabla34[#All],3,0) -> 3.8 | H86: =+Tabla1103453454455456479108133140154[[#This Row],[Costo]]*Tabla1103453454455456479108133140154[[#This Row],[Unidades]] -> 260.2734 | J86: VALOR DE VENTA | K86: 39900
B87: CILANTRO LIMPIO X KILO | C87: g | D87: 2 | E87: 40 | F87: 3.333 | G87: =+VLOOKUP(Tabla1103453454455456479108133140154[[#This Row],[Ingrediente]],Tabla34[#All],3,0) -> 5.5 | H87: =+Tabla1103453454455456479108133140154[[#This Row],[Costo]]*Tabla1103453454455456479108133140154[[#This Row],[Unidades]] -> 18.3315 | J87: IPOCONSUMO | K87: =+K86/1.08*0.08 -> 2955.5556
B88: COGOLLO EUROPEO *250 | C88: g | D88: 4 | E88: 5 | F88: 4.211 | G88: =+VLOOKUP(Tabla1103453454455456479108133140154[[#This Row],[Ingrediente]],Tabla34[#All],3,0) -> 24 | H88: =+Tabla1103453454455456479108133140154[[#This Row],[Costo]]*Tabla1103453454455456479108133140154[[#This Row],[Unidades]] -> 101.064 | J88: VALOR ANTES DE IPO | K88: =+K86-K87 -> 36944.444
B89: FILETE DE TILAPIA FRESCA LO | C89: g | D89: 150 | E89: 10 | F89: 166.667 | G89: =+VLOOKUP(Tabla1103453454455456479108133140154[[#This Row],[Ingrediente]],Tabla34[#All],3,0) -> 37 | H89: =+Tabla1103453454455456479108133140154[[#This Row],[Costo]]*Tabla1103453454455456479108133140154[[#This Row],[Unidades]] -> 6166.679 | J89: MARGEN. | K89: =+K85/K88 -> 0.25029942
B90: LIMON TAHITI X KILO | C90: g | D90: 20 | E90: 78 | F90: 90.909 | G90: =+VLOOKUP(Tabla1103453454455456479108133140154[[#This Row],[Ingrediente]],Tabla34[#All],3,0) -> 4.5 | H90: =+Tabla1103453454455456479108133140154[[#This Row],[Costo]]*Tabla1103453454455456479108133140154[[#This Row],[Unidades]] -> 409.0905 | J90: GANANCIA | K90: =+K88-K85 -> 27697.272
B91: SUB. BASE LECHE DE TIGRE | C91: g | D91: 80 | E91: 0 | F91: 80 | G91: =+VLOOKUP(Tabla1103453454455456479108133140154[[#This Row],[Ingrediente]],Tabla34[#All],3,0) -> 10.179495 | H91: =+Tabla1103453454455456479108133140154[[#This Row],[Costo]]*Tabla1103453454455456479108133140154[[#This Row],[Unidades]] -> 814.35963 | J91: MARGEN PORCENTUAL | K91: =+K90/K85 -> 2.9952151
B92: SUB. CAMOTE GLASEADO | C92: g | D92: 30 | E92: 0 | F92: 30 | G92: =+VLOOKUP(Tabla1103453454455456479108133140154[[#This Row],[Ingrediente]],Tabla34[#All],3,0) -> 11.90893 | H92: =+Tabla1103453454455456479108133140154[[#This Row],[Costo]]*Tabla1103453454455456479108133140154[[#This Row],[Unidades]] -> 357.26791
B93: SUB. CANCHA CHULPI | C93: g | D93: 20 | E93: 0 | F93: 20 | G93: =+VLOOKUP(Tabla1103453454455456479108133140154[[#This Row],[Ingrediente]],Tabla34[#All],3,0) -> 16.68247 | H93: =+Tabla1103453454455456479108133140154[[#This Row],[Costo]]*Tabla1103453454455456479108133140154[[#This Row],[Unidades]] -> 333.6494
H94: =SUBTOTAL(109,Tabla1103453454455456479108133140154[Total costo]) -> 8806.8313
B96: LECHE DE TIGRE 2.0 | J96: ANALISIS RECETA
B97: Ingrediente | C97: Und | D97: Unidades Netas | E97: % Merma | F97: Unidades | G97: Costo | H97: Total costo | J97: COSTO DEL PLATO | K97: =+Tabla1103453454455456479108133140154333431[[#Totals],[Total costo]] -> 12313.492
B98: AJI DULCE X KILO | C98: g | D98: 2 | E98: 0 | F98: 2 | G98: =+VLOOKUP(Tabla1103453454455456479108133140154333431[[#This Row],[Ingrediente]],Tabla34[#All],3,0) -> 8 | H98: =+Tabla1103453454455456479108133140154333431[[#This Row],[Costo]]*Tabla1103453454455456479108133140154333431[[#This Row],[Unidades]] -> 16 | J98: MARGEN DE ERROR DEL 5% | K98: =+K97*5% -> 615.6746
B99: AJI ROCOTO X KILO | C99: g | D99: 50 | E99: 0 | F99: 50 | G99: =+VLOOKUP(Tabla1103453454455456479108133140154333431[[#This Row],[Ingrediente]],Tabla34[#All],3,0) -> 14 | H99: =+Tabla1103453454455456479108133140154333431[[#This Row],[Costo]]*Tabla1103453454455456479108133140154333431[[#This Row],[Unidades]] -> 700 | J99: COSTO + MARGEN ERROR | K99: =+K97+K98 -> 12929.167
B100: BROTES DE RABANO 50 | C100: g | D100: 1 | E100: 10 | F100: 1.111 | G100: =+VLOOKUP(Tabla1103453454455456479108133140154333431[[#This Row],[Ingrediente]],Tabla34[#All],3,0) -> 328.34 | H100: =+Tabla1103453454455456479108133140154333431[[#This Row],[Costo]]*Tabla1103453454455456479108133140154333431[[#This Row],[Unidades]] -> 364.78574 | J100: VALOR DE VENTA | K100: 49900
B101: CEBOLLA MORADA LIMPIA | C101: g | D101: 80 | E101: 27 | F101: 109.589 | G101: =+VLOOKUP(Tabla1103453454455456479108133140154333431[[#This Row],[Ingrediente]],Tabla34[#All],3,0) -> 3.8 | H101: =+Tabla1103453454455456479108133140154333431[[#This Row],[Costo]]*Tabla1103453454455456479108133140154333431[[#This Row],[Unidades]] -> 416.4382 | J101: IPOCONSUMO | K101: =+K100/1.08*0.08 -> 3696.2963
B102: CILANTRO LIMPIO X KILO | C102: g | D102: 3 | E102: 40 | F102: 5 | G102: =+VLOOKUP(Tabla1103453454455456479108133140154333431[[#This Row],[Ingrediente]],Tabla34[#All],3,0) -> 5.5 | H102: =+Tabla1103453454455456479108133140154333431[[#This Row],[Costo]]*Tabla1103453454455456479108133140154333431[[#This Row],[Unidades]] -> 27.5 | J102: VALOR ANTES DE IPO | K102: =+K100-K101 -> 46203.704
B103: COGOLLO EUROPEO *250 | C103: g | D103: 5 | E103: 10 | F103: 5.556 | G103: =+VLOOKUP(Tabla1103453454455456479108133140154333431[[#This Row],[Ingrediente]],Tabla34[#All],3,0) -> 24 | H103: =+Tabla1103453454455456479108133140154333431[[#This Row],[Costo]]*Tabla1103453454455456479108133140154333431[[#This Row],[Unidades]] -> 133.344 | J103: MARGEN. | K103: =+K99/K102 -> 0.27982966
B104: FILETE DE TILAPIA FRESCA LO | C104: g | D104: 100 | E104: 10 | F104: 111.111 | G104: =+VLOOKUP(Tabla1103453454455456479108133140154333431[[#This Row],[Ingrediente]],Tabla34[#All],3,0) -> 37 | H104: =+Tabla1103453454455456479108133140154333431[[#This Row],[Costo]]*Tabla1103453454455456479108133140154333431[[#This Row],[Unidades]] -> 4111.107 | J104: GANANCIA | K104: =+K102-K99 -> 33274.537
B105: HARINA DE TRIGO HAZ DE OROS BOLSA X550g | C105: g | D105: 20 | E105: 0 | F105: 20 | G105: =+VLOOKUP(Tabla1103453454455456479108133140154333431[[#This Row],[Ingrediente]],Tabla34[#All],3,0) -> 4.746 | H105: =+Tabla1103453454455456479108133140154333431[[#This Row],[Costo]]*Tabla1103453454455456479108133140154333431[[#This Row],[Unidades]] -> 94.92 | J105: MARGEN PORCENTUAL | K105: =+K104/K99 -> 2.5736026
B106: LIMON TAHITI X KILO | C106: g | D106: 40 | E106: 78 | F106: 181.818 | G106: =+VLOOKUP(Tabla1103453454455456479108133140154333431[[#This Row],[Ingrediente]],Tabla34[#All],3,0) -> 4.5 | H106: =+Tabla1103453454455456479108133140154333431[[#This Row],[Costo]]*Tabla1103453454455456479108133140154333431[[#This Row],[Unidades]] -> 818.181
B107: SUB. BASE LECHE DE TIGRE | C107: g | D107: 150 | E107: 0 | F107: 150 | G107: =+VLOOKUP(Tabla1103453454455456479108133140154333431[[#This Row],[Ingrediente]],Tabla34[#All],3,0) -> 10.179495 | H107: =+Tabla1103453454455456479108133140154333431[[#This Row],[Costo]]*Tabla1103453454455456479108133140154333431[[#This Row],[Unidades]] -> 1526.9243
B108: SUB. CALAMAR CEVICHERIA | C108: g | D108: 40 | E108: 0 | F108: 40 | G108: =+VLOOKUP(Tabla1103453454455456479108133140154333431[[#This Row],[Ingrediente]],Tabla34[#All],3,0) -> 76.437956 | H108: =+Tabla1103453454455456479108133140154333431[[#This Row],[Costo]]*Tabla1103453454455456479108133140154333431[[#This Row],[Unidades]] -> 3057.5182
B109: SUB. CAMOTE GLASEADO | C109: g | D109: 20 | E109: 0 | F109: 20 | G109: =+VLOOKUP(Tabla1103453454455456479108133140154333431[[#This Row],[Ingrediente]],Tabla34[#All],3,0) -> 11.90893 | H109: =+Tabla1103453454455456479108133140154333431[[#This Row],[Costo]]*Tabla1103453454455456479108133140154333431[[#This Row],[Unidades]] -> 238.1786
B110: SUB. CANCHA CHULPI | C110: g | D110: 20 | E110: 0 | F110: 20 | G110: =+VLOOKUP(Tabla1103453454455456479108133140154333431[[#This Row],[Ingrediente]],Tabla34[#All],3,0) -> 16.68247 | H110: =+Tabla1103453454455456479108133140154333431[[#This Row],[Costo]]*Tabla1103453454455456479108133140154333431[[#This Row],[Unidades]] -> 333.6494
B111: SUB. HUEVO BATIDO | C111: g | D111: 20 | E111: 0 | F111: 20 | G111: =+VLOOKUP(Tabla1103453454455456479108133140154333431[[#This Row],[Ingrediente]],Tabla34[#All],3,0) -> 23.747278 | H111: =+Tabla1103453454455456479108133140154333431[[#This Row],[Costo]]*Tabla1103453454455456479108133140154333431[[#This Row],[Unidades]] -> 474.94555
...

Sheet INSUMOS
A1: ArtÃ­culo | B1: SubartÃ­culo | C1: Coste
A2: ABSOLUT 350ML | B2: UNIDADES | C2: 0
A3: ABSOLUT 700 ML | B3: ONZA | C3: 3500
A4: ACEITE DE AJONJOLI KADOYA X 1.62LT | B4: GRAMOS | C4: 84.475309
A5: ACEITE DE OLIVA VIR EXTRA GRAN S ABRIL PX1L | B5: GRAMOS | C5: 43.443
A6: ACEITE MESTRE OLEO X 3000CC | B6: GRAMOS | C6: 18.859
A7: ACEITE VEGETAL X 20LT | B7: GRAMOS | C7: 8.2499667
A8: ACEITUNA VERDE DESHUESADA 330GNDO | B8: GRAMOS | C8: 50.792
A9: ACEITUNAS MORADA ALFA *1000g | B9: GRAMOS | C9: 39.473
A10: ACHIOTE EN GRANO*1000 | B10: GRAMOS | C10: 0
A11: ACQUA PANNA VIDRIO 505 ML | B11: UNIDADES | C11: 8377.1429
A12: ADEREZO QUESO CHEDDAR X 1L | B12: GRAMOS | C12: 0
A13: AGRAZ *1000 | B13: GRAMOS | C13: 45
... A216: FRESA JUMBO I X KILO | B216: GRAMOS | C216: 15.5
A217: FRESH CITRUS 1.5LT PET (12)NVOIIDAD | B217: UNIDADES | C217: =1940.33333083/1500 -> 1.2935556
A218: FRIJOL CANARIO * KILO | B218: GRAMOS | C218: 13.333333
A219: GEL ANTIBACTERIAL SOFT CARE DESE H5X950M | B219: GRAMOS | C219: 0
A220: GINEBRA HENDRICKS 750CC | B220: ONZA | C220: 8980.25
A221: GINEBRA PINK GORDONS 700 ml | B221: ONZA | C221: 4390
A222: GINEBRA SELVA X700ML | B222: ONZA | C222: 6227.3182
A223: GINGER ALE BOTELLA 300ML - SCHWEPPES | B223: UNIDADES | C223: 1709.9658
A224: GINGER BEER SIN LICOR JUNIPER X 200ML | B224: UNIDADES | C224: 5133.6667
A225: GORDON DRY GIN 750 L50 | B225: ONZA | C225: 3090.4545
A226: GORRO MALLA NEGRA 53CM*20u | B226: UNIDADES | C226: 424.55
A227: GORRO TIPO MONJA VELO 6UND | B227: UNIDADES | C227: 4703
A228: GOTAS AMARGAS BITTER ANGOSTURA*150G | B228: GRAMOS | C228: 482.66184
A229: GREY GOOSE ORIGINAL 700ML | B229: ONZA | C229: 8727.2727
... A690: MAYOESA ALASENA X475G | B690: GRAMOS | C690: 32
A692: SUB. CHIPS DE CAMOTE | C692: 1
A693: PAN FRANCES 100GR 9.5- 10CM | C693: 2500
A694: VODKA BELVEDERE PURE 750ml | B694: ONZA | C694: =208000/24 -> 8666.6667
A695: JALAPEÃ‘O X KILO | C695: 14
A696: CAJA DE HIELO CUBO IGLU X 18UN | C696: 1222
A697: SUB. MIEL DE ROCOTO | C697: 15
A698: SUB. ALMIBAR DE TAMARINDO | C698: 10
A699: JAGERMEISTER - JAGER 750ML | C699: 4448.9545
A700: SUB. ALMIBAR DE GUAYABA | C700: 7.2297833
A701: POSTRE | C701: 10200
A702: AGUARDIENTE ANTIOQUEÃ‘O REAL SIN AZUCAR 24Â° 75OML | C702: 3090.9074
A703: RON CARBON 750ML | C703: 7065.7727
A704: SUGG DE CAFE X 750 ML
A705: SUB. TARTAR DE SALMON | C705: 51.411917
A706: SUB. PULPA DE CANGREJO | C706: 10536.305
A707: SUB. SALSA ANTICUCHERA BBQ ANTICUCHERA | C707: 15.555053

Sheet CARNES
B6: LOMO SALTADO | J6: ANALISIS RECETA
B7: Ingrediente | C7: Und | D7: Unidades Netas | E7: % Merma | F7: Unidades | G7: Costo | H7: Total costo | J7: COSTO DEL PLATO | K7: =SUM(Tabla1103453454455456479108135108[Total costo]) -> 16713.485
B8: SOLOMITO X 200G | C8: uds | D8: 1 | E8: 0 | F8: 1 | G8: =+VLOOKUP(Tabla1103453454455456479108135108[[#This Row],[Ingrediente]],Tabla34[#All],3,0) -> 12280 | H8: =+Tabla1103453454455456479108135108[[#This Row],[Costo]]*Tabla1103453454455456479108135108[[#This Row],[Unidades]] -> 12280 | J8: MARGEN DE ERROR DEL 5% | K8: =+K7*5% -> 835.67425
B9: SUB. PAPA CRIOLLA | C9: uds | D9: 1 | E9: 0 | F9: 1 | G9: =+VLOOKUP(Tabla1103453454455456479108135108[[#This Row],[Ingrediente]],Tabla34[#All],3,0) -> 1333.3333 | H9: =+Tabla1103453454455456479108135108[[#This Row],[Costo]]*Tabla1103453454455456479108135108[[#This Row],[Unidades]] -> 1333.3333 | J9: COSTO + MARGEN ERROR | K9: =+K7+K8 -> 17549.159
B10: SALSA DE OSTRAS ASIAFOOD PO 2LT | C10: g | D10: 30 | E10: 0 | F10: 30 | G10: =+VLOOKUP(Tabla1103453454455456479108135108[[#This Row],[Ingrediente]],Tabla34[#All],3,0) -> 26.269316 | H10: =+Tabla1103453454455456479108135108[[#This Row],[Costo]]*Tabla1103453454455456479108135108[[#This Row],[Unidades]] -> 788.07947 | J10: VALOR DE VENTA | K10: 59900
B11: SALSA DE SOYA X 2O LITROS | C11: g | D11: 50 | E11: 0 | F11: 50 | G11: =+VLOOKUP(Tabla1103453454455456479108135108[[#This Row],[Ingrediente]],Tabla34[#All],3,0) -> 8.925 | H11: =+Tabla1103453454455456479108135108[[#This Row],[Costo]]*Tabla1103453454455456479108135108[[#This Row],[Unidades]] -> 446.25 | J11: IPOCONSUMO | K11: =+K10/1.08*0.08 -> 4437.037
B12: SUB. ARROZ COCIDO | C12: g | D12: 80 | E12: 0 | F12: 80 | G12: =+VLOOKUP(Tabla1103453454455456479108135108[[#This Row],[Ingrediente]],Tabla34[#All],3,0) -> 4.8201292 | H12: =+Tabla1103453454455456479108135108[[#This Row],[Costo]]*Tabla1103453454455456479108135108[[#This Row],[Unidades]] -> 385.61034 | J12: VALOR ANTES DE IPO | K12: =+K10-K11 -> 55462.963
B13: BROTES DE RABANO 50 | C13: g | D13: 1 | E13: 0 | F13: 1 | G13: =+VLOOKUP(Tabla1103453454455456479108135108[[#This Row],[Ingrediente]],Tabla34[#All],3,0) -> 328.34 | H13: =+Tabla1103453454455456479108135108[[#This Row],[Costo]]*Tabla1103453454455456479108135108[[#This Row],[Unidades]] -> 328.34 | J13: MARGEN. | K13: =+K9/K12 -> 0.31641222
B14: CEBOLLA MORADA LIMPIA | C14: g | D14: 50 | E14: 27 | F14: 68.493 | G14: =+VLOOKUP(Tabla1103453454455456479108135108[[#This Row],[Ingrediente]],Tabla34[#All],3,0) -> 3.8 | H14: =+Tabla1103453454455456479108135108[[#This Row],[Costo]]*Tabla1103453454455456479108135108[[#This Row],[Unidades]] -> 260.2734 | J14: GANANCIA | K14: =+K12-K9 -> 37913.804
B15: SUB. FONDO DE PESCADO | C15: g | D15: 50 | E15: 0 | F15: 50 | G15: =+VLOOKUP(Tabla1103453454455456479108135108[[#This Row],[Ingrediente]],Tabla34[#All],3,0) -> 4.5393524 | H15: =+Tabla1103453454455456479108135108[[#This Row],[Costo]]*Tabla1103453454455456479108135108[[#This Row],[Unidades]] -> 226.96762 | J15: MARGEN PORCENTUAL | K15: =+K14/K9 -> 2.1604342
B16: TOMATE CHONTO X KILO | C16: g | D16: 60 | E16: 30 | F16: 85.714 | G16: =+VLOOKUP(Tabla1103453454455456479108135108[[#This Row],[Ingrediente]],Tabla34[#All],3,0) -> 2.5 | H16: =+Tabla1103453454455456479108135108[[#This Row],[Costo]]*Tabla1103453454455456479108135108[[#This Row],[Unidades]] -> 214.285
B17: SUB. PASTA DE AJO | C17: g | D17: 10 | E17: 0 | F17: 10 | G17: =+VLOOKUP(Tabla1103453454455456479108135108[[#This Row],[Ingrediente]],Tabla34[#All],3,0) -> 10.625185 | H17: =+Tabla1103453454455456479108135108[[#This Row],[Costo]]*Tabla1103453454455456479108135108[[#This Row],[Unidades]] -> 106.25185
B18: PIMIENTA NEGRA MOLIDA BADIA 453GR | C18: g | D18: 1 | E18: 0 | F18: 1 | G18: =+VLOOKUP(Tabla1103453454455456479108135108[[#This Row],[Ingrediente]],Tabla34[#All],3,0) -> 94.613742 | H18: =+Tabla1103453454455456479108135108[[#This Row],[Costo]]*Tabla1103453454455456479108135108[[#This Row],[Unidades]] -> 94.613742
B19: AJONJOLI NEGRO X 500GR | C19: g | D19: 2 | E19: 0 | F19: 2 | G19: =+VLOOKUP(Tabla1103453454455456479108135108[[#This Row],[Ingrediente]],Tabla34[#All],3,0) -> 40.97 | H19: =+Tabla1103453454455456479108135108[[#This Row],[Costo]]*Tabla1103453454455456479108135108[[#This Row],[Unidades]] -> 81.94
B20: COMINO MOLIDO X 500GR | C20: g | D20: 1 | E20: 0 | F20: 1 | G20: =+VLOOKUP(Tabla1103453454455456479108135108[[#This Row],[Ingrediente]],Tabla34[#All],3,0) -> 58.140353 | H20: =+Tabla1103453454455456479108135108[[#This Row],[Costo]]*Tabla1103453454455456479108135108[[#This Row],[Unidades]] -> 58.140353
B21: AJINOMOTO X KILO | C21: g | D21: 2 | E21: 0 | F21: 2 | G21: =+VLOOKUP(Tabla1103453454455456479108135108[[#This Row],[Ingrediente]],Tabla34[#All],3,0) -> 20.111 | H21: =+Tabla1103453454455456479108135108[[#This Row],[Costo]]*Tabla1103453454455456479108135108[[#This Row],[Unidades]] -> 40.222
B22: AJONJOLI BLANCO TOSTADO *500G | C22: g | D22: 2 | E22: 0 | F22: 2 | G22: =+VLOOKUP(Tabla1103453454455456479108135108[[#This Row],[Ingrediente]],Tabla34[#All],3,0) -> 18.139 | H22: =+Tabla1103453454455456479108135108[[#This Row],[Costo]]*Tabla1103453454455456479108135108[[#This Row],[Unidades]] -> 36.278
B23: CILANTRO LIMPIO X KILO | C23: g | D23: 3 | E23: 40 | F23: 5 | G23: =+VLOOKUP(Tabla1103453454455456479108135108[[#This Row],[Ingrediente]],Tabla34[#All],3,0) -> 5.5 | H23: =+Tabla1103453454455456479108135108[[#This Row],[Costo]]*Tabla1103453454455456479108135108[[#This Row],[Unidades]] -> 27.5
B24: SAL REFISAL X 1000G | C24: g | D24: 2 | E24: 0 | F24: 2 | G24: =+VLOOKUP(Tabla1103453454455456479108135108[[#This Row],[Ingrediente]],Tabla34[#All],3,0) -> 2.6999076 | H24: =+Tabla1103453454455456479108135108[[#This Row],[Costo]]*Tabla1103453454455456479108135108[[#This Row],[Unidades]] -> 5.3998151
B25: SUB. VINAGRE BLANCO | C25: g | D25: 30 | E25: 0 | F25: 30 | G25: 0 | H25: =+Tabla1103453454455456479108135108[[#This Row],[Costo]]*Tabla1103453454455456479108135108[[#This Row],[Unidades]] -> 0
H26: =SUBTOTAL(109,Tabla1103453454455456479108135108[Total costo]) -> 16713.485
B28: LOMITO SALSA DE QUESO | J28: ANALISIS RECETA
B29: Ingrediente | C29: Und | D29: Unidades Netas | E29: % Merma | F29: Unidades | G29: Costo | H29: Total costo | J29: COSTO DEL PLATO | K29: =SUM(Tabla1103453454455456479108129136118[Total costo]) -> 21704.767
B30: ACEITE VEGETAL X 20LT | C30: g | D30: 10 | E30: 0 | F30: 10 | G30: =+VLOOKUP(Tabla1103453454455456479108129136118[[#This Row],[Ingrediente]],Tabla34[#All],3,0) -> 8.2499667 | H30: =+Tabla1103453454455456479108129136118[[#This Row],[Costo]]*Tabla1103453454455456479108129136118[[#This Row],[Unidades]] -> 82.499667 | J30: MARGEN DE ERROR DEL 5% | K30: =+K29*5% -> 1085.2384
B31: AJINOMOTO X KILO | C31: g | D31: 2 | E31: 0 | F31: 2 | G31: =+VLOOKUP(Tabla1103453454455456479108129136118[[#This Row],[Ingrediente]],Tabla34[#All],3,0) -> 20.111 | H31: =+Tabla1103453454455456479108129136118[[#This Row],[Costo]]*Tabla1103453454455456479108129136118[[#This Row],[Unidades]] -> 40.222 | J31: COSTO + MARGEN ERROR | K31: =+K29+K30 -> 22790.006
B32: CILANTRO LIMPIO X KILO | C32: g | D32: 2 | E32: 40 | F32: 3.333 | G32: =+VLOOKUP(Tabla1103453454455456479108129136118[[#This Row],[Ingrediente]],Tabla34[#All],3,0) -> 5.5 | H32: =+Tabla1103453454455456479108129136118[[#This Row],[Costo]]*Tabla1103453454455456479108129136118[[#This Row],[Unidades]] -> 18.3315 | J32: VALOR DE VENTA | K32: 65900
B33: CREMA DE LECHE X 9700G | C33: g | D33: 150 | E33: 0 | F33: 150 | G33: =+VLOOKUP(Tabla1103453454455456479108129136118[[#This Row],[Ingrediente]],Tabla34[#All],3,0) -> 17.008247 | H33: =+Tabla1103453454455456479108129136118[[#This Row],[Costo]]*Tabla1103453454455456479108129136118[[#This Row],[Unidades]] -> 2551.2371 | J33: IPOCONSUMO | K33: =+K32/1.08*0.08 -> 4881.4815
B34: PIMIENTA ROSADA EN GRANO X250G | C34: g | D34: 2 | E34: 0 | F34: 2 | G34: =+VLOOKUP(Tabla1103453454455456479108129136118[[#This Row],[Ingrediente]],Tabla34[#All],3,0) -> 416.51208 | H34: =+Tabla1103453454455456479108129136118[[#This Row],[Costo]]*Tabla1103453454455456479108129136118[[#This Row],[Unidades]] -> 833.02417 | J34: VALOR ANTES DE IPO | K34: =+K32-K33 -> 61018.519
B35: QUESO ALPINA PARMESANO RAYADO 2.5 L | C35: g | D35: 40 | E35: 0 | F35: 40 | G35: =+VLOOKUP(Tabla1103453454455456479108129136118[[#This Row],[Ingrediente]],Tabla34[#All],3,0) -> 60.9875 | H35: =+Tabla1103453454455456479108129136118[[#This Row],[Costo]]*Tabla1103453454455456479108129136118[[#This Row],[Unidades]] -> 2439.5 | J35: MARGEN. | K35: =+K31/K34 -> 0.37349327
B36: SAL REFISAL X 1000G | C36: g | D36: 2 | E36: 0 | F36: 2 | G36: =+VLOOKUP(Tabla1103453454455456479108129136118[[#This Row],[Ingrediente]],Tabla34[#All],3,0) -> 2.6999076 | H36: =+Tabla1103453454455456479108129136118[[#This Row],[Costo]]*Tabla1103453454455456479108129136118[[#This Row],[Unidades]] -> 5.3998151 | J36: GANANCIA | K36: =+K34-K31 -> 38228.513
B37: SOLOMITO X 200G | C37: uds | D37: 1 | E37: 0 | F37: 1 | G37: =+VLOOKUP(Tabla1103453454455456479108129136118[[#This Row],[Ingrediente]],Tabla34[#All],3,0) -> 12280 | H37: =+Tabla1103453454455456479108129136118[[#This Row],[Costo]]*Tabla1103453454455456479108129136118[[#This Row],[Unidades]] -> 12280 | J37: MARGEN PORCENTUAL | K37: =+K36/K31 -> 1.6774244
B38: SUB. PASTA DE AJO | C38: g | D38: 3 | E38: 0 | F38: 3 | G38: =+VLOOKUP(Tabla1103453454455456479108129136118[[#This Row],[Ingrediente]],Tabla34[#All],3,0) -> 10.625185 | H38: =+Tabla1103453454455456479108129136118[[#This Row],[Costo]]*Tabla1103453454455456479108129136118[[#This Row],[Unidades]] -> 31.875556
B39: VINO BLANCO CAVIC TETRAPACK X 1LT | C39: g | D39: 15 | E39: 0 | F39: 15 | G39: =+VLOOKUP(Tabla1103453454455456479108129136118[[#This Row],[Ingrediente]],Tabla34[#All],3,0) -> 16.0345 | H39: =+Tabla1103453454455456479108129136118[[#This Row],[Costo]]*Tabla1103453454455456479108129136118[[#This Row],[Unidades]] -> 240.5175
B40: CHAMPIÃ‘ON X KILO | C40: g | D40: 50 | E40: 0 | F40: 50 | G40: =+VLOOKUP(Tabla1103453454455456479108129136118[[#This Row],[Ingrediente]],Tabla34[#All],3,0) -> 27 | H40: =+Tabla1103453454455456479108129136118[[#This Row],[Costo]]*Tabla1103453454455456479108129136118[[#This Row],[Unidades]] -> 1350
B41: AJI DULCE X KILO | C41: g | D41: 15 | E41: 5 | F41: 15.789 | G41: =+VLOOKUP(Tabla1103453454455456479108129136118[[#This Row],[Ingrediente]],Tabla34[#All],3,0) -> 8 | H41: =+Tabla1103453454455456479108129136118[[#This Row],[Costo]]*Tabla1103453454455456479108129136118[[#This Row],[Unidades]] -> 126.312
B42: CEBOLLA MORADA LIMPIA | C42: g | D42: 30 | E42: 0 | F42: 30 | G42: =+VLOOKUP(Tabla1103453454455456479108129136118[[#This Row],[Ingrediente]],Tabla34[#All],3,0) -> 3.8 | H42: =+Tabla1103453454455456479108129136118[[#This Row],[Costo]]*Tabla1103453454455456479108129136118[[#This Row],[Unidades]] -> 114
B43: SUB. MIX DE VERDURAS | C43: uds | D43: 1 | E43: 0 | F43: 1 | G43: =+VLOOKUP(Tabla1103453454455456479108129136118[[#This Row],[Ingrediente]],Tabla34[#All],3,0) -> 497.5 | H43: =+Tabla1103453454455456479108129136118[[#This Row],[Costo]]*Tabla1103453454455456479108129136118[[#This Row],[Unidades]] -> 497.5
B44: SALSA DE SOYA X 2O LITROS | C44: g | D44: 10 | E44: 0 | F44: 10 | G44: =+VLOOKUP(Tabla1103453454455456479108129136118[[#This Row],[Ingrediente]],Tabla34[#All],3,0) -> 8.925 | H44: =+Tabla1103453454455456479108129136118[[#This Row],[Costo]]*Tabla1103453454455456479108129136118[[#This Row],[Unidades]] -> 89.25
B45: VINO BLANCO CAVIC TETRAPACK X 1LT | C45: g | D45: 10 | E45: 0 | F45: 10 | G45: =+VLOOKUP(Tabla1103453454455456479108129136118[[#This Row],[Ingrediente]],Tabla34[#All],3,0) -> 16.0345 | H45: =+Tabla1103453454455456479108129136118[[#This Row],[Costo]]*Tabla1103453454455456479108129136118[[#This Row],[Unidades]] -> 160.345
B46: ACEITE DE AJONJOLI KADOYA X 1.62LT | C46: g | D46: 10 | E46: 0 | F46: 10 | G46: =+VLOOKUP(Tabla1103453454455456479108129136118[[#This Row],[Ingrediente]],Tabla34[#All],3,0) -> 84.475309 | H46: =+Tabla1103453454455456479108129136118[[#This Row],[Costo]]*Tabla1103453454455456479108129136118[[#This Row],[Unidades]] -> 844.75309
H47: =SUBTOTAL(109,Tabla1103453454455456479108129136118[Total costo]) -> 21704.767
B51: LOMO ANTICUCHERO | J51: ANALISIS RECETA
B52: Ingrediente | C52: Und | D52: Cant. | E52: Columna2 | F52: Columna1 | G52: Costo | H52: Total costo | J52: COSTO DEL PLATO | K52: =SUM(Tabla1103453454455456479108131138129[Total costo]) -> 21400.281
B53: SOLOMITO X 200G | C53: uds | D53: 1 | E53: 0 | F53: 1 | G53: =+VLOOKUP(Tabla1103453454455456479108131138129[[#This Row],[Ingrediente]],Tabla34[#All],3,0) -> 12280 | H53: =+Tabla1103453454455456479108131138129[[#This Row],[Costo]]*Tabla1103453454455456479108131138129[[#This Row],[Columna1]] -> 12280 | J53: MARGEN DE ERROR DEL 5% | K53: =+K52*5% -> 1070.014
B54: SUB. SALSA ANTICUCHERA | C54: g | D54: 90 | E54: 0 | F54: 90 | G54: =+VLOOKUP(Tabla1103453454455456479108131138129[[#This Row],[Ingrediente]],Tabla34[#All],3,0) -> 18 | H54: =+Tabla1103453454455456479108131138129[[#This Row],[Costo]]*Tabla1103453454455456479108131138129[[#This Row],[Columna1]] -> 1620 | J54: COSTO + MARGEN ERROR | K54: =+K52+K53 -> 22470.295
B55: SUB. PURE DE PAPA (ROCOTO) | C55: g | D55: 200 | E55: 0 | F55: 200 | G55: =+VLOOKUP(Tabla1103453454455456479108131138129[[#This Row],[Ingrediente]],Tabla34[#All],3,0) -> 10.046057 | H55: =+Tabla1103453454455456479108131138129[[#This Row],[Costo]]*Tabla1103453454455456479108131138129[[#This Row],[Columna1]] -> 2009.2115 | J55: VALOR DE VENTA | K55: 63900
B56: SUB. PASTA DE AJI AMARILLO (ROCOTO) | C56: g | D56: 60 | E56: 0 | F56: 60 | G56: =+VLOOKUP(Tabla1103453454455456479108131138129[[#This Row],[Ingrediente]],Tabla34[#All],3,0) -> 23.317904 | H56: =+Tabla1103453454455456479108131138129[[#This Row],[Costo]]*Tabla1103453454455456479108131138129[[#This Row],[Columna1]] -> 1399.0742 | J56: IPOCONSUMO | K56: =+K55/1.08*0.08 -> 4733.3333
B57: SUB. CHIMICHURRI (ROCOTO) | C57: g | D57: 20 | E57: 0 | F57: 20 | G57: =+VLOOKUP(Tabla1103453454455456479108131138129[[#This Row],[Ingrediente]],Tabla34[#All],3,0) -> 64.196282 | H57: =+Tabla1103453454455456479108131138129[[#This Row],[Costo]]*Tabla1103453454455456479108131138129[[#This Row],[Columna1]] -> 1283.9256 | J57: VALOR ANTES DE IPO | K57: =+K55-K56 -> 59166.667
B58: CREMA DE LECHE X 9700G | C58: g | D58: 60 | E58: 0 | F58: 60 | G58: =+VLOOKUP(Tabla1103453454455456479108131138129[[#This Row],[Ingrediente]],Tabla34[#All],3,0) -> 17.008247 | H58: =+Tabla1103453454455456479108131138129[[#This Row],[Costo]]*Tabla1103453454455456479108131138129[[#This Row],[Columna1]] -> 1020.4948 | J58: MARGEN. | K58: =+K54/K57 -> 0.37977963
B59: ACEITE MESTRE OLEO X 3000CC | C59: g | D59: 40 | E59: 0 | F59: 40 | G59: =+VLOOKUP(Tabla1103453454455456479108131138129[[#This Row],[Ingrediente]],Tabla34[#All],3,0) -> 18.859 | H59: =+Tabla1103453454455456479108131138129[[#This Row],[Costo]]*Tabla1103453454455456479108131138129[[#This Row],[Columna1]] -> 754.36 | J59: GANANCIA | K59: =+K57-K54 -> 36696.372
B60: CREMA DE LECHE X 9700G | C60: g | D60: 30 | E60: 0 | F60: 30 | G60: =+VLOOKUP(Tabla1103453454455456479108131138129[[#This Row],[Ingrediente]],Tabla34[#All],3,0) -> 17.008247 | H60: =+Tabla1103453454455456479108131138129[[#This Row],[Costo]]*Tabla1103453454455456479108131138129[[#This Row],[Columna1]] -> 510.24742 | J60: MARGEN PORCENTUAL | K60: =+K59/K54 -> 1.6331059
B61: BROTES DE RABANO 50 | C61: g | D61: 1 | E61: 0 | F61: 1 | G61: =+VLOOKUP(Tabla1103453454455456479108131138129[[#This Row],[Ingrediente]],Tabla34[#All],3,0) -> 328.34 | H61: =+Tabla1103453454455456479108131138129[[#This Row],[Costo]]*Tabla1103453454455456479108131138129[[#This Row],[Columna1]] -> 328.34
B62: PIMIENTA NEGRA MOLIDA BADIA 453GR | C62: g | D62: 2 | E62: 0 | F62: 2 | G62: =+VLOOKUP(Tabla1103453454455456479108131138129[[#This Row],[Ingrediente]],Tabla34[#All],3,0) -> 94.613742 | H62: =+Tabla1103453454455456479108131138129[[#This Row],[Costo]]*Tabla1103453454455456479108131138129[[#This Row],[Columna1]] -> 189.22748
B63: SAL REFISAL X 1000G | C63: g | D63: 2 | E63: 0 | F63: 2 | G63: =+VLOOKUP(Tabla1103453454455456479108131138129[[#This Row],[Ingrediente]],Tabla34[#All],3,0) -> 2.6999076 | H63: =+Tabla1103453454455456479108131138129[[#This Row],[Costo]]*Tabla1103453454455456479108131138129[[#This Row],[Columna1]] -> 5.3998151
H64: =SUBTOTAL(109,Tabla1103453454455456479108131138129[Total costo]) -> 21400.281
B66: COSTILLA ROCOTO | J66: ANALISIS RECETA
B67: Ingrediente | C67: Und | D67: Cant. | E67: Columna2 | F67: Columna1 | G67: Costo | H67: Total costo | J67: COSTO DEL PLATO | K67: =SUM(Tabla1103453454455456479108132139130[Total costo]) -> 20762.542
B68: SUB. COSTILLAS (ROCOTO) | C68: uds | D68: 1 | E68: 0 | F68: 1 | G68: =+VLOOKUP(Tabla1103453454455456479108132139130[[#This Row],[Ingrediente]],Tabla34[#All],3,0) -> 15663.996 | H68: =+Tabla1103453454455456479108132139130[[#This Row],[Costo]]*Tabla1103453454455456479108132139130[[#This Row],[Columna1]] -> 15663.996 | J68: MARGEN DE ERROR DEL 5% | K68: =+K67*5% -> 1038.1271
B69: SUB. SALSA ANTICUCHERA BBQ ANTICUCHERA | C69: g | D69: 240 | E69: 0 | F69: 240 | G69: =+VLOOKUP(Tabla1103453454455456479108132139130[[#This Row],[Ingrediente]],Tabla34[#All],3,0) -> 15.555053 | H69: =+Tabla1103453454455456479108132139130[[#This Row],[Costo]]*Tabla1103453454455456479108132139130[[#This Row],[Columna1]] -> 3733.2128 | J69: COSTO + MARGEN ERROR | K69: =+K67+K68 -> 21800.669
B70: CEBOLLIN*KILO | C70: g | D70: 2 | E70: 0 | F70: 2 | G70: =+VLOOKUP(Tabla1103453454455456479108132139130[[#This Row],[Ingrediente]],Tabla34[#All],3,0) -> 16 | H70: =+Tabla1103453454455456479108132139130[[#This Row],[Costo]]*Tabla1103453454455456479108132139130[[#This Row],[Columna1]] -> 32 | J70: VALOR DE VENTA | K70: 65900
B71: SUB. PAPA CRIOLLA | C71: uds | D71: 1 | E71: 0 | F71: 1 | G71: =+VLOOKUP(Tabla1103453454455456479108132139130[[#This Row],[Ingrediente]],Tabla34[#All],3,0) -> 1333.3333 | H71: =+Tabla1103453454455456479108132139130[[#This Row],[Costo]]*Tabla1103453454455456479108132139130[[#This Row],[Columna1]] -> 1333.3333 | J71: IPOCONSUMO | K71: =+K70/1.08*0.08 -> 4881.4815
H72: =SUBTOTAL(109,Tabla1103453454455456479108132139130[Total costo]) -> 20762.542 | J72: VALOR ANTES DE IPO | K72: =+K70-K71 -> 61018.519
J73: MARGEN. | K73: =+K69/K72 -> 0.35727955
J74: GANANCIA | K74: =+K72-K69 -> 39217.85
J75: MARGEN PORCENTUAL | K75: =+K74/K69 -> 1.7989287
B85: TACU TACU DE LOMO SALTADO CLASICO | J85: ANALISIS RECETA
B86: Ingrediente | C86: Und | D86: Cant. | E86: Columna2 | F86: Columna1 | G86: Costo | H86: Total costo | J86: COSTO DEL PLATO | K86: =SUM(Tabla1103453454455456479108132139130429[Total costo]) -> #N/A
B87: AJI AMARILLO X KILO | C87: g | D87: 15 | E87: 10 | F87: 16.667 | G87: =+VLOOKUP(Tabla1103453454455456479108132139130429[[#This Row],[Ingrediente]],Tabla34[#All],3,0) -> 13 | H87: =+Tabla1103453454455456479108132139130429[[#This Row],[Costo]]*Tabla1103453454455456479108132139130429[[#This Row],[Columna1]] -> 216.671 | J87: MARGEN DE ERROR DEL 5% | K87: =+K86*5% -> #N/A
B88: AJINOMOTO X KILO | C88: g | D88: 2 | E88: 0 | F88: 2 | G88: =+VLOOKUP(Tabla1103453454455456479108132139130429[[#This Row],[Ingrediente]],Tabla34[#All],3,0) -> 20.111 | H88: =+Tabla1103453454455456479108132139130429[[#This Row],[Costo]]*Tabla1103453454455456479108132139130429[[#This Row],[Columna1]] -> 40.222 | J88: COSTO + MARGEN ERROR | K88: =+K86+K87 -> #N/A
B89: BROTES DE RABANO 50 | C89: g | D89: 1 | E89: 0 | F89: 1 | G89: =+VLOOKUP(Tabla1103453454455456479108132139130429[[#This Row],[Ingrediente]],Tabla34[#All],3,0) -> 328.34 | H89: =+Tabla1103453454455456479108132139130429[[#This Row],[Costo]]*Tabla1103453454455456479108132139130429[[#This Row],[Columna1]] -> 328.34 | J89: VALOR DE VENTA | K89: 62000
B90: CEBOLLA MORADA LIMPIA | C90: g | D90: 50 | E90: 27 | F90: 68.493 | G90: =+VLOOKUP(Tabla1103453454455456479108132139130429[[#This Row],[Ingrediente]],Tabla34[#All],3,0) -> 3.8 | H90: =+Tabla1103453454455456479108132139130429[[#This Row],[Costo]]*Tabla1103453454455456479108132139130429[[#This Row],[Columna1]] -> 260.2734 | J90: IPOCONSUMO | K90: =+K89/1.08*0.08 -> 4592.5926
B91: CILANTRO LIMPIO X KILO | C91: g | D91: 3 | E91: 40 | F91: 5 | G91: =+VLOOKUP(Tabla1103453454455456479108132139130429[[#This Row],[Ingrediente]],Tabla34[#All],3,0) -> 5.5 | H91: =+Tabla1103453454455456479108132139130429[[#This Row],[Costo]]*Tabla1103453454455456479108132139130429[[#This Row],[Columna1]] -> 27.5 | J91: VALOR ANTES DE IPO | K91: =+K89-K90 -> 57407.407
B92: COMINO MOLIDO X 500GR | C92: g | D92: 2 | E92: 0 | F92: 2 | G92: =+VLOOKUP(Tabla1103453454455456479108132139130429[[#This Row],[Ingrediente]],Tabla34[#All],3,0) -> 58.140353 | H92: =+Tabla1103453454455456479108132139130429[[#This Row],[Costo]]*Tabla1103453454455456479108132139130429[[#This Row],[Columna1]] -> 116.28071 | J92: MARGEN. | K92: =+K88/K91 -> #N/A
B93: HUEVO DE CODORNIZ *24UND | C93: uds | D93: 3 | E93: 0 | F93: 3 | G93: =+VLOOKUP(Tabla1103453454455456479108132139130429[[#This Row],[Ingrediente]],Tabla34[#All],3,0) -> 354.16667 | H93: =+Tabla1103453454455456479108132139130429[[#This Row],[Costo]]*Tabla1103453454455456479108132139130429[[#This Row],[Columna1]] -> 1062.5 | J93: GANANCIA | K93: =+K91-K88 -> #N/A
B94: PIMIENTA NEGRA MOLIDA BADIA 453GR | C94: g | D94: 1 | E94: 0 | F94: 1 | G94: =+VLOOKUP(Tabla1103453454455456479108132139130429[[#This Row],[Ingrediente]],Tabla34[#All],3,0) -> 94.613742 | H94: =+Tabla1103453454455456479108132139130429[[#This Row],[Costo]]*Tabla1103453454455456479108132139130429[[#This Row],[Columna1]] -> 94.613742 | J94: MARGEN PORCENTUAL | K94: =+K93/K88 -> #N/A
B95: PLATANO MADURO | C95: g | D95: 80 | E95: 20 | F95: 100 | G95: =+VLOOKUP(Tabla1103453454455456479108132139130429[[#This Row],[Ingrediente]],Tabla34[#All],3,0) -> 3.4 | H95: =+Tabla1103453454455456479108132139130429[[#This Row],[Costo]]*Tabla1103453454455456479108132139130429[[#This Row],[Columna1]] -> 340
B96: SAL REFISAL X 1000G | C96: g | D96: 1 | E96: 0 | F96: 1 | G96: =+VLOOKUP(Tabla1103453454455456479108132139130429[[#This Row],[Ingrediente]],Tabla34[#All],3,0) -> 2.6999076 | H96: =+Tabla1103453454455456479108132139130429[[#This Row],[Costo]]*Tabla1103453454455456479108132139130429[[#This Row],[Columna1]] -> 2.6999076
B97: SALSA DE OSTRAS ASIAFOOD PO 2LT | C97: g | D97: 40 | E97: 0 | F97: 40 | G97: =+VLOOKUP(Tabla1103453454455456479108132139130429[[#This Row],[Ingrediente]],Tabla34[#All],3,0) -> 26.269316 | H97: =+Tabla1103453454455456479108132139130429[[#This Row],[Costo]]*Tabla1103453454455456479108132139130429[[#This Row],[Columna1]] -> 1050.7726
B98: SALSA DE SOYA X 2O LITROS | C98: g | D98: 80 | E98: 0 | F98: 80 | G98: =+VLOOKUP(Tabla1103453454455456479108132139130429[[#This Row],[Ingrediente]],Tabla34[#All],3,0) -> 8.925 | H98: =+Tabla1103453454455456479108132139130429[[#This Row],[Costo]]*Tabla1103453454455456479108132139130429[[#This Row],[Columna1]] -> 714
B99: SOLOMITO X 200G | C99: uds | D99: 1 | E99: 0 | F99: 1 | G99: =+VLOOKUP(Tabla1103453454455456479108132139130429[[#This Row],[Ingrediente]],Tabla34[#All],3,0) -> 12280 | H99: =+Tabla1103453454455456479108132139130429[[#This Row],[Costo]]*Tabla1103453454455456479108132139130429[[#This Row],[Columna1]] -> 12280
B100: SUB. FONDO DE PESCADO | C100: g | D100: 20 | E100: 0 | F100: 20 | G100: =+VLOOKUP(Tabla1103453454455456479108132139130429[[#This Row],[Ingrediente]],Tabla34[#All],3,0) -> 4.5393524 | H100: =+Tabla1103453454455456479108132139130429[[#This Row],[Costo]]*Tabla1103453454455456479108132139130429[[#This Row],[Columna1]] -> 90.787048
B101: SUB. MEZCLADE TACU TACU | C101: uds | D101: 1 | E101: 0 | F101: 1 | G101: =+VLOOKUP(Tabla1103453454455456479108132139130429[[#This Row],[Ingrediente]],Tabla34[#All],3,0) -> 1758.6011 | H101: =+Tabla1103453454455456479108132139130429[[#This Row],[Costo]]*Tabla1103453454455456479108132139130429[[#This Row],[Columna1]] -> 1758.6011
B102: SUB. VINAGRE BLANCO | C102: g | D102: 20 | E102: 0 | F102: 20 | G102: =+VLOOKUP(Tabla1103453454455456479108132139130429[[#This Row],[Ingrediente]],Tabla34[#All],3,0) -> #N/A | H102: =+Tabla1103453454455456479108132139130429[[#This Row],[Costo]]*Tabla1103453454455456479108132139130429[[#This Row],[Columna1]] -> #N/A
B103: TOMATE CHONTO X KILO | C103: g | D103: 60 | E103: 30 | F103: 85.714 | G103: =+VLOOKUP(Tabla1103453454455456479108132139130429[[#This Row],[Ingrediente]],Tabla34[#All],3,0) -> 2.5 | H103: =+Tabla1103453454455456479108132139130429[[#This Row],[Costo]]*Tabla1103453454455456479108132139130429[[#This Row],[Columna1]] -> 214.285
H104: =SUBTOTAL(109,Tabla1103453454455456479108132139130429[Total costo]) -> #N/A
B108: AJÃ DE GALLINA | J108: ANALISIS RECETA
B109: Ingrediente | C109: Und | D109: Cant. | E109: Columna2 | F109: Columna1 | G109: Costo | H109: Total costo | J109: COSTO DEL PLATO | K109: =SUM(Tabla110345345445545647910813213913042975[Total costo]) -> 14733.783
B110: ACEITUNAS MORADA ALFA *1000g | C110: g | D110: 10 | E110: 0 | F110: 10 | G110: =+VLOOKUP(Tabla110345345445545647910813213913042975[[#This Row],[Ingrediente]],Tabla34[#All],3,0) -> 39.473 | H110: =+Tabla110345345445545647910813213913042975[[#This Row],[Costo]]*Tabla110345345445545647910813213913042975[[#This Row],[Columna1]] -> 394.73 | J110: MARGEN DE ERROR DEL 5% | K110: =+K109*5% -> 736.68917
B111: AJINOMOTO X KILO | C111: g | D111: 1 | E111: 0 | F111: 1 | G111: =+VLOOKUP(Tabla110345345445545647910813213913042975[[#This Row],[Ingrediente]],Tabla34[#All],3,0) -> 20.111 | H111: =+Tabla110345345445545647910813213913042975[[#This Row],[Costo]]*Tabla110345345445545647910813213913042975[[#This Row],[Columna1]] -> 20.111 | J111: COSTO + MARGEN ERROR | K111: =+K109+K110 -> 15470.473
B112: CILANTRO LIMPIO X KILO | C112: g | D112: 3 | E112: 40 | F112: 5 | G112: =+VLOOKUP(Tabla110345345445545647910813213913042975[[#This Row],[Ingrediente]],Tabla34[#All],3,0) -> 5.5 | H112: =+Tabla110345345445545647910813213913042975[[#This Row],[Costo]]*Tabla110345345445545647910813213913042975[[#This Row],[Columna1]] -> 27.5 | J112: VALOR DE VENTA | K112: 49000
B113: COMINO MOLIDO X 500GR | C113: g | D113: 4 | E113: 0 | F113: 4 | G113: =+VLOOKUP(Tabla110345345445545647910813213913042975[[#This Row],[Ingrediente]],Tabla34[#All],3,0) -> 58.140353 | H113: =+Tabla110345345445545647910813213913042975[[#This Row],[Costo]]*Tabla110345345445545647910813213913042975[[#This Row],[Columna1]] -> 232.56141 | J113: IPOCONSUMO | K113: =+K112/1.08*0.08 -> 3629.6296
B114: CREMA DE LECHE X 9700G | C114: g | D114: 150 | E114: 0 | F114: 150 | G114: =+VLOOKUP(Tabla110345345445545647910813213913042975[[#This Row],[Ingrediente]],Tabla34[#All],3,0) -> 17.008247 | H114: =+Tabla110345345445545647910813213913042975[[#This Row],[Costo]]*Tabla110345345445545647910813213913042975[[#This Row],[Columna1]] -> 2551.2371 | J114: VALOR ANTES DE IPO | K114: =+K112-K113 -> 45370.37
B115: HUEVO DE CODORNIZ *24UND | C115: uds | D115: 2 | E115: 0 | F115: 2 | G115: =+VLOOKUP(Tabla110345345445545647910813213913042975[[#This Row],[Ingrediente]],Tabla34[#All],3,0) -> 354.16667 | H115: =+Tabla110345345445545647910813213913042975[[#This Row],[Costo]]*Tabla110345345445545647910813213913042975[[#This Row],[Columna1]] -> 708.33333 | J115: MARGEN. | K115: =+K111/K114 -> 0.34098184
B116: NUEZ PECANA X 907 GR | C116: g | D116: 1 | E116: 0 | F116: 1 | G116: =+VLOOKUP(Tabla110345345445545647910813213913042975[[#This Row],[Ingrediente]],Tabla34[#All],3,0) -> 116.4796 | H116: =+Tabla110345345445545647910813213913042975[[#This Row],[Costo]]*Tabla110345345445545647910813213913042975[[#This Row],[Columna1]] -> 116.4796 | J116: GANANCIA | K116: =+K114-K111 -> 29899.898
B117: PAPA NEVADA X KILO | C117: g | D117: 120 | E117: 5 | F117: 126.316 | G117: =+VLOOKUP(Tabla110345345445545647910813213913042975[[#This Row],[Ingrediente]],Tabla34[#All],3,0) -> 4 | H117: =+Tabla110345345445545647910813213913042975[[#This Row],[Costo]]*Tabla110345345445545647910813213913042975[[#This Row],[Columna1]] -> 505.264 | J117: MARGEN PORCENTUAL | K117: =+K116/K111 -> 1.9327075
B118: QUESO ALPINA PARMESANO RAYADO 2.5 L | C118: g | D118: 40 | E118: 0 | F118: 40 | G118: =+VLOOKUP(Tabla110345345445545647910813213913042975[[#This Row],[Ingrediente]],Tabla34[#All],3,0) -> 60.9875 | H118: =+Tabla110345345445545647910813213913042975[[#This Row],[Costo]]*Tabla110345345445545647910813213913042975[[#This Row],[Columna1]] -> 2439.5
B119: SAL REFISAL X 1000G | C119: g | D119: 5 | E119: 0 | F119: 5 | G119: =+VLOOKUP(Tabla110345345445545647910813213913042975[[#This Row],[Ingrediente]],Tabla34[#All],3,0) -> 2.6999076 | H119: =+Tabla110345345445545647910813213913042975[[#This Row],[Costo]]*Tabla110345345445545647910813213913042975[[#This Row],[Columna1]] -> 13.499538
B120: SUB. ADEREZO DE CEBOLLA | C120: g | D120: 10 | E120: 0 | F120: 10 | G120: =+VLOOKUP(Tabla110345345445545647910813213913042975[[#This Row],[Ingrediente]],Tabla34[#All],3,0) -> 12.807238 | H120: =+Tabla110345345445545647910813213913042975[[#This Row],[Costo]]*Tabla110345345445545647910813213913042975[[#This Row],[Columna1]] -> 128.07238
B121: SUB. ARROZ COCIDO | C121: g | D121: 100 | E121: 0 | F121: 100 | G121: =+VLOOKUP(Tabla110345345445545647910813213913042975[[#This Row],[Ingrediente]],Tabla34[#All],3,0) -> 4.8201292 | H121: =+Tabla110345345445545647910813213913042975[[#This Row],[Costo]]*Tabla110345345445545647910813213913042975[[#This Row],[Columna1]] -> 482.01292
B122: SUB. PASTA DE AJI AMARILLO (ROCOTO) | C122: g | D122: 150 | E122: 0 | F122: 150 | G122: =+VLOOKUP(Tabla110345345445545647910813213913042975[[#This Row],[Ingrediente]],Tabla34[#All],3,0) -> 23.317904 | H122: =+Tabla110345345445545647910813213913042975[[#This Row],[Costo]]*Tabla110345345445545647910813213913042975[[#This Row],[Columna1]] -> 3497.6856
...

Sheet ENTRADAS
B6: TIRADITO TRES SABORES | J6: ANALISIS RECETA
B7: Ingrediente | C7: Und | D7: Unidades Netas | E7: % Merma | F7: Unidades | G7: Costo | H7: Total costo | J7: COSTO DEL PLATO | K7: =SUM(Tabla1103453454455456479108109[Total costo]) -> 12361.851
B8: AGUACATE CHOCKETTE X KILO | C8: g | D8: 30 | E8: 25 | F8: 40 | G8: =+VLOOKUP(Tabla1103453454455456479108109[[#This Row],[Ingrediente]],Tabla34[#All],3,0) -> 14 | H8: =+Tabla1103453454455456479108109[[#This Row],[Costo]]*Tabla1103453454455456479108109[[#This Row],[Unidades]] -> 560 | J8: MARGEN DE ERROR DEL 5% | K8: =+K7*5% -> 618.09257
B9: BROTES DE RABANO 50 | C9: g | D9: 1 | E9: 0 | F9: 1 | G9: =+VLOOKUP(Tabla1103453454455456479108109[[#This Row],[Ingrediente]],Tabla34[#All],3,0) -> 328.34 | H9: =+Tabla1103453454455456479108109[[#This Row],[Costo]]*Tabla1103453454455456479108109[[#This Row],[Unidades]] -> 328.34 | J9: COSTO + MARGEN ERROR | K9: =+K7+K8 -> 12979.944
B10: FILETE DE ATUN ENTERO KG | C10: g | D10: 50 | E10: 10 | F10: 55.556 | G10: =+VLOOKUP(Tabla1103453454455456479108109[[#This Row],[Ingrediente]],Tabla34[#All],3,0) -> 51.296296 | H10: =+Tabla1103453454455456479108109[[#This Row],[Costo]]*Tabla1103453454455456479108109[[#This Row],[Unidades]] -> 2849.817 | J10: VALOR DE VENTA | K10: 57000
B11: FILETE DE TILAPIA FRESCA LO | C11: g | D11: 50 | E11: 10 | F11: 55.556 | G11: =+VLOOKUP(Tabla1103453454455456479108109[[#This Row],[Ingrediente]],Tabla34[#All],3,0) -> 37 | H11: =+Tabla1103453454455456479108109[[#This Row],[Costo]]*Tabla1103453454455456479108109[[#This Row],[Unidades]] -> 2055.572 | J11: IPOCONSUMO | K11: =+K10/1.08*0.08 -> 4222.2222
B12: MAIZ CANCHA | C12: g | D12: 5 | E12: 0 | F12: 5 | G12: =+VLOOKUP(Tabla1103453454455456479108109[[#This Row],[Ingrediente]],Tabla34[#All],3,0) -> 15 | H12: =+Tabla1103453454455456479108109[[#This Row],[Costo]]*Tabla1103453454455456479108109[[#This Row],[Unidades]] -> 75 | J12: VALOR ANTES DE IPO | K12: =+K10-K11 -> 52777.778
B13: SALMON FRESCO 3-4TD | C13: g | D13: 50 | E13: 10 | F13: 55.556 | G13: =+VLOOKUP(Tabla1103453454455456479108109[[#This Row],[Ingrediente]],Tabla34[#All],3,0) -> 55 | H13: =+Tabla1103453454455456479108109[[#This Row],[Costo]]*Tabla1103453454455456479108109[[#This Row],[Unidades]] -> 3055.58 | J13: MARGEN. | K13: =+K9/K12 -> 0.24593578
B14: SUB. ACEITE DE CILANTRO | C14: g | D14: 10 | E14: 0 | F14: 10 | G14: =+VLOOKUP(Tabla1103453454455456479108109[[#This Row],[Ingrediente]],Tabla34[#All],3,0) -> 16.110971 | H14: =+Tabla1103453454455456479108109[[#This Row],[Costo]]*Tabla1103453454455456479108109[[#This Row],[Unidades]] -> 161.10971 | J14: GANANCIA | K14: =+K12-K9 -> 39797.834
B15: SUB. BASE LECHE DE TIGRE | C15: g | D15: 90 | E15: 0 | F15: 90 | G15: =+VLOOKUP(Tabla1103453454455456479108109[[#This Row],[Ingrediente]],Tabla34[#All],3,0) -> 10.179495 | H15: =+Tabla1103453454455456479108109[[#This Row],[Costo]]*Tabla1103453454455456479108109[[#This Row],[Unidades]] -> 916.15458 | J15: MARGEN PORCENTUAL | K15: =+K14/K9 -> 3.0661022
B16: SUB. CAMOTE GLASEADO | C16: g | D16: 20 | E16: 0 | F16: 20 | G16: =+VLOOKUP(Tabla1103453454455456479108109[[#This Row],[Ingrediente]],Tabla34[#All],3,0) -> 11.90893 | H16: =+Tabla1103453454455456479108109[[#This Row],[Costo]]*Tabla1103453454455456479108109[[#This Row],[Unidades]] -> 238.1786
B17: SUB. CHALACA | C17: g | D17: 30 | E17: 0 | F17: 30 | G17: =+VLOOKUP(Tabla1103453454455456479108109[[#This Row],[Ingrediente]],Tabla34[#All],3,0) -> 11.132676 | H17: =+Tabla1103453454455456479108109[[#This Row],[Costo]]*Tabla1103453454455456479108109[[#This Row],[Unidades]] -> 333.98027
B18: SUB. PASTA DE AJI AMARILLO (ROCOTO) | C18: g | D18: 50 | E18: 0 | F18: 50 | G18: =+VLOOKUP(Tabla1103453454455456479108109[[#This Row],[Ingrediente]],Tabla34[#All],3,0) -> 23.317904 | H18: =+Tabla1103453454455456479108109[[#This Row],[Costo]]*Tabla1103453454455456479108109[[#This Row],[Unidades]] -> 1165.8952
B19: SUB. PASTA DE AJI ROCOTO (PC) | C19: g | D19: 50 | E19: 0 | F19: 50 | G19: =+VLOOKUP(Tabla1103453454455456479108109[[#This Row],[Ingrediente]],Tabla34[#All],3,0) -> 12.444478 | H19: =+Tabla1103453454455456479108109[[#This Row],[Costo]]*Tabla1103453454455456479108109[[#This Row],[Unidades]] -> 622.2239
H20: =SUBTOTAL(109,Tabla1103453454455456479108109[Total costo]) -> 12361.851
B25: CHIPS | J25: ANALISIS RECETA
B26: Ingrediente | C26: Und | D26: Unidades Netas | E26: % Merma | F26: Unidades | G26: Costo | H26: Total costo | J26: COSTO DEL PLATO | K26: =+Tabla1103453454455456479108109113[[#Totals],[Total costo]] -> 1962.4722
B27: SUB. CHIPS DE PLATANO | C27: g | D27: 40 | E27: 0 | F27: 40 | G27: =+VLOOKUP(Tabla1103453454455456479108109113[[#This Row],[Ingrediente]],Tabla34[#All],3,0) -> 9.7905401 | H27: =+Tabla1103453454455456479108109113[[#This Row],[Costo]]*Tabla1103453454455456479108109113[[#This Row],[Unidades]] -> 391.6216 | J27: MARGEN DE ERROR DEL 5% | K27: =+K26*5% -> 98.123612
B28: SUB. CHIPS DE YUCA | C28: g | D28: 40 | E28: 0 | F28: 40 | G28: =+VLOOKUP(Tabla1103453454455456479108109113[[#This Row],[Ingrediente]],Tabla34[#All],3,0) -> 11.478188 | H28: =+Tabla1103453454455456479108109113[[#This Row],[Costo]]*Tabla1103453454455456479108109113[[#This Row],[Unidades]] -> 459.12754 | J28: COSTO + MARGEN ERROR | K28: =+K26+K27 -> 2060.5958
B29: SUB. HUANCAINA | C29: g | D29: 30 | E29: 0 | F29: 30 | G29: =+VLOOKUP(Tabla1103453454455456479108109113[[#This Row],[Ingrediente]],Tabla34[#All],3,0) -> 12.253166 | H29: =+Tabla1103453454455456479108109113[[#This Row],[Costo]]*Tabla1103453454455456479108109113[[#This Row],[Unidades]] -> 367.59498 | J29: VALOR DE VENTA | K29: 29900
B30: SUB. GUACAMOLE (ROCOTO) | C30: g | D30: 30 | E30: 0 | F30: 30 | G30: =+VLOOKUP(Tabla1103453454455456479108109113[[#This Row],[Ingrediente]],Tabla34[#All],3,0) -> 24.804271 | H30: =+Tabla1103453454455456479108109113[[#This Row],[Costo]]*Tabla1103453454455456479108109113[[#This Row],[Unidades]] -> 744.12812 | J30: IPOCONSUMO | K30: =+K29/1.08*0.08 -> 2214.8148
H31: =SUBTOTAL(109,Tabla1103453454455456479108109113[Total costo]) -> 1962.4722 | J31: VALOR ANTES DE IPO | K31: =+K29-K30 -> 27685.185
J32: MARGEN. | K32: =+K28/K31 -> 0.074429549
J33: GANANCIA | K33: =+K31-K28 -> 25624.589
J34: MARGEN PORCENTUAL | K34: =+K33/K28 -> 12.435524
B36: CHICHARRONCITOS ACEVICHADOS | J36: ANALISIS RECETA
B37: Ingrediente | C37: Und | D37: Unidades Netas | E37: % Merma | F37: Unidades | G37: Costo | H37: Total costo | J37: COSTO DEL PLATO | K37: =SUM(Tabla1103453454455456479108109114[Total costo]) -> 11281.487
B38: SUB. SALSA DE CHICHARRONES | C38: g | D38: 40 | E38: 0 | F38: 40 | G38: =+VLOOKUP(Tabla1103453454455456479108109114[[#This Row],[Ingrediente]],Tabla34[#All],3,0) -> 17.685474 | H38: =+Tabla1103453454455456479108109114[[#This Row],[Costo]]*Tabla1103453454455456479108109114[[#This Row],[Unidades]] -> 707.41896 | J38: MARGEN DE ERROR DEL 5% | K38: =+K37*5% -> 564.07434
B39: AGUACATE CHOCKETTE X KILO | C39: g | D39: 40 | E39: 25 | F39: 53.333 | G39: =+VLOOKUP(Tabla1103453454455456479108109114[[#This Row],[Ingrediente]],Tabla34[#All],3,0) -> 14 | H39: =+Tabla1103453454455456479108109114[[#This Row],[Costo]]*Tabla1103453454455456479108109114[[#This Row],[Unidades]] -> 746.662 | J39: COSTO + MARGEN ERROR | K39: =+K37+K38 -> 11845.561
B40: SUB. CHIPS DE PLATANO | C40: g | D40: 20 | E40: 0 | F40: 20 | G40: =+VLOOKUP(Tabla1103453454455456479108109114[[#This Row],[Ingrediente]],Tabla34[#All],3,0) -> 9.7905401 | H40: =+Tabla1103453454455456479108109114[[#This Row],[Costo]]*Tabla1103453454455456479108109114[[#This Row],[Unidades]] -> 195.8108 | J40: VALOR DE VENTA | K40: 49000
B41: CHICHARRON UND*300G | C41: uds | D41: 1 | E41: 0 | F41: 1 | G41: =+VLOOKUP(Tabla1103453454455456479108109114[[#This Row],[Ingrediente]],Tabla34[#All],3,0) -> 8755 | H41: =+Tabla1103453454455456479108109114[[#This Row],[Costo]]*Tabla1103453454455456479108109114[[#This Row],[Unidades]] -> 8755 | J41: IPOCONSUMO | K41: =+K40/1.08*0.08 -> 3629.6296
B42: SUB. BASE LECHE DE TIGRE | C42: g | D42: 10 | E42: 0 | F42: 10 | G42: =+VLOOKUP(Tabla1103453454455456479108109114[[#This Row],[Ingrediente]],Tabla34[#All],3,0) -> 10.179495 | H42: =+Tabla1103453454455456479108109114[[#This Row],[Costo]]*Tabla1103453454455456479108109114[[#This Row],[Unidades]] -> 101.79495 | J42: VALOR ANTES DE IPO | K42: =+K40-K41 -> 45370.37
B43: SUB. MAYONESA ACEVICHADA | C43: g | D43: 30 | E43: 0 | F43: 30 | G43: =+VLOOKUP(Tabla1103453454455456479108109114[[#This Row],[Ingrediente]],Tabla34[#All],3,0) -> 22.545489 | H43: =+Tabla1103453454455456479108109114[[#This Row],[Costo]]*Tabla1103453454455456479108109114[[#This Row],[Unidades]] -> 676.36466 | J43: MARGEN. | K43: =+K39/K42 -> 0.26108584
B44: CEBOLLA MORADA LIMPIA | C44: g | D44: 8 | E44: 20 | F44: 10 | G44: =+VLOOKUP(Tabla1103453454455456479108109114[[#This Row],[Ingrediente]],Tabla34[#All],3,0) -> 3.8 | H44: =+Tabla1103453454455456479108109114[[#This Row],[Costo]]*Tabla1103453454455456479108109114[[#This Row],[Unidades]] -> 38 | J44: GANANCIA | K44: =+K42-K39 -> 33524.809
B45: CILANTRO LIMPIO X KILO | C45: g | D45: 2 | E45: 40 | F45: 3.333 | G45: =+VLOOKUP(Tabla1103453454455456479108109114[[#This Row],[Ingrediente]],Tabla34[#All],3,0) -> 5.5 | H45: =+Tabla1103453454455456479108109114[[#This Row],[Costo]]*Tabla1103453454455456479108109114[[#This Row],[Unidades]] -> 18.3315 | J45: MARGEN PORCENTUAL | K45: =+K44/K39 -> 2.8301579
B46: AJI DULCE X KILO | C46: g | D46: 5 | E46: 5 | F46: 5.263 | G46: =+VLOOKUP(Tabla1103453454455456479108109114[[#This Row],[Ingrediente]],Tabla34[#All],3,0) -> 8 | H46: =+Tabla1103453454455456479108109114[[#This Row],[Costo]]*Tabla1103453454455456479108109114[[#This Row],[Unidades]] -> 42.104
H47: =SUBTOTAL(109,Tabla1103453454455456479108109114[Total costo]) -> 11281.487
B53: PULPO SALTADO | J53: ANALISIS RECETA
B54: Ingrediente | C54: Und | D54: Unidades Netas | E54: % Merma | F54: Unidades | G54: Costo | H54: Total costo | J54: COSTO DEL PLATO | K54: =SUM(Tabla1103453454455456479108109116[Total costo]) -> 28766.968
B55: ACEITE MESTRE OLEO X 3000CC | C55: g | D55: 30 | E55: 0 | F55: 30 | G55: =+VLOOKUP(Tabla1103453454455456479108109116[[#This Row],[Ingrediente]],Tabla34[#All],3,0) -> 18.859 | H55: =+Tabla1103453454455456479108109116[[#This Row],[Costo]]*Tabla1103453454455456479108109116[[#This Row],[Unidades]] -> 565.77 | J55: MARGEN DE ERROR DEL 5% | K55: =+K54*5% -> 1438.3484
B56: TOMATE CHERRY X KILO | C56: g | D56: 60 | E56: 0 | F56: 60 | G56: =+VLOOKUP(Tabla1103453454455456479108109116[[#This Row],[Ingrediente]],Tabla34[#All],3,0) -> 5 | H56: =+Tabla1103453454455456479108109116[[#This Row],[Costo]]*Tabla1103453454455456479108109116[[#This Row],[Unidades]] -> 300 | J56: COSTO + MARGEN ERROR | K56: =+K54+K55 -> 30205.316
B57: SUB. CHIMICHURRI (ROCOTO) | C57: g | D57: 40 | E57: 0 | F57: 40 | G57: =+VLOOKUP(Tabla1103453454455456479108109116[[#This Row],[Ingrediente]],Tabla34[#All],3,0) -> 64.196282 | H57: =+Tabla1103453454455456479108109116[[#This Row],[Costo]]*Tabla1103453454455456479108109116[[#This Row],[Unidades]] -> 2567.8513 | J57: VALOR DE VENTA | K57: 99000
B58: SUB. HUANCAINA | C58: g | D58: 30 | E58: 0 | F58: 30 | G58: =+VLOOKUP(Tabla1103453454455456479108109116[[#This Row],[Ingrediente]],Tabla34[#All],3,0) -> 12.253166 | H58: =+Tabla1103453454455456479108109116[[#This Row],[Costo]]*Tabla1103453454455456479108109116[[#This Row],[Unidades]] -> 367.59498 | J58: IPOCONSUMO | K58: =+K57/1.08*0.08 -> 7333.3333
B59: SUB. PULPO MEXICANO (ROCOTO)*150G | C59: uds | D59: 1 | E59: 0 | F59: 1 | G59: =+VLOOKUP(Tabla1103453454455456479108109116[[#This Row],[Ingrediente]],Tabla34[#All],3,0) -> 20955.187 | H59: =+Tabla1103453454455456479108109116[[#This Row],[Costo]]*Tabla1103453454455456479108109116[[#This Row],[Unidades]] -> 20955.187 | J59: VALOR ANTES DE IPO | K59: =+K57-K58 -> 91666.667
B60: CHAMPIÃ‘ON X KILO | C60: g | D60: 100 | E60: 0 | F60: 100 | G60: =+VLOOKUP(Tabla1103453454455456479108109116[[#This Row],[Ingrediente]],Tabla34[#All],3,0) -> 27 | H60: =+Tabla1103453454455456479108109116[[#This Row],[Costo]]*Tabla1103453454455456479108109116[[#This Row],[Unidades]] -> 2700 | J60: MARGEN. | K60: =+K56/K59 -> 0.32951254
B61: CEBOLLA MORADA LIMPIA | C61: g | D61: 60 | E61: 30 | F61: 85.714 | G61: =+VLOOKUP(Tabla1103453454455456479108109116[[#This Row],[Ingrediente]],Tabla34[#All],3,0) -> 3.8 | H61: =+Tabla1103453454455456479108109116[[#This Row],[Costo]]*Tabla1103453454455456479108109116[[#This Row],[Unidades]] -> 325.7132 | J61: GANANCIA | K61: =+K59-K56 -> 61461.351
B62: SAL REFISAL X 1000G | C62: g | D62: 2 | E62: 0 | F62: 2 | G62: =+VLOOKUP(Tabla1103453454455456479108109116[[#This Row],[Ingrediente]],Tabla34[#All],3,0) -> 2.6999076 | H62: =+Tabla1103453454455456479108109116[[#This Row],[Costo]]*Tabla1103453454455456479108109116[[#This Row],[Unidades]] -> 5.3998151 | J62: MARGEN PORCENTUAL | K62: =+K61/K56 -> 2.0347859
B63: AJINOMOTO X KILO | C63: g | D63: 2 | E63: 0 | F63: 2 | G63: =+VLOOKUP(Tabla1103453454455456479108109116[[#This Row],[Ingrediente]],Tabla34[#All],3,0) -> 20.111 | H63: =+Tabla1103453454455456479108109116[[#This Row],[Costo]]*Tabla1103453454455456479108109116[[#This Row],[Unidades]] -> 40.222
B64: PIMIENTA NEGRA MOLIDA BADIA 453GR | C64: g | D64: 2 | E64: 0 | F64: 2 | G64: =+VLOOKUP(Tabla1103453454455456479108109116[[#This Row],[Ingrediente]],Tabla34[#All],3,0) -> 94.613742 | H64: =+Tabla1103453454455456479108109116[[#This Row],[Costo]]*Tabla1103453454455456479108109116[[#This Row],[Unidades]] -> 189.22748
B65: PAPA CRIOLLA BALIN O CHIRIYA | C65: g | D65: 150 | E65: 10 | F65: 166.667 | G65: =+VLOOKUP(Tabla1103453454455456479108109116[[#This Row],[Ingrediente]],Tabla34[#All],3,0) -> 4.5 | H65: =+Tabla1103453454455456479108109116[[#This Row],[Costo]]*Tabla1103453454455456479108109116[[#This Row],[Unidades]] -> 750.0015
H66: =SUBTOTAL(109,Tabla1103453454455456479108109116[Total costo]) -> 28766.968
B69: TORNADO TRUFADO | J69: ANALISIS RECETA
B70: Ingrediente | C70: Und | D70: Unidades Netas | E70: % Merma | F70: Unidades | G70: Costo | H70: Total costo | J70: COSTO DEL PLATO | K70: =SUM(Tabla1103453454455456479108109117[Total costo]) -> 11004.881
B71: FILETE DE TILAPIA FRESCA LO | C71: g | D71: 90 | E71: 10 | F71: 100 | G71: =+VLOOKUP(Tabla1103453454455456479108109117[[#This Row],[Ingrediente]],Tabla34[#All],3,0) -> 37 | H71: =+Tabla1103453454455456479108109117[[#This Row],[Costo]]*Tabla1103453454455456479108109117[[#This Row],[Unidades]] -> 3700 | J71: MARGEN DE ERROR DEL 5% | K71: =+K70*5% -> 550.24407
B72: SUB. SALSA ANTICUCHERA | C72: g | D72: 10 | E72: 0 | F72: 10 | G72: =+VLOOKUP(Tabla1103453454455456479108109117[[#This Row],[Ingrediente]],Tabla34[#All],3,0) -> 18 | H72: =+Tabla1103453454455456479108109117[[#This Row],[Costo]]*Tabla1103453454455456479108109117[[#This Row],[Unidades]] -> 180 | J72: COSTO + MARGEN ERROR | K72: =+K70+K71 -> 11555.125
B73: AGUACATE CHOCKETTE X KILO | C73: g | D73: 30 | E73: 25 | F73: 40 | G73: =+VLOOKUP(Tabla1103453454455456479108109117[[#This Row],[Ingrediente]],Tabla34[#All],3,0) -> 14 | H73: =+Tabla1103453454455456479108109117[[#This Row],[Costo]]*Tabla1103453454455456479108109117[[#This Row],[Unidades]] -> 560 | J73: VALOR DE VENTA | K73: 42000
B74: SUB. SALSA TRUFADA CON AJI PANKA | C74: g | D74: 45 | E74: 0 | F74: 45 | G74: =+VLOOKUP(Tabla1103453454455456479108109117[[#This Row],[Ingrediente]],Tabla34[#All],3,0) -> 113.58939 | H74: =+Tabla1103453454455456479108109117[[#This Row],[Costo]]*Tabla1103453454455456479108109117[[#This Row],[Unidades]] -> 5111.5225 | J74: IPOCONSUMO | K74: =+K73/1.08*0.08 -> 3111.1111
B75: SUB. REMOLACHA CROCANTE | C75: g | D75: 5 | E75: 0 | F75: 5 | G75: =+VLOOKUP(Tabla1103453454455456479108109117[[#This Row],[Ingrediente]],Tabla34[#All],3,0) -> 8.4791597 | H75: =+Tabla1103453454455456479108109117[[#This Row],[Costo]]*Tabla1103453454455456479108109117[[#This Row],[Unidades]] -> 42.395798 | J75: VALOR ANTES DE IPO | K75: =+K73-K74 -> 38888.889
B76: BROTES DE RABANO 50 | C76: g | D76: 1 | E76: 0 | F76: 1 | G76: =+VLOOKUP(Tabla1103453454455456479108109117[[#This Row],[Ingrediente]],Tabla34[#All],3,0) -> 328.34 | H76: =+Tabla1103453454455456479108109117[[#This Row],[Costo]]*Tabla1103453454455456479108109117[[#This Row],[Unidades]] -> 328.34 | J76: MARGEN. | K76: =+K72/K75 -> 0.2971318
B77: QUESO PHILADELPHIA KRAFT 190GR | C77: g | D77: 30 | E77: 0 | F77: 30 | G77: =+VLOOKUP(Tabla1103453454455456479108109117[[#This Row],[Ingrediente]],Tabla34[#All],3,0) -> 28.148148 | H77: =+Tabla1103453454455456479108109117[[#This Row],[Costo]]*Tabla1103453454455456479108109117[[#This Row],[Unidades]] -> 844.44444 | J77: GANANCIA | K77: =+K75-K72 -> 27333.763
B78: SUB. CAMOTE GLASEADO | C78: g | D78: 20 | E78: 0 | F78: 20 | G78: =+VLOOKUP(Tabla1103453454455456479108109117[[#This Row],[Ingrediente]],Tabla34[#All],3,0) -> 11.90893 | H78: =+Tabla1103453454455456479108109117[[#This Row],[Costo]]*Tabla1103453454455456479108109117[[#This Row],[Unidades]] -> 238.1786 | J78: MARGEN PORCENTUAL | K78: =+K77/K72 -> 2.3655099
H79: =SUBTOTAL(109,Tabla1103453454455456479108109117[Total costo]) -> 11004.881
B82: SPRING ROLLS AJÃ DE GALLINA | J82: ANALISIS RECETA
B83: Ingrediente | C83: Und | D83: Unidades Netas | E83: % Merma | F83: Unidades | G83: Costo | H83: Total costo | J83: COSTO DEL PLATO | K83: =SUM(Tabla1103453454455456479108109117119120[Total costo]) -> 9600.606
B84: SUB. SPRING ROLLS AJI DEGALLINA | C84: uds | D84: 3 | E84: 0 | F84: 3 | G84: =+VLOOKUP(Tabla1103453454455456479108109117119120[[#This Row],[Ingrediente]],Tabla34[#All],3,0) -> 1768.5014 | H84: =+Tabla1103453454455456479108109117119120[[#This Row],[Costo]]*Tabla1103453454455456479108109117119120[[#This Row],[Unidades]] -> 5305.5043 | J84: MARGEN DE ERROR DEL 5% | K84: =+K83*5% -> 480.0303
B85: BROTES DE RABANO 50 | C85: g | D85: 1 | E85: 0 | F85: 1 | G85: =+VLOOKUP(Tabla1103453454455456479108109117119120[[#This Row],[Ingrediente]],Tabla34[#All],3,0) -> 328.34 | H85: =+Tabla1103453454455456479108109117119120[[#This Row],[Costo]]*Tabla1103453454455456479108109117119120[[#This Row],[Unidades]] -> 328.34 | J85: COSTO + MARGEN ERROR | K85: =+K83+K84 -> 10080.636
B86: SUB. HUANCAINA | C86: g | D86: 30 | E86: 0 | F86: 30 | G86: =+VLOOKUP(Tabla1103453454455456479108109117119120[[#This Row],[Ingrediente]],Tabla34[#All],3,0) -> 12.253166 | H86: =+Tabla1103453454455456479108109117119120[[#This Row],[Costo]]*Tabla1103453454455456479108109117119120[[#This Row],[Unidades]] -> 367.59498 | J86: VALOR DE VENTA | K86: 32000
B87: TOGARASHI HACHI 300 GR | C87: g | D87: 1 | E87: 0 | F87: 1 | G87: =+VLOOKUP(Tabla1103453454455456479108109117119120[[#This Row],[Ingrediente]],Tabla34[#All],3,0) -> 99.166667 | H87: =+Tabla1103453454455456479108109117119120[[#This Row],[Costo]]*Tabla1103453454455456479108109117119120[[#This Row],[Unidades]] -> 99.166667 | J87: IPOCONSUMO | K87: =+K86/1.08*0.08 -> 2370.3704
B88: HOJA DE BIJAO | C88: uds | D88: 1 | E88: 0 | F88: 1 | G88: =+VLOOKUP(Tabla1103453454455456479108109117119120[[#This Row],[Ingrediente]],Tabla34[#All],3,0) -> 3500 | H88: =+Tabla1103453454455456479108109117119120[[#This Row],[Costo]]*Tabla1103453454455456479108109117119120[[#This Row],[Unidades]] -> 3500 | J88: VALOR ANTES DE IPO | K88: =+K86-K87 -> 29629.63
H89: =SUBTOTAL(109,Tabla1103453454455456479108109117119120[Total costo]) -> 9600.606 | J89: MARGEN. | K89: =+K85/K88 -> 0.34022147
J90: GANANCIA | K90: =+K88-K85 -> 19548.993
J91: MARGEN PORCENTUAL | K91: =+K90/K85 -> 1.9392619
B93: EMPANADAS ROCOTO | J93: ANALISIS RECETA
B94: Ingrediente | C94: Und | D94: Unidades Netas | E94: % Merma | F94: Unidades | G94: Costo | H94: Total costo | J94: COSTO DEL PLATO | K94: =+Tabla1103453454455456479108109117119120122[[#Totals],[Total costo]] -> 6996.0744
B95: SUB. EMPANADAS | C95: uds | D95: 3 | E95: 0 | F95: 3 | G95: =+VLOOKUP(Tabla1103453454455456479108109117119120122[[#This Row],[Ingrediente]],Tabla34[#All],3,0) -> 2050.0822 | H95: =+Tabla1103453454455456479108109117119120122[[#This Row],[Costo]]*Tabla1103453454455456479108109117119120122[[#This Row],[Unidades]] -> 6150.2465 | J95: MARGEN DE ERROR DEL 5% | K95: =+K94*5% -> 349.80372
B96: SUB. SALSA DE EMPANADAS | C96: g | D96: 30 | E96: 0 | F96: 30 | G96: =+VLOOKUP(Tabla1103453454455456479108109117119120122[[#This Row],[Ingrediente]],Tabla34[#All],3,0) -> 17.249597 | H96: =+Tabla1103453454455456479108109117119120122[[#This Row],[Costo]]*Tabla1103453454455456479108109117119120122[[#This Row],[Unidades]] -> 517.4879 | J96: COSTO + MARGEN ERROR | K96: =+K94+K95 -> 7345.8781
B97: BROTES DE RABANO 50 | C97: g | D97: 1 | E97: 0 | F97: 1 | G97: =+VLOOKUP(Tabla1103453454455456479108109117119120122[[#This Row],[Ingrediente]],Tabla34[#All],3,0) -> 328.34 | H97: =+Tabla1103453454455456479108109117119120122[[#This Row],[Costo]]*Tabla1103453454455456479108109117119120122[[#This Row],[Unidades]] -> 328.34 | J97: VALOR DE VENTA | K97: 45000
H98: =SUBTOTAL(109,Tabla1103453454455456479108109117119120122[Total costo]) -> 6996.0744 | J98: IPOCONSUMO | K98: =+K97/1.08*0.08 -> 3333.3333
J99: VALOR ANTES DE IPO | K99: =+K97-K98 -> 41666.667
J100: MARGEN. | K100: =+K96/K99 -> 0.17630107
J101: GANANCIA | K101: =+K99-K96 -> 34320.789
J102: MARGEN PORCENTUAL | K102: =+K101/K96 -> 4.6721152
B105: LANGOSTINOS CROCANTES | J105: ANALISIS RECETA
B106: Ingrediente | C106: Und | D106: Unidades Netas | E106: % Merma | F106: Unidades | G106: Costo | H106: Total costo | J106: COSTO DEL PLATO | K106: =SUM(Tabla1103453454455456479108109117119120123[Total costo]) -> 15610.633
B107: SUB. CREMA MELCOCHA (ROCOTO) | C107: g | D107: 30 | E107: 0 | F107: 30 | G107: =+VLOOKUP(Tabla1103453454455456479108109117119120123[[#This Row],[Ingrediente]],Tabla34[#All],3,0) -> 94.925893 | H107: =+Tabla1103453454455456479108109117119120123[[#This Row],[Costo]]*Tabla1103453454455456479108109117119120123[[#This Row],[Unidades]] -> 2847.7768 | J107: MARGEN DE ERROR DEL 5% | K107: =+K106*5% -> 780.53166
B108: SUB. LANGOSTINOS CROCANTES | C108: uds | D108: 5 | E108: 0 | F108: 5 | G108: =+VLOOKUP(Tabla1103453454455456479108109117119120123[[#This Row],[Ingrediente]],Tabla34[#All],3,0) -> 2037.858 | H108: =+Tabla1103453454455456479108109117119120123[[#This Row],[Costo]]*Tabla1103453454455456479108109117119120123[[#This Row],[Unidades]] -> 10189.29 | J108: COSTO + MARGEN ERROR | K108: =+K106+K107 -> 16391.165
B109: HOJA DE BIJAO | C109: uds | D109: 0.5 | E109: 0 | F109: 0.5 | G109: =+VLOOKUP(Tabla1103453454455456479108109117119120123[[#This Row],[Ingrediente]],Tabla34[#All],3,0) -> 3500 | H109: =+Tabla1103453454455456479108109117119120123[[#This Row],[Costo]]*Tabla1103453454455456479108109117119120123[[#This Row],[Unidades]] -> 1750 | J109: VALOR DE VENTA | K109: 59000
